Workbook

Sheet Summary
A1: MATARA OT RENOVATION - CONSOLIDATED BOQ & ENGINEER'S PRELIMINARY ESTIMATE – REV 7
A2: Updated with reviewed Electrical and Ancillary Works BOQs. Site Works, MVAC and Rainwater packages have been adjusted to remove identified overlaps. Original source sheets are retained where applicable for audit; reviewed package sheets govern this consolidated estimate.
A4: Package / Section | B4: Reviewed Direct / Base Amount (LKR) | C4: Contingency (LKR) | D4: VAT / Tax (LKR) | E4: Consolidated Total (LKR) | F4: Status / Review Note
A5: A. Site Works / Landscaping – REVIEWED | B5: ='Site Works - Reviewed'!J39 -> 8984311 | C5: ='Site Works - Reviewed'!J41 -> 898431.1 | D5: 0 | E5: ='Site Works - Reviewed'!J42 -> 9882742.1 | F5: Detailed Site Works re-totalled; clear duplicate items removed. Original source sheet retained.
A6: B. Modular Operating Theatre Package | B6: 1.4860536e+08 | C6: 14860536 | D6: 29423862 | E6: 1.9288976e+08 | F6: UNCHANGED specialist package; electrical interfaces reconciled against reviewed Electrical BOQ.
A7: C. Added Renovation Works incl. Equipment Relocation & MEP Strip-out | B7: ='Added Renovation BOQ'!G100 -> 76810177 | C7: 6252222.6 | D7: 12379401 | E7: 81153849 | F7: Existing preliminary renovation estimate retained.
A8: D. MVAC Works – REVIEWED | B8: ='MVAC BOQ & Estimate'!G31 -> 98100000 | C8: ='MVAC BOQ & Estimate'!#REF! -> #REF! | D8: 0 | E8: ='MVAC BOQ & Estimate'!#REF! -> #REF! | F8: Electrical allowance reduced because DB-AC and power feeders/cables are now in Electrical BOQ.
A9: E. Medical Gas System | B9: ='Medical Gas BOQ & Estimate'!G30 -> 40525000 | C9: ='Medical Gas BOQ & Estimate'!#REF! -> #REF! | D9: 0 | E9: ='Medical Gas BOQ & Estimate'!#REF! -> #REF! | F9: Preliminary specialist estimate; Modular OT terminal hardware excluded.
A10: F. Water Supply System | B10: ='Water Supply BOQ & Estimate'!G32 -> 7038560 | C10: ='Water Supply BOQ & Estimate'!#REF! -> #REF! | D10: 0 | E10: ='Water Supply BOQ & Estimate'!#REF! -> #REF! | F10: Preliminary specialist estimate; sanitary fixtures excluded where already measured.
A11: G. Wastewater & Sewerage System | B11: ='Wastewater & Sewer BOQ'!G30 -> 5632000 | C11: ='Wastewater & Sewer BOQ'!G32 -> 563200 | D11: 0 | E11: ='Wastewater & Sewer BOQ'!G33 -> 6195200 | F11: Preliminary specialist estimate; foul drainage only.
A12: H. Rainwater Disposal System – REVIEWED | B12: ='Rainwater Disposal BOQ'!G24 -> 3479000 | C12: ='Rainwater Disposal BOQ'!#REF! -> #REF! | D12: 0 | E12: ='Rainwater Disposal BOQ'!#REF! -> #REF! | F12: Courtyard diversion retained; general roof gutters/downpipes removed because Ancillary Roof BOQ includes them.
A13: I. Electrical Installation – REVIEWED | B13: ='Electrical BOQ - Reviewed'!K54 -> 18731600 | C13: ='Electrical BOQ - Reviewed'!K56 -> 1873160 | D13: 0 | E13: ='Electrical BOQ - Reviewed'!K57 -> 20604760 | F13: Source LKR 21.0396m less LKR 2.308m identified Modular OT overlaps.
A14: J. Ancillary Buildings & Extension – REVIEWED | B14: ='Ancillary Works - Reviewed'!H65 -> 15503821 | D14: 0 | F14: Detailed source line items used; stale subtotals and roof amount errors corrected in reviewed sheet.
A16: PROJECT TOTAL | B16: =SUM(B5:B14) -> 4.2340983e+08 | D16: =SUM(D5:D14) -> 41803262 | F16: VAT/tax is carried only where already included in the earlier Modular OT and Added Renovation package estimates; newly reviewed/additional packages are shown excluding VAT.
A18: Key Consolidation Controls / Findings | B18: Value | D18: Source / Cross-check | E18: Reference | F18: Consolidation Treatment
A19: Electrical source subtotal | B19: LKR 21,039,600 | D19: Uploaded Mathara Hospital BOQ(1).xls | E19: Electrical source | F19: Reviewed line by line
A20: Electrical duplicate deduction | B20: LKR 2,308,000 | D20: Modular OT C6/E2 vs Electrical lighting/socket quantities | E20: Electrical Reconciliation | F20: 40 OT lights/points and 80 OT sockets removed from Electrical
A21: MVAC electrical overlap | B21: LKR 4,000,000 direct reduction | D21: Electrical DB-AC/cables now detailed in source Electrical BOQ | E21: MVAC E2 | F21: MVAC E2 reduced from LKR 5.0m to LKR 1.0m interface-only
A22: Site Works source detailed direct subtotal | B22: LKR 9,176,793 | D22: Site Works - Unchanged | E22: Detailed rows | F22: Old consolidated Summary had been carrying an outdated lower source amount
A23: Site Works reviewed direct subtotal | B23: LKR 8,984,311 | D23: Site Works - Reviewed | E23: Duplicate removal register | F23: Canopy roof, hardstanding overlap, excess disposal and duplicate landscape maintenance adjusted
A24: Ancillary reviewed direct subtotal | B24: ='Ancillary Works - Reviewed'!#REF! -> #REF! | D24: Uploaded BOQ_Ancilary Building and extension.xlsx | E24: Ancillary Works - Reviewed | F24: Detailed line items govern; stale summary ignored
A25: Ancillary roof schedule | B25: Qty × Rate recalculated | D25: Source Sheet1 | E25: R.02-R.15 | F25: Stored amounts were inconsistent with current displayed quantities/rates
A26: Rainwater roof drainage overlap | B26: LKR 357,000 direct removed | D26: Ancillary Roof R.08-R.12 vs Rainwater D1-D4 | E26: Rainwater Reconciliation | F26: Courtyard diversion remains; general roof drainage governed by Ancillary BOQ
A27: Estimate status | B27: Preliminary / Budgetary | D27: All reviewed packages | E27: Rev 7 | F27: Final tender requires coordinated drawings, remeasurement and supplier quotations for specialist items

Sheet Added Renovation BOQ
A1: ADDED PREPARATORY / DEMOLITION / CIVIL RENOVATION BOQ & ESTIMATE
A2: Project: Improvement to MEP Services and Renovation of Theatre Complex at District General Hospital Matara | I2: Contingency | J2: 0.1
A3: Section | B3: Item No. | C3: Description | D3: Unit | E3: Qty | F3: Rate (LKR) | G3: Amount (LKR) | H3: Rate Type | I3: Rate Ref. | J3: Drawing / Basis | K3: Remarks / Qualification
A4: A - Preparatory / Enabling Works
A5: A | B5: A1 | C5: Prepare renovation phasing, infection-control/dust/noise control plans, permits, demolition method statements and coordination submissions for work in/adjacent to the occupied hospital. | D5: LS | E5: 1 | F5: 150000 | G5: =E5*F5 -> 150000 | H5: Engineer PS | I5: PS-A1 | J5: Hospital renovation / ICRA basis | K5: Excludes specialist OT validation already in modular package.
A6: A | B6: A2 | C6: Provide and maintain dust-tight temporary partitions/hoardings, zipped/controlled access, local negative-air/dust extraction arrangements and sealed interfaces as required for phased internal demolition. | D6: LS | E6: 1 | F6: 500000 | G6: =E6*F6 -> 500000 | H6: Engineer PS | I6: PS-A2 | J6: Hospital operational constraint | K6: Final arrangement to infection-control approval; power to temporary equipment by relevant trade.
A7: A | B7: A3 | C7: Protect retained floors, walls, doors, lifts, adjacent equipment and operational routes; provide temporary floor/wall protection and reinstate after completion. | D7: LS | E7: 1 | F7: 50000 | G7: =E7*F7 -> 50000 | H7: Engineer PS | I7: PS-A3 | J7: Existing plans / hospital constraint | K7: Protection for internal renovation only; site-work protection remains in unchanged Site Works BOQ.
A8: A | B8: A4 | C8: Detailed measured survey, setting-out, service detection/scanning and marking of existing structure/services before demolition; maintain survey records and coordinate revised shop drawings. | D8: LS | E8: 1 | F8: 450000 | G8: =E8*F8 -> 450000 | H8: Engineer PS | I8: PS-A4 | J8: Drawings 004/005/006/007 | K8: Includes verification of slab/beam positions and service routes before cutting.
A9: A | B9: A5 | C9: Temporary internal debris route, controlled material handling, daily hospital-sensitive housekeeping and progressive cleaning during demolition and civil works. | D9: LS | E9: 1 | F9: 600000 | G9: =E9*F9 -> 600000 | H9: Engineer PS | I9: PS-A5 | J9: Hospital operational constraint | K9: Separate from final terminal clean.
A10: A | B10: A6 | C10: Prepare existing structural slab/substrate in four OTs and scrub rooms by inspection, grinding and local patch repair before modular flooring installation; exclude self-levelling screed, conductive vinyl, copper grid and coving included in unchanged Modular OT BOQ. | D10: m² | E10: 220 | F10: 1500 | G10: =E10*F10 -> 330000 | H10: Engineer PS | I10: PS-A6 | J10: OT + scrub measured area ≈219.989 m² | K10: Only substrate repair/preparation prior to specialist modular flooring.
A11: A | B11: A7 | C11: Prepare structural slab/wall interfaces for modular OT support fixings: survey/mark anchors, remove loose finishes and locally repair concrete; exclude modular secondary steel/support frames and specialist penetrations already in modular package. | D11: LS | E11: 1 | F11: 500000 | G11: =E11*F11 -> 500000 | H11: Engineer PS | I11: PS-A7 | J11: Modular OT interface | K11: No double payment for modular support frames.
A12: A | B12: A8 | C12: Final pre-installation builders' clean and dust removal of OT/scrub structural shell immediately before specialist modular theatre installation. | D12: LS | E12: 1 | F12: 400000 | G12: =E12*F12 -> 400000 | H12: Engineer PS | I12: PS-A8 | J12: Modular OT preparatory work | K12: Not the final cleanroom/OT validation or terminal clean.
A13: Subtotal - A - Preparatory / Enabling Works | G13: =SUM(G5:G12) -> 2980000
A14: B - Demolition & Strip-out
A15: B | B15: B1 | C15: Carefully dismantle existing aluminium door/window assemblies including frames, glazing and fittings; stack reusable materials and make good disturbed jambs/sills. | D15: m² | E15: 220 | F15: 405 | G15: =E15*F15 -> 89100 | H15: Matara BSR 2026 | I15: DM41 | J15: Drawing 006 / existing openings | K15: Preliminary combined area; remeasure by opening schedule.
A16: B | B16: B2 | C16: Carefully remove aluminium glazed partition / curtain-wall type assemblies including mullions, transoms, glazing and sealants; stack/dispose as directed and make good fixing locations. | D16: m² | E16: 70 | F16: 369 | G16: =E16*F16 -> 25830 | H16: Matara BSR 2026 - qualified | I16: DM43 | J16: Drawing 006 | K16: Closest BSR proxy for aluminium partition removal; specialist glass handling may require adjustment.
B17: B3 | C17: Carefully dismantle existing wooden door including frames, slashes ,glazing and fittings; stack reusable materials and make good disturbed jambs/sills. | D17: m2 | E17: 60 | F17: =1000 -> 1000 | G17: =E17*F17 -> 60000
A18: B | B18: B4 | C18: Demolish non-load-bearing brick/block partition walls including finishes; controlled cutting, dust suppression, protection of structure/services and clearing debris. | D18: m³ | E18: 70 | F18: 2000 | G18: =E18*F18 -> 140000 | H18: Matara BSR 2026 - qualified | I18: DM08 | J18: Drawing 006 red demolition | K18: Quantity assumes predominantly 100/150 mm partitions; verify wall thicknesses.
A19: B | B19: B5 | C19: Demolish any load-bearing masonry only where specifically instructed after structural approval, including controlled sequence; masonry demolition rate only. | D19: m³ | E19: 10 | F19: 2000 | G19: =E19*F19 -> 20000 | H19: Matara BSR 2026 - qualified | I19: DM08 | J19: Drawing 005/006 | K19: ZERO provisional quantity. Temporary propping/needling priced separately under C7.
A20: B | B20: B6 | C20: Remove existing floor tiles and tile-bed/screed finishes to areas receiving new finishes, protect structural slab and prepare exposed surface. | D20: m² | E20: 800 | F20: 770 | G20: =E20*F20 -> 616000 | H20: Matara BSR 2026 | I20: DM19 | J20: Drawings 006/007 + finish renewal allowance | K20: Preliminary internal renovation floor-strip area.
B21: B7 | C21: Cut /remove existing floor concrete without damaging the reinforcement if any; up to a maximum of 150mm depth for wall foundation rate to included removal of debris | D21: m3 | E21: 2 | F21: 30000 | G21: =E21*F21 -> 60000 | H21: Engineer PS
A22: B | B22: B8 | C22: Carefully dismantle and remove existing lightweight canopy roof covering, including corrugated roofing sheets, frames, ridge/flashing pieces, gutters where affected, screws, bolts and other fixings; lower materials safely, segregate reusable materials if directed, load and transport debris to an approved disposal location, complete. | D22: m² | E22: 45 | F22: 650 | G22: =E22*F22 -> 29250 | H22: Derived from BSR | I22: PS-B6 | J22: Drawing 009 ceiling layout | K22: MEP disconnection/removal above ceilings is measured separately under Section I; protect all live services to remain.
B23: B9 | C23: Carefully remove existing timber trolley/wall guard fixed to walls, including removal of timber sections, brackets, screws, nails and other fixings; cutting where necessary; making good minor holes/damaged plaster surfaces caused by removal; lowering, loading, transporting and disposing of debris/materials to an approved disposal location, complete as directed by the Engineer. | D23: m | E23: 50 | F23: 690 | G23: =E23*F23 -> 34500
A24: B | B24: B10 | C24: Remove existing wall tiles, splashbacks and bonded wall finishes where required for new wet-area/hygienic finishes, including surface preparation. | D24: m² | E24: 200 | F24: 650 | G24: =E24*F24 -> 130000 | H24: Engineer PS | I24: PS-B7 | J24: Wet rooms / equipment washing / accessible WC | K24: Actual finish build-up to be verified before demolition.
A25: B | B25: B11 | C25: Carefully remove existing sanitary fixtures, counters and minor fixed non-medical fittings affected by renovation; cap openings by relevant MEP trade and store/dispose as directed. | D25: Nr | E25: 15 | F25: 6500 | G25: =E25*F25 -> 97500 | H25: Engineer PS | I25: PS-B8 | J25: Room layout / wet areas | K25: Medical equipment relocation is measured separately under Section I; sanitary fixture removal remains under this item.
B26: B12 | C26: Demolishing reinforced cement concrete in suspended floors up to 100mm-150mm thick , removing reinforcement and clearing debris. | D26: m3 | E26: 20 | F26: 22344 | G26: =E26*F26 -> 446880
B27: B13 | C27: Demolishing cement concrete and clearing debris in floors from 100mm to 150mm thick floors. | D27: m3 | E27: 40 | F27: 10209 | G27: =E27*F27 -> 408360
A28: B | B28: B14 | C28: Load, cart and dispose demolition/strip-out debris by tractor trailer to approved disposal point up to 3 km, including fees/attendance. | D28: Load | E28: 45 | F28: 4207 | G28: =E28*F28 -> 189315 | H28: Existing Site BOQ BSR | I28: B40 | J28: Disposal allowance | K28: Preliminary load count; hazardous material disposal excluded.
A29: Subtotal - B - Demolition & Strip-out | G29: =SUM(G15:G28) -> 2346735
A30: C - Structural / Builders' Work
A31: C | B31: C1 | C31: Saw-cut and form new openings in non-load-bearing walls for doors, transfer openings and coordinated services; provide neat edges and making good. | D31: m2 | E31: 75 | F31: 5000 | G31: =E31*F31 -> 375000 | H31: Engineer PS | I31: PS-C1 | J31: Drawings 007/008 | K31: Excludes structural beam/slab openings unless Engineer-approved.
A32: C | B32: C2 | C32: Grade 25 concrete to local slab infills, upstands, small equipment plinths, thresholds and builders-work bases; reinforcement/formwork separate. | D32: m³ | E32: 12 | F32: 32300 | G32: =E32*F32 -> 387600 | H32: Matara BSR 2026 | I32: CT54 | J32: New construction / local making good | K32: Final member sizes/details to Engineer approval.
B33: C3 | C33: Grade 25 concrete to stiffner columns; reinforcement/formwork separate. | D33: m³ | E33: 3 | F33: 34300 | G33: =E33*F33 -> 102900
A34: C | B34: C4 | C34: High-yield/mild steel reinforcement to local concrete works, cut, bend and fix including binding wire. | D34: kg | E34: 1500 | F34: 494 | G34: =E34*F34 -> 741000 | H34: Matara BSR 2026 - qualified | I34: RF02 | J34: Local structural works | K34: Split by bar grade/level if final BSR requires.
A35: C | B35: C5 | C35: Plywood formwork to local beams, trimming/upstands/plinths and concrete repairs, including props, ties and striking. | D35: m² | E35: 50 | F35: 4070 | G35: =E35*F35 -> 203500 | H35: Matara BSR 2026 - qualified | I35: FW19 | J35: Local structural works | K35: Budgetary proxy; final formwork category to actual member.
A36: C | B36: C6 | C36: Pre-cast lintels size 225 mm × 225 mm deep in Grade 25 concrete, reinforced with 4 nos. of 12mm dia. tor steel bars and 6mm mild steel stirrups @ 150mm c/c, including necessary formwork on the ground floor. | D36: m | E36: 45 | F36: 5650 | G36: =E36*F36 -> 254250 | H36: Derived Matara BSR 2026 | I36: DER-L100 | J36: New door openings | K36: Final lintel size/reinforcement to approved details.
A37: C | B37: C7 | C37: Pre-cast lintels size 225 mm × 150 mm deep in Grade 25 concrete, reinforced with 4 nos. of 10 mm dia. tor steel bars and 6mm mild steel stirrups @ 150mm c/c, including necessary formwork on the ground floor. | D37: m | E37: 12 | F37: 3800 | G37: =E37*F37 -> 45600 | H37: Derived Matara BSR 2026 | I37: DER-L150 | J37: New door openings | K37: Final lintel size/reinforcement to approved details.
A38: C | B38: C8 | C38: Pre-cast lintels size 150 mm × 150 mm deep in Grade 25 concrete, reinforced with 4 nos. of 10 mm dia. tor steel bars and 6mm mild steel stirrups @ 150mm c/c, including necessary formwork on the ground floor. | D38: m | E38: 14 | F38: =F37/225*150 -> 2533.3333 | G38: =E38*F38 -> 35466.667 | H38: Derived Matara BSR 2026 | I38: DER-L150 | J38: New door openings | K38: Final lintel size/reinforcement to approved details.
A39: C | B39: C9 | C39: Temporary shoring, propping and needling for any Engineer-approved structural/load-bearing alteration, complete with design/method statement and removal after permanent works. | D39: LS | E39: 1 | F39: 1500000 | G39: =E39*F39 -> 1500000 | H39: Engineer PS | I39: PS-C7 | J39: Structural safety allowance | K39: Provisional; use only where structural Engineer confirms need.
A40: C | B40: C10 | C40: Core drilling / controlled builders-work openings in retained masonry/RCC for coordinated non-modular services and civil interfaces, including making good after installation. | D40: LS | E40: 1 | F40: 600000 | G40: =E40*F40 -> 600000 | H40: Engineer PS | I40: PS-C8 | J40: Coordination allowance | K40: Specialist structural approval required for RCC openings.
A41: C | B41: C11 | C41: Fire-stop and seal non-modular builders-work penetrations/openings after MEP installation, including approved collars/mortar/sealant and cleanable finishing. | D41: LS | E41: 1 | F41: 800000 | G41: =E41*F41 -> 800000 | H41: Engineer PS | I41: PS-C9 | J41: Non-modular areas | K41: OT modular envelope penetration seals remain in specialist package.
A42: C | B42: C12 | C42: Crack repair, spalled concrete repair, edge repair and local restoration of retained walls/slabs/columns uncovered during demolition. | D42: LS | E42: 1 | F42: 750000 | G42: =E42*F42 -> 750000 | H42: Engineer PS | I42: PS-C10 | J42: Existing building condition allowance | K42: Use approved repair method/material after exposing substrate.
A43: Subtotal - C - Structural / Builders' Work | G43: =SUM(G31:G42) -> 5795316.7
A44: D - Masonry & Plastering
A45: D | B45: D1 | C45: 4" thick cement sand solid block wall (blocks confirming to S.L.S.855 and subject to the approval of sample blocks) in cement and sand mortar 1:5 in ground floor. | D45: m² | E45: 100 | F45: 4190 | G45: =E45*F45 -> 419000 | H45: Matara BSR 2026 | I45: CB01 | J45: Drawing 007 new partitions | K45: Non-load-bearing only.
A46: D | B46: D2 | C46: 6" thick cement sand solid block wall (blocks confirming to S.L.S. 855 and subject to the approval of sample blocks) in cement and sand mortar 1:5 in ground floor. | D46: m² | E46: 550 | F46: 5890 | G46: =E46*F46 -> 3239500 | H46: BSR | I46: DER-CB6 | J46: Drawing 007 new partitions | K46: Derived from 100 mm BSR rate; confirm approval.
A47: D | B47: D3 | C47: 225 mm brickwork in 1:5 cement:sand mortar for local walls/infill where shown or instructed. | D47: m³ | E47: 35 | F47: 42000 | G47: =E47*F47 -> 1470000 | H47: Matara BSR 2026 | I47: BK01 | J47: Local infill allowance | K47: Use only where 225 mm masonry is actually required.
A48: D | B48: D4 | C48: Plastering 5/8" thick to walls in cement and sand 1:5 finished semi-rough. | D48: m² | E48: 960 | F48: 2357 | G48: =E48*F48 -> 2262720 | H48: Derived Matara BSR 2026 | I48: DER-PLSKIM | J48: New wall faces | K48: Area equals preliminary new-wall faces including allowance for reveals.
A49: D | B49: D5 | C49: 10 mm cement:sand 1:3 plaster repair to RCC soffits, beams and column faces after ceiling/partition alterations. | D49: m² | E49: 300 | F49: 1740 | G49: =E49*F49 -> 522000 | H49: Matara BSR 2026 - qualified | I49: PL02 | J49: Existing RCC surfaces | K49: Includes preparation and curing; workability enhancer subject to approval.
A50: D | B50: D6 | C50: Patch plaster/make good existing wall surfaces after demolition, chased services and door/frame removals; finish smooth to match adjacent surfaces. | D50: m² | E50: 500 | F50: 2357 | G50: =E50*F50 -> 1178500 | H50: Derived Matara BSR 2026 | I50: DER-PLSKIM | J50: Renovation making-good allowance | K50: Actual patch area to be jointly measured.
A51: Subtotal - D - Masonry & Plastering | G51: =SUM(G45:G50) -> 9091720
A52: E - Architectural Finishes
A53: E | B53: E1 | C53: Hospital-grade non-conductive welded clinical vinyl sheet flooring with coved skirting to recovery, sterile/semi-clean and other clinical support areas outside the unchanged modular OT floor scope. | D53: m² | E53: 240 | F53: 13500 | G53: =E53*F53 -> 3240000 | H53: Market benchmark | I53: MOD-R2 derived | J53: Room types / Employer Requirements | K53: Same budgetary installed level used for modular scrub clinical vinyl; confirm supplier quote.
A54: E | B54: E2 | C54: 600x600 mm glazed/homogeneous ceramic floor tiles to general staff, public/support rooms including 20 mm 1:3 screed bedding and grout. | D54: m² | E54: 500 | F54: 5782.31 | G54: =E54*F54 -> 2891155 | H54: NWSDB 2025 +27% | I54: T1.9.1.1 | J54: General non-clinical/support areas | K54: Based on Indian/Chinese glazed tile basic LKR 4,553/m² x 1.27; final finish selection to room data.
A55: E | B55: E3 | C55: 600x600 mm homogeneous matt/non-slip ceramic floor tiles to toilets, wet rooms and changing wet areas including screed bedding and grout. | D55: m² | E55: 90 | F55: 5746.75 | G55: =E55*F55 -> 517207.5 | H55: NWSDB 2025 +27% | I55: T1.9.1.1 | J55: Accessible toilet / wet areas | K55: Based on homogeneous matt basic LKR 4,525/m² x 1.27.
A56: E | B56: E4 | C56: 300x600 mm glazed ceramic wall tiles to toilets, equipment-washing splash zones and wet-area walls including bedding and grout. | D56: m² | E56: 220 | F56: 6393.18 | G56: =E56*F56 -> 1406499.6 | H56: NWSDB 2025 +27% | I56: T2.13.2 | J56: Wet-area wall finishes | K56: Basic LKR 5,034/m² x 1.27; final height/extents to drawings.
A57: E | B57: E5 | C57: Supply and install proprietary aluminium clip-in suspended ceiling system to all designated internal areas excluding Operating Theatres, comprising minimum 0.70 mm thick, 600 × 600 mm aluminium clip-in ceiling panels, plain or perforated as approved, with minimum 80-micron factory-applied high-quality polyester/epoxy powder-coated finish, colour as selected by the Engineer, complete with proprietary concealed clip-in carrier system, hot-dip galvanised suspension members, carrier channels, adjustable hangers/4 mm diameter hanger rods, approved soffit anchors, perimeter aluminium/GI trims and angles, hold-down clips where required and all necessary fixing accessories. Rate shall include setting out to coordinated ceiling modules, levelling, cutting and forming panels around columns and walls, trimming and openings for light fittings, air-conditioning diffusers/grilles, sprinklers, detectors, speakers, medical/ELV services and other ceiling-mounted installations, strengthening/support around openings where required, removable panels for access to services, making good, protection and cleaning on completion, and all labour, materials, plant and accessories necessary to provide a complete ceiling system in accordance with approved shop drawings, manufacturer's recommendations and Engineer's approval. Panels in clinical/wet/hygiene-sensitive areas shall be non-corrosive, non-shedding, washable and resistant to normal hospital cleaning/disinfection agents. Operating Theatre modular/hygienic ceilings are excluded and measured separately. | D57: m² | E57: 750 | F57: =24952*1.1 -> 27447.2 | G57: =E57*F57 -> 20585400 | H57: BSR-2024-U773 | I57: T2.14.2 | J57: Drawing 009 CF-01 / non-OT areas | K57: Basic LKR 5,920/m² x 1.27; use cleanable healthcare-suitable product.
A58: E | B58: E7 | C58: Prepare plastered internal walls and apply one coat filler and two coats approved washable low-VOC emulsion paint to specified colour. | D58: m² | E58: 1900 | F58: 1126.49 | G58: =E58*F58 -> 2140331 | H58: NWSDB 2025 +27% | I58: V.1.1.1.1 | J58: Non-OT painted walls | K58: Basic LKR 887/m² x 1.27.
A59: E | B59: E8 | C59: Prepare and paint sides/soffits of slabs and beams with filler and two coats approved emulsion paint. | D59: m² | E59: 300 | F59: 1336.04 | G59: =E59*F59 -> 400812 | H59: NWSDB 2025 +27% | I59: V.1.1.1.1 | J59: Exposed soffits/beams | K59: Basic LKR 1,052/m² x 1.27.
A60: E | B60: E9 | C60: Waterproofing to toilet/equipment-washing wet floors and local upstands, including surface preparation, detailing and flood/pond test where practical. | D60: m² | E60: 90 | F60: 5500 | G60: =E60*F60 -> 495000 | H60: Engineer PS | I60: PS-E9 | J60: Wet rooms | K60: Specialist system/quotation to be approved.
A61: E | B61: E10 | C61: Hospital corridor trolley/bumper guard to walls, complete with rails, brackets, end caps, corners and fixings. | D61: m | E61: 120 | F61: 5000 | G61: =E61*F61 -> 600000 | H61: Engineer PS | I61: PS-E10 | J61: Drawing 010 trolley/corner guard | K61: Final material/profile/height to approved detail.
A62: E | B62: E11 | C62: Heavy-duty corner guards to exposed wall/column corners in trolley routes. | D62: Nr | E62: 40 | F62: 6000 | G62: =E62*F62 -> 240000 | H62: Engineer PS | I62: PS-E11 | J62: Drawing 010 trolley/corner guard | K62: Final count/profile by site measurement.
A63: E | B63: E12 | C63: Transition strips, thresholds, sealants, movement-joint trims and minor finish accessories between new finishes and retained/modular finishes. | D63: LS | E63: 1 | F63: 500000 | G63: =E63*F63 -> 500000 | H63: Engineer PS | I63: PS-E12 | J63: Interface allowance | K63: Avoid duplication with modular specialist coves/trims inside modular OT scope.
A64: Subtotal - E - Architectural Finishes | G64: =SUM(G53:G63) -> 33016405
A65: F - Doors, Glazing & Fixed Joinery
A66: F | B66: F1 | C66: 1500 mm × 2200 mm Double-Leaf, Double-Action Swing Door for Corridors Provide and install a 1500 mm wide × 2200 mm high double-leaf swing door, comprising two equal 750 mm leaves, capable of opening in both directions. Door leaves shall have a rigid, impact-resistant core with smooth, non-porous hygienic finishes on both sides, resistant to hospital cleaning agents and disinfectants. Provide a heavy-duty stainless-steel or aluminium frame, double-action floor springs or pivot hinges, flush vision panels of laminated safety glass, stainless-steel push plates, kick plates and edge protection. The door shall close smoothly and quietly, have a flush threshold suitable for beds and trolleys, and include all seals, ironmongery, reinforcement, accessories and making good necessary for a complete installation. | D66: Nr | E66: 10 | F66: 220000 | G66: =E66*F66 -> 2200000 | H66: Engineer PS / market allowance | I66: PS-F1 | J66: Drawing 008: 62 door tags less 8 modular OT doors | K66: Door type schedule not provided; remeasure and split single/double/fire/acoustic doors before tender.
B67: F2 | C67: 1500 mm × 2200 mm Door Within Curtain Wall Provide and install a 1500 mm wide × 2200 mm high, double-leaf, single-action swing door integrated with the curtain-wall system. Provide powder-coated aluminium door leaves and frame matching the curtain-wall finish, glazed with laminated safety glass of the required thickness. Each leaf shall open in one direction only and operate on heavy-duty pivots or hinges. Include concealed door closers, stainless-steel pull/push handles, locks, door stops, weather seals, gaskets, threshold, flashings, perimeter sealant and all necessary ironmongery. Reinforce and securely anchor the surrounding curtain-wall framing to withstand door-operation loads. Complete the installation weathertight, smoothly operating and in accordance with the approved shop drawings. | E67: 6 | F67: 210000 | G67: =E67*F67 -> 1260000
B68: F3 | C68: 1000 mm × 2200 mm Single-Leaf Door with Vision Panel Provide and install a 1000 mm wide × 2200 mm high single-leaf, single-action swing door. The door shall have a rigid, impact-resistant core with smooth, non-porous hygienic finishes on both sides, suitable for regular cleaning with hospital-grade disinfectants. Provide a flush, hermetically sealed vision panel, approximately 250 mm × 350 mm, glazed with double-laminated safety glass. Include a stainless-steel or aluminium frame, heavy-duty hinges, lever handles, lockset, door closer, door stop, kick plates, seals, flush threshold and all necessary ironmongery and accessories. The door shall operate smoothly, close quietly and permit safe passage of wheelchairs and equipment. | E68: 15 | F68: 155000 | G68: =E68*F68 -> 2325000
B69: F4 | C69: 750 mm × 2200 mm Door for Bathroom and Changing Room Provide and install a 750 mm wide × 2200 mm high single-leaf, single-action swing door. The door shall have a moisture-resistant solid core with smooth, non-porous and easily cleanable finishes on both sides, suitable for humid hospital bathroom and changing-room conditions. Provide a corrosion-resistant frame, stainless-steel hinges and lever handles, privacy lock with external emergency release, door stop, rubber seals and all necessary ironmongery. The door shall open outwards where required for emergency access and include a minimum 300 mm high stainless-steel kick plate and an undercut or transfer grille where required for ventilation. | E69: 8 | F69: 120000 | G69: =E69*F69 -> 960000
B70: F5 | C70: Accessible-Toilet Door Provide and install a single-leaf door, minimum 1000 mm nominal width × 2200 mm height, arranged to provide at least 900 mm clear opening when the door is fully open. The door shall open outward into the circulation space, without obstructing the accessible route, or shall be a compliant sliding door where shown. Provide a moisture-resistant solid core with smooth, non-porous and easily cleanable finishes on both sides. Equip the door with corrosion-resistant hinges, an easy-grip lever handle, and a privacy lock operable with one hand without tight grasping or twisting. The lock shall incorporate an occupied/vacant indicator and allow emergency release from outside. Provide and install a 750 mm wide × 2200 mm high single-leaf, single-action swing door. The door shall have a moisture-resistant solid core with smooth, non-porous and easily cleanable finishes on both sides, suitable for humid hospital bathroom and changing-room conditions. Provide a corrosion-resistant frame, stainless-steel hinges and lever handles, privacy lock with external emergency release, door stop, rubber seals and all necessary ironmongery. The door shall open outwards where required for emergency access and include a minimum 300 mm high stainless-steel kick plate and an undercut or transfer grille where required for ventilation. | E70: 1 | F70: 180000 | G70: =E70*F70 -> 180000
B71: F6 | C71: 500 mm × 2200 mm Double-Leaf Door Provide and install a 1500 mm wide × 2200 mm high double-leaf, single-action steel door to the HVAC technical room. The door shall comprise one active leaf and one inactive leaf, sized to permit the installation, removal and maintenance of the largest equipment. Provide heavy-duty galvanized-steel leaves and frame with corrosion-resistant powder-coated finish, internal reinforcement and suitable acoustic insulation. Equip the active leaf with a heavy-duty lever handle, mortice lock and door closer, and the inactive leaf with concealed top and bottom flush bolts. Include stainless-steel hinges, door stops, seals, kick plates, hold-open devices where permitted, and all necessary ironmongery. The doors shall open outward where required by the approved fire and escape strategy. Provide weatherproof ventilation louvers with insect mesh only where indicated by the HVAC design. The complete door assembly, including frame, hardware, seals, louvers and glazing where applicable, shall achieve the fire rating required for the enclosing wall and comply with the approved fire-safety requirements. | E71: 3 | F71: 195000 | G71: =E71*F71 -> 585000
A72: F | B72: F7 | C72: Aluminium-Glazed Curtain Wall Design, fabricate, supply and install a complete aluminium-framed glazed curtain-wall system of approved profile, configuration and colour, comprising powder-coated or anodised aluminium mullions, transoms, pressure plates, cover caps and all required internal reinforcement. Include approved performance glazing, spandrel panels where indicated, thermal and acoustic insulation, vapour barriers, flashings, copings, closures, perimeter trims, EPDM gaskets, setting blocks, backing rods, structural and weather-grade silicone sealants, anchors, brackets, fasteners and all accessories. The system shall be securely connected to the building structure and designed to accommodate structural movement, thermal expansion and specified wind loads. Provide complete air- and watertight construction, controlled drainage and condensation discharge. Include interfaces with adjacent walls, roofs, floors, doors and windows; all necessary cutting, forming, protection, testing, cleaning and making good; and preparation of shop drawings and calculations. | D72: m2 | E72: 120 | F72: 45000 | G72: =E72*F72 -> 5400000 | H72: Engineer PS | I72: PS-F3 | J72: Room layout RN-20/RN-25/support rooms | K72: Loose furniture excluded.
A73: Subtotal - F - Doors, Glazing & Fixed Joinery | G73: =SUM(G66:G72) -> 12910000
A74: G - Sanitary / Fixed Architectural Fittings
A75: G | B75: G1 | C75: Accessible toilet fixture and accessory package: WC, wash-hand basin, grab rails, mirror, dispensers and minor accessories; exclude electrical emergency-call wiring and main pipework. | D75: Set | E75: 1 | F75: 450000 | G75: =E75*F75 -> 450000 | H75: Engineer PS | I75: PS-G1 | J75: RN-27 Accessible Toilet | K75: Final fixture selection and accessibility clearances to approved detail.
A76: G | B76: G2 | C76: Sanitary fixture allowance for staff/changing/utility areas outside RN-27, including standard WCs, wash basins, mirrors and accessories; exclude distribution pipework/drainage mains. | D76: LS | E76: 1 | F76: 1000000 | G76: =E76*F76 -> 1000000 | H76: Engineer PS | I76: PS-G2 | J76: Staff/support wet areas | K76: Provisional fixture allowance; final count from sanitary layout.
C77: Semi Luksary range
C78: Supply and fix white vitreous china (vc) floor standing close coupled semi back to wall water closet suite with wash down flushing with 6/3 liters dual flushing has horizontal outlet with vario drain bend and two lateral holes for bottom water connection , P trap, cistern with water inlet from rear of "Rocell" brand or approved equivalent complete to working order inclusive of universal bend . Prime cost of the water closet, tank and seat cover is Rs.60000 | E78: 7 | F78: 90000 | G78: =E78*F78 -> 630000
C79: Supply and fix wall hung wash basin with half pedestal and single tap hole in center of "Rocell" brand or approved equivalent complete to working order inclusive of the 1 1/4" chromium plated waste outlet of "Rocell" brand or approved equivalent and 1 1/4" chromium plated siphon cleanable bottle trap of "Rocell" brand or approved equivalent. Prime cost of wash basin is Rs.25000 | E79: 7 | F79: 45000 | G79: =E79*F79 -> 315000
C80: Supply and fix 4mm thick mirror of size 20" x 28" rectangular, beveled edge wall mounted mirror. Prime cost of the 4mm thick mirror of size 20" x 28" is Rs. 12,522.00. | E80: 7 | F80: 25000 | G80: =E80*F80 -> 175000
A81: G | B81: G3 | C81: Non-OT sinks/worktops to tea/dining and equipment-washing/support areas, stainless steel or approved hygienic finish including brackets and local sealants. | D81: Nr | E81: 2 | F81: 250000 | G81: =E81*F81 -> 500000 | H81: Engineer PS | I81: PS-G3 | J81: RN-20 / RN-23 | K81: Scrub sinks already included in modular package.
A82: G | B82: G4 | C82: Adjustable shelving / wall-mounted fixed storage to sterile/general/utility stores not already included in specialist Modular OT package. | D82: LS | E82: 1 | F82: 750000 | G82: =E82*F82 -> 750000 | H82: Engineer PS | I82: PS-G4 | J82: RN-11/12/21/22/33 | K82: Final storage layout to clinical-user approval.
A83: Subtotal - G - Sanitary / Fixed Architectural Fittings | G83: =SUM(G75:G82) -> 3820000
A84: H - Completion / Handover
A85: H | B85: H1 | C85: Civil/architectural testing and inspections including substrate moisture checks, adhesion/finish checks, door operation checks and defect/punch-list close-out. | D85: LS | E85: 1 | F85: 350000 | G85: =E85*F85 -> 350000 | H85: Engineer PS | I85: PS-H1 | J85: Handover requirement | K85: Specialist OT commissioning/validation remains in unchanged Modular OT BOQ.
A86: H | B86: H2 | C86: Final builders' deep clean and terminal construction clean of non-OT renovation areas prior to clinical reoccupation, including dust removal from ledges/ceiling zones. | D86: LS | E86: 1 | F86: 500000 | G86: =E86*F86 -> 500000 | H86: Engineer PS | I86: PS-H2 | J86: Hospital infection-control requirement | K86: Environmental/OT cleanroom validation excluded.
A87: H | B87: H3 | C87: As-built drawings, material data, warranties, cleaning/maintenance information and civil/architectural handover records for added works. | D87: LS | E87: 1 | F87: 250000 | G87: =E87*F87 -> 250000 | H87: Engineer PS | I87: PS-H3 | J87: Deliverables | K87: Coordinate with overall Contractor's Documents.
A88: Subtotal - H - Completion / Handover | G88: =SUM(G85:G87) -> 1100000
A90: I - Existing Equipment Relocation & MEP Service Strip-out
A91: I | B91: I1 | C91: Prepare a room-by-room inventory, identification/tagging and photographic condition record of existing medical equipment, furniture and retained fixtures; agree relocation/storage destinations and sequence with the Employer/Engineer before dismantling. | D91: LS | E91: 1 | F91: 250000 | G91: =E91*F91 -> 250000 | H91: Engineer PS | I91: PS-I1 | J91: Site photographs / existing occupied clinical rooms | K91: Include labelling, relocation register and handover/receipt record for items moved.
A92: I | B92: I2 | C92: Carefully dismantle, lift, move and relocate loose or semi-fixed hospital furniture, trolleys, cabinets, tables, chairs and non-specialist equipment to temporary or permanent locations within the hospital/site as directed, including protection during handling and stacking. | D92: LS | E92: 1 | F92: 1000000 | G92: =E92*F92 -> 1000000 | H92: Engineer PS | I92: PS-I2 | J92: Site photographs / Employer direction | K92: Excludes OEM/biomedical decommissioning, calibration and recommissioning of specialist medical equipment.
A93: I | B93: I3 | C93: Specialist attendance for safe disconnection, dismantling, relocation and reinstallation of fixed/sensitive medical equipment and ceiling/wall-mounted clinical equipment where directed, including biomedical/OEM coordination, temporary protection and functional handover. | D93: PS | E93: 1 | F93: 1500000 | G93: =E93*F93 -> 1500000 | H93: Engineer PS / provisional sum | I93: PS-I3 | J93: Site photographs / existing theatre & clinical equipment | K93: Use only on written instruction. Replacement equipment and major overhaul excluded; actual vendor/biomedical costs to be substantiated.
A94: I | B94: I4 | C94: Isolate, identify and remove redundant electrical and ELV service lines affected by the renovation, including cables, conduits, trunking, cable trays, small distribution accessories, abandoned wiring and supports; make safe and cap/terminate retained circuits as directed. | D94: LS | E94: 1 | F94: 900000 | G94: =E94*F94 -> 900000 | H94: Engineer PS | I94: PS-I4 | J94: Existing exposed/concealed MEP services / demolition coordination | K94: Final isolation and testing by licensed electrical personnel. New electrical/ELV installation is excluded except where already in the unchanged Modular OT package.
A95: I | B95: I5 | C95: Remove redundant HVAC service lines and air-distribution components affected by the renovation, including sheet-metal/flexible duct branches, grilles, diffusers, dampers, insulation, hangers and supports; blank/cap retained branches and protect live systems. | D95: LS | E95: 1 | F95: 900000 | G95: =E95*F95 -> 900000 | H95: Engineer PS | I95: PS-I5 | J95: Site photographs showing extensive overhead ductwork / ceiling strip-out | K95: AHUs, major plant and new HVAC installation excluded unless separately instructed or included in the unchanged Modular OT package.
A96: I | B96: I6 | C96: Remove redundant plumbing, water-supply and drainage service lines affected by the renovation, including small-bore pipework, traps, valves, brackets and supports; drain down, cap retained branches and temporarily seal drainage openings. | D96: LS | E96: 1 | F96: 600000 | G96: =E96*F96 -> 600000 | H96: Engineer PS | I96: PS-I6 | J96: Wet areas / equipment washing / existing services | K96: New distribution pipework, sanitary drainage mains and fixture connections excluded except where separately measured.
A97: I | B97: I7 | C97: Remove or reroute redundant medical-gas service lines only where specifically instructed, including isolation, purging, cutting/removal, certified capping of retained branches, identification and pressure/leak testing by an approved medical-gas specialist. | D97: LS | E97: 1 | F97: 600000 | G97: =E97*F97 -> 600000 | H97: Engineer PS / specialist allowance | I97: PS-I7 | J97: Existing theatre/clinical services / Employer direction | K97: No medical-gas work without approved permit-to-work and medical-gas specialist. New medical-gas distribution remains outside this added civil estimate unless included in the unchanged Modular OT package.
A98: Subtotal - I - Existing Equipment Relocation & MEP Service Strip-out | G98: =SUM(G91:G97) -> 5750000
A100: DIRECT ADDED RENOVATION WORKS SUBTOTAL | G100: =G13+G29+G43+G51+G64+G73+G83+G88+G98 -> 76810177

Sheet Ancillary Works - Reviewed
C1: MATARA HOSPITAL – ANCILLARY BUILDINGS / EXTENSION BOQ REVIEWED FOR CONSOLIDATION
A3: Section | B3: Item | C3: Description | D3: Unit | E3: Qty | G3: Rate (LKR) | H3: Amount | I3: Reviewed Amount | J3: Review Action | K3: Rate / Source Note | L3: Duplication Check | M3: Status | N3: Remarks
A4: C1. Demolition Work | C4: Demolition Work
A5: C1. Demolition Work | B5: C1.1 | C5: Demolish existing brick/block walls, foundations and obsolete plinths where required, including stacking serviceable material and disposal of debris. | D5: m³ | E5: 15 | G5: 1459 | H5: =E5*G5 -> 21885 | I5: 21885 | J5: RETAIN | K5: BSR Z07 / existing BOQ | L5: Site Work duplicates reviewed separately | M5: Source amount
A6: C1. Demolition Work | B6: C1.2 | C6: Demolish existing concrete floors/plinths/columns, slabs where required and clear debris from site. | D6: m³ | E6: 9 | G6: 10209 | H6: =E6*G6 -> 91881 | I6: 91881 | J6: RETAIN | K6: BSR Z02 / existing BOQ | L6: Site Work duplicates reviewed separately | M6: Source amount
A7: C1. Demolition Work | B7: C1.3 | C7: Removing roof tiles/cement fibre or asbestos roofing sheets and timber frame work, stacking serviceable materials and clearing debris away in two storied building. | D7: m2 | E7: 30 | G7: 550 | H7: =E7*G7 -> 16500
A8: C2. Excavation and Earth Work | C8: Excavation and earth work
A9: C2. Excavation and Earth Work | B9: C2.1 | C9: Removing top soil manually to a depth not exceeding 6" and removing all debris away from site up to a distance of 30'-0". (Removing top soil up to 2 sqrs.) | D9: m² | E9: 48 | G9: 80 | H9: =E9*G9 -> 3840 | I9: 3840 | J9: RETAIN | K9: BSR | L9: Site Work duplicates reviewed separately | M9: Source amount
A10: C2. Excavation and Earth Work | B10: C2.2 | C10: Manual excavation for column/walls including part backfill and disposal/stockpiling within site. | D10: m³ | E10: 30 | F10: =70*0.6*0.6+6*1.2*1.2*0.6 -> 30.384 | G10: 1889 | H10: =E10*G10 -> 56670 | I10: 15112 | J10: RETAIN | K10: BSR B07 / existing BOQ | L10: Site Work duplicates reviewed separately | M10: Source amount
A11: C2. Excavation and Earth Work | B11: C2.3 | C11: Random rubble (6"-9") masonry in cement sand mortar 1:5. | D11: m3 | E11: 30 | F11: =70*0.45*0.9 -> 28.35 | G11: 21797 | H11: =E11*G11 -> 653910 | I11: 261564 | J11: RETAIN | L11: Site Work duplicates reviewed separately | M11: Source amount
A12: C2. Excavation and Earth Work | B12: C2.4 | C12: Approved earth supplying, spreading & levelling manually, including watering in 225mm thick layers (measured on piled volume) & Compaction using a machine Rammer. Rate includes hire charges for the machine rammer. | D12: m³ | E12: 30 | F12: =100*0.3 -> 30 | G12: 4500 | H12: =E12*G12 -> 135000 | I12: 33740 | J12: RETAIN | K12: BSR B25 / existing BOQ | L12: Site Work duplicates reviewed separately | M12: Source amount
A13: C2. Excavation and Earth Work | B13: C2.6 | C13: Anti-termite treatment for the new construction with applying Biflexthrine 10Tc (Biflex ) or approved equivalent as per manufacturer's standards of application including horizontal & vertical barriers with 10 years warranty on application. (Measured on plinth area) | D13: m² | E13: 120 | F13: =70+30 -> 100 | G13: 850 | H13: =E13*G13 -> 102000 | I13: 40800 | J13: RETAIN | K13: BSR B41 / existing BOQ | L13: Site Work duplicates reviewed separately | M13: Source amount
A14: C3-Concrete Work | C14: Concrete Work
A15: C3-Concrete Work | B15: C3.1 | C15: Plain cement concrete 1:3:6 blinding under pad/wall foundations, 50mm thick. | D15: m² | E15: 55 | F15: =70*0.6+6*1.2*1.2 -> 50.64 | G15: 1431 | H15: =E15*G15 -> 78705 | I15: 89437.5 | J15: RETAIN | K15: BSR C02 / existing BOQ | L15: Site Work duplicates reviewed separately | M15: Source amount
A16: C3-Concrete Work | B16: C3.2 | C16: Grade 25 concrete to foundations. | D16: m³ | E16: 3 | F16: =6*1.2*1.2*0.3 -> 2.592 | G16: 34095 | H16: =E16*G16 -> 102285 | I16: 647805 | J16: RETAIN | K16: BSR C04 / existing BOQ | L16: Site Work duplicates reviewed separately | M16: Source amount
A17: C3-Concrete Work | B17: C3.3 | C17: Grade 25 concrete to columns up to roof level. | D17: m³ | E17: 3 | F17: =6*4*0.3*0.3 -> 2.16 | G17: 34095 | H17: =E17*G17 -> 102285 | I17: 184113 | J17: RETAIN | K17: BSR C04 / existing BOQ | L17: Site Work duplicates reviewed separately | M17: Source amount
A18: C3-Concrete Work | B18: C3.4 | C18: Grade 25 concrete to plinth/ground beams. | D18: m³ | E18: 3 | F18: =3*4*0.4*0.3+2*0.25*0.25*8 -> 2.44 | G18: 34095 | H18: =E18*G18 -> 102285 | I18: 508015.5 | J18: RETAIN | K18: BSR C04 / existing BOQ | L18: Site Work duplicates reviewed separately | M18: Source amount
A19: C3-Concrete Work | B19: C3.5 | C19: Gauge 750 polythene damp proof membrane with 6" laps laid under floors. | D19: m2 | E19: 100 | G19: 90 | H19: =E19*G19 -> 9000
A20: C3-Concrete Work | B20: C3.6 | C20: Grade 25 concrete in ground slab, including placing, compacting and finishing to receive floor finish. | D20: m³ | E20: 11 | F20: =8*4*0.1+70*0.1 -> 10.2 | G20: 34095 | H20: =E20*G20 -> 375045 | I20: 511425 | J20: RETAIN | K20: BSR C04 / existing BOQ | L20: Site Work duplicates reviewed separately | M20: Source amount
A21: C3-Concrete Work | B21: C3.7 | C21: Grade 25 concrete to roof beams, drain and parapet | D21: m³ | E21: 4 | F21: =3*4*0.4*0.3+2*0.25*0.25*8 -> 2.44 | G21: 35095 | H21: =E21*G21 -> 140380 | I21: 508015.5 | J21: RETAIN | K21: BSR C04 / existing BOQ | L21: Site Work duplicates reviewed separately | M21: Source amount
A22: C3-Concrete Work | B22: C3.8 | C22: Grade 25 concrete in roof slab, including placing, compacting and finishing to receive floor finish. | D22: m³ | E22: 5 | F22: =8*4*0.15 -> 4.8 | G22: 35095 | H22: =E22*G22 -> 175475 | I22: 531882 | J22: RETAIN | K22: BSR C04 / existing BOQ | L22: Site Work duplicates reviewed separately | M22: Source amount
A23: C3-Concrete Work | B23: C3.9 | C23: Curing of exposed reinforced concrete surfaces for 7 days. | D23: m²/day | E23: 1000 | G23: 32 | H23: =E23*G23 -> 32000 | I23: 32000 | J23: RETAIN | K23: BSR C37 / existing BOQ | L23: Site Work duplicates reviewed separately | M23: Source amount
A24: C3-Concrete Work | B24: C3.10 | C24: Formwork to sides of pad/wall foundations. | D24: m² | E24: 15 | F24: =1.2*4*6*0.3+70*0.05 -> 12.14 | G24: 1159 | H24: =E24*G24 -> 17385 | I24: 34770 | J24: RETAIN | K24: BSR D01 / existing BOQ | L24: Site Work duplicates reviewed separately | M24: Source amount
A25: C3-Concrete Work | B25: C3.11 | C25: Formwork to columns. | D25: m² | E25: 30 | F25: =6*4*0.3*4 -> 28.8 | G25: 3328 | H25: =E25*G25 -> 99840 | I25: 239616 | J25: RETAIN | K25: BSR D08 / existing BOQ | L25: Site Work duplicates reviewed separately | M25: Source amount
A26: C3-Concrete Work | B26: C3.12 | C26: Formwork to sides of plinth/ground beams. | D26: m² | E26: 25 | F26: =3*2*4*0.4+2*2*8*0.4 -> 22.4 | G26: 2047 | H26: =E26*G26 -> 51175 | I26: 92115 | J26: RETAIN | K26: BSR D03 / existing BOQ | L26: Site Work duplicates reviewed separately | M26: Source amount
A27: C3-Concrete Work | B27: C3.13 | C27: Formwork to sides and soffits of roof beams. | D27: m² | E27: 35 | F27: =F26+3*4*0.3+2*8*0.3 -> 30.8 | G27: 3868 | H27: =E27*G27 -> 135380 | I27: 264571.2 | J27: RETAIN | K27: BSR D06 / existing BOQ | L27: Site Work duplicates reviewed separately | M27: Source amount
A28: C3-Concrete Work | B28: C3.14 | C28: Formwork to soffit of roof slab | D28: m² | E28: 35 | F28: =4*8 -> 32 | G28: 3506 | H28: =E28*G28 -> 122710 | I28: 417214 | J28: RETAIN | K28: BSR D05 / existing BOQ | L28: Site Work duplicates reviewed separately | M28: Source amount
A29: C3-Concrete Work | B29: C3.15 | C29: Tor steel reinforcement to pad foundations, beams, coulumns and slab including cutting, bending, placing and tying. | D29: kg | E29: 4000 | F29: =22*140 -> 3080 | G29: 437 | H29: =E29*G29 -> 1748000 | I29: 546250 | J29: RETAIN | K29: BSR E04 / existing BOQ | L29: Site Work duplicates reviewed separately | M29: Source amount
A30: C3-Concrete Work | B30: C3.16 | C30: Supplying and laying in position of B.R.C mesh (6mm) - 4" x 4" | D30: m2 | E30: 120 | G30: 1485 | H30: =E30*G30 -> 178200 | I30: 546490.35 | J30: RETAIN | K30: BSR E04 proxy / existing BOQ | L30: Site Work duplicates reviewed separately | M30: Source amount
C31: Measonary Work
B32: C4.1 | C32: 3/4" thick D.P.C. in cement sand 1:3 finished with 2 coats of D.P.C. tar and blinded with sand. | D32: m2 | E32: =100*0.45 -> 45 | G32: 2487 | H32: =E32*G32 -> 111915
B33: C4.2 | C33: 150mm thick cement sand solid block wall (blocks confirming to S.L.S. 855 and subject to the approval of sample blocks) in cement and sand mortar 1:5 in ground floor. | D33: m² | E33: 175 | G33: 5890 | H33: =E33*G33 -> 1030750
B34: C4.3 | C34: 100mm thick cement sand solid block wall (blocks confirming to S.L.S.855 and subject to the approval of sample blocks) in cement and sand mortar 1:5 in ground floor. | D34: m² | E34: 25 | G34: 4190 | H34: =E34*G34 -> 104750 | I34: 1307280 | J34: RETAIN | K34: BSR G03 / existing BOQ | L34: Site Work duplicates reviewed separately | M34: Source amount
C35: Water proofing Work
B36: C5.1 | C36: Type - 1 - Internal Wet Areas without Exposure to Sunlight (Cementitious water proofing using Barralastic or approved equivalnt) Application of cementitious water proofing using Barralastic or approved equivalnt for internal wet areas such as toilet floors and walls where the surfaces are not directly exposed to sunlight and weathering. Rate shall include for cleaning the substrate and all other work as per manufacturer's specifications on application and shall include ponding test for a 300mm water height kept for a period of 48 hours for horizontal surfaces. | D36: m2 | E36: 20 | G36: 5587 | H36: =E36*G36 -> 111740
B37: C5.2 | C37: Type - 4 - Application of membrane type water proofing material for roofs) On roofs laying of Topseal 4 mm thick, Torch-on membrane or any other equivalent product marketed/installed by a specialist contractor registered at ICTAD under water proofing category including 1:3 cement,sand protective screed laid to slope. Rate shall include the formation of edges, torch welding and fixing metal strip on vertical walls at termination edges. | D37: m2 | E37: 40 | G37: 6135 | H37: =E37*G37 -> 245400
C38: Floor Finish
B39: C6.1 | C39: Rendering 1/2" thick in cement sand 1:3 finished smooth with cement slurry without colour pigment and expansion joints filled with construction expansion joint sealent including the cost for cleaning the joints prior application of construction expansion joint sealent by M/s Bitumix or approved equivalent. | D39: m2 | E39: 50 | G39: 1550 | H39: =E39*G39 -> 77500
B40: C6.2 | C40: Homogeneous porcelain semi - glazed floor tile 12" x 24" paving on tile adhesive (mortar) bedding and pointed with tile grout to match the tile. (Prime Cost of tile is Rs.627.00)-Floor | D40: m² | E40: 100 | G40: 6299 | H40: =E40*G40 -> 629900 | I40: 503920 | J40: RETAIN | L40: Site Work duplicates reviewed separately | M40: Source amount
B41: C6.3 | C41: Homogeneous porcelain semi - glazed floor tile 12" x 24" paving on tile adhesive (mortar) bedding and pointed with tile grout to match the tile. (Prime Cost of tile is Rs.627.00)-Bath Rooms | D41: m² | E41: 20 | G41: 6300 | H41: =E41*G41 -> 126000 | I41: 75600 | J41: RETAIN | L41: Site Work duplicates reviewed separately | M41: Source amount
C42: Wall Finish
B43: C7.1 | C43: Glazed Ceramic wall tiling of size 12" x 24" approved colour, supplying and fixing to walls on tile adhesive (mortar) layer, and pointed with tile grout to match the tile. (Prime Cost of tile Rs.700.00) | D43: m² | E43: 75 | G43: 6900 | H43: =E43*G43 -> 517500 | I43: 345000 | J43: RETAIN | L43: Site Work duplicates reviewed separately | M43: Source amount
B44: C7.2 | C44: Plastering 5/8" thick to walls in cement and sand 1:5 finished semi-rough. | D44: m2 | E44: 400 | G44: 1550 | H44: =E44*G44 -> 620000
C45: Painting
B46: C8.1 | C46: Painting walls with two coats of emulsion paint including preparing surface. | D46: m2 | E46: 300 | G46: 750 | H46: =E46*G46 -> 225000
B47: C8.2 | C47: Painting walls with two coats of weathershield paint including preparing surface. | D47: m2 | E47: 150 | G47: 935 | H47: =E47*G47 -> 140250
B48: C8.3 | C48: Painting soffit with two coats of emulsion paint including preparing surface. | D48: m² | E48: 35 | G48: 850 | H48: =E48*G48 -> 29750 | I48: 340000 | J48: RETAIN | K48: Added item / BSR painting proxy | L48: Site Work duplicates reviewed separately | M48: Source amount
B49: C9 | C49: Roof Work
B50: C9.1 | C50: 150×65×14×2 mm galvanized C-section primary framing/rafters/edge members | D50: m | E50: 265 | G50: 3650 | H50: =E50*G50 -> 967250 | I50: 967250 | J50: RECALCULATED | K50: Uploaded roof schedule | L50: Rainwater general roof items removed from Rainwater package | M50: Reviewed | N50: Source stored amount 438,000 does not equal Qty×Rate 967,250; Qty×Rate used.
B51: C9.2 | C51: 100×50×2 mm galvanized C-section secondary purlins | D51: m | E51: 294 | G51: 2730 | H51: =E51*G51 -> 802620 | I51: 884520 | J51: RECALCULATED | K51: Uploaded roof schedule | L51: Rainwater general roof items removed from Rainwater package | M51: Reviewed | N51: Source stored amount 177,450 does not equal Qty×Rate 884,520; Qty×Rate used.
B52: C9.3 | C52: Plates, cleats, stiffeners, anchor bolts/chemical anchors, bolts and bracing | D52: Item | E52: 1 | G52: 120000 | H52: =E52*G52 -> 120000 | I52: 120000 | J52: RETAIN | K52: Uploaded roof schedule | L52: Rainwater general roof items removed from Rainwater package | M52: Reviewed
B53: C9.4 | C53: 50 mm PIR insulated Zn/Al sandwich roof panels, complete | D53: m² | E53: 272 | F53: =E53/4 -> 68 | G53: 16500 | H53: =E53*G53 -> 4488000 | I53: 4488000 | J53: RECALCULATED | K53: Uploaded roof schedule | L53: Rainwater general roof items removed from Rainwater package | M53: Reviewed | N53: Source stored amount 1,237,500 does not equal Qty×Rate 4,488,000; Qty×Rate used.
B54: C9.5 | C54: Flashing into existing walls, 0.47 mm AZ150 Zn/Al, min. 450 mm girth, chased, sealed and dressed over roofing | D54: m | E54: 50 | G54: 2370 | H54: =E54*G54 -> 118500 | I54: 118500 | J54: RECALCULATED | K54: Uploaded roof schedule | L54: Rainwater general roof items removed from Rainwater package | M54: Reviewed | N54: Source stored amount 49,770 does not equal Qty×Rate 118,500; Qty×Rate used.
B55: C9.6 | C55: Zn/Al barge/verge capping | D55: m | E55: 26 | G55: 2220 | H55: =E55*G55 -> 57720 | I55: 57720 | J55: RECALCULATED | K55: Uploaded roof schedule | L55: Rainwater general roof items removed from Rainwater package | M55: Reviewed | N55: Source stored amount 35,520 does not equal Qty×Rate 57,720; Qty×Rate used.
B56: C9.7 | C56: 0.47 mm AZ150 Zn/Al eaves gutter, 470 mm girth | D56: m | E56: 60 | G56: 2650 | H56: =E56*G56 -> 159000 | I56: 145750 | J56: RECALCULATED | K56: Uploaded roof schedule | L56: Rainwater general roof items removed from Rainwater package | M56: Reviewed | N56: Source stored amount 55,650 does not equal Qty×Rate 145,750; Qty×Rate used.
B57: C9.8 | C57: Gutter stop ends | D57: No. | E57: 12 | G57: 1630 | H57: =E57*G57 -> 19560 | I57: 19560 | J57: RECALCULATED | K57: Uploaded roof schedule | L57: Rainwater general roof items removed from Rainwater package | M57: Reviewed | N57: Source stored amount 6,520 does not equal Qty×Rate 19,560; Qty×Rate used.
B58: C9.9 | C58: Running heads/nozzles | D58: No. | E58: 8 | G58: 3580 | H58: =E58*G58 -> 28640 | I58: 19560 | J58: RECALCULATED | K58: Uploaded roof schedule | L58: Rainwater general roof items removed from Rainwater package | M58: Reviewed | N58: Source stored amount 7,160 does not equal Qty×Rate 28,640; Qty×Rate used.
B59: C9.10 | C59: 100×100 mm Zn/Al downpipes | D59: m | E59: 36 | G59: 2090 | H59: =E59*G59 -> 75240 | I59: 19560 | J59: RECALCULATED | K59: Uploaded roof schedule | L59: Rainwater general roof items removed from Rainwater package | M59: Reviewed | N59: Source stored amount 14,630 does not equal Qty×Rate 75,240; Qty×Rate used.
B60: C9.11 | C60: Connect downpipes to adjacent stormwater system and make good | D60: No. | E60: 4 | G60: 12500 | H60: =E60*G60 -> 50000 | I60: 19560 | J60: RECALCULATED | K60: Uploaded roof schedule | L60: Rainwater general roof items removed from Rainwater package | M60: Reviewed | N60: Source stored amount 25,000 does not equal Qty×Rate 50,000; Qty×Rate used.
B61: C9.12 | C61: Roof and flashing water-tightness testing | D61: Item | E61: 1 | G61: 25000 | H61: =E61*G61 -> 25000 | I61: 19560 | J61: RETAIN | K61: Uploaded roof schedule | L61: Rainwater general roof items removed from Rainwater package | M61: Reviewed
C62: General
B63: C10.1 | C63: Structural calculations, shop drawings, flashing details, drainage layout and as-builts | D63: Item | E63: 1 | G63: 50000 | H63: =E63*G63 -> 50000 | I63: 19560 | J63: RETAIN | K63: Uploaded roof schedule | L63: Rainwater general roof items removed from Rainwater package | M63: Reviewed
B64: C10.2 | C64: Final cleaning, coating touch-up and handover | D64: Item | E64: 1 | G64: 20000 | H64: =E64*G64 -> 20000 | I64: 19560 | J64: RETAIN | K64: Uploaded roof schedule | L64: Rainwater general roof items removed from Rainwater package | M64: Reviewed
H65: =SUM(H5:H64) -> 15503821

Sheet Takeoff & Assumptions
A1: PRELIMINARY QUANTITY TAKEOFF & ASSUMPTIONS - ADDED RENOVATION WORKS
A3: Ref | B3: Parameter / Quantity | C3: Unit | D3: Preliminary Value | E3: Basis / Calculation | F3: Drawing / Source | G3: Action before Tender
A4: T01 | B4: OT1 area | C4: m² | D4: 43.403 | E4: 7.628 x 5.690 | F4: Modular source measurement / Room layout | G4: Verify by measured survey
A5: T02 | B5: OT2 area | C5: m² | D5: 31.573 | E5: 6.675 x 4.730 | F5: Modular source measurement / Room layout | G5: Verify by measured survey
A6: T03 | B6: OT3 area | C6: m² | D6: 61.514 | E6: 7.220 x 8.520 | F6: Modular source measurement / Room layout | G6: Verify by measured survey
A7: T04 | B7: OT4 area | C7: m² | D7: 51.417 | E7: 6.340 x 8.110 | F7: Modular source measurement / Room layout | G7: Verify by measured survey
A8: T05 | B8: Total four OT floor area | C8: m² | D8: 187.908 | E8: T01+T02+T03+T04 | F8: Modular source measurement | G8: Do not alter Modular OT BOQ quantity basis
A9: T06 | B9: Total scrub area | C9: m² | D9: 32.081 | E9: RN-03 + RN-06 + RN-08 | F9: Modular source measurement | G9: Do not alter Modular OT BOQ quantity basis
A10: T07 | B10: OT + scrub area used for preparatory substrate allowance | C10: m² | D10: 219.989 | E10: T05+T06 | F10: Modular source workbook | G10: Local patch/grind only; specialist flooring excluded
A11: T08 | B11: Approx. gross internal renovation floor area | C11: m² | D11: 1050 | E11: Drawing-scale/design allowance | F11: Drawings 004/007/011 | G11: Obtain full measured floor-area schedule
A12: T09 | B12: Approx. non-modular floor area | C12: m² | D12: 830 | E12: T08 - T07 | F12: Derived | G12: Split by room finish schedule before tender
A13: T10 | B13: Floor finish strip-out allowance | C13: m² | D13: 980 | E13: Most renovated floor area, excluding small retained zones | F13: Drawing 006 + renovation allowance | G13: Joint measure before demolition
A14: T11 | B14: Ceiling strip-out allowance | C14: m² | D14: 900 | E14: Approx. renovation ceiling extent | F14: Drawing 009 | G14: Survey ceiling/MEP conditions
A15: T12 | B15: 100 mm new block partition projected area | C15: m² | D15: 400 | E15: Preliminary wall takeoff | F15: Drawing 007 cyan new construction | G15: Measure wall lengths by thickness and height
... A29: T26 | B29: Existing redundant MEP service strip-out | C29: LS | D29: 1 | E29: Provisional multi-trade allowance for electrical/ELV, HVAC, plumbing/drainage and medical-gas lines affected by renovation. | F29: Site photographs / demolition coordination | G29: Undertake detailed service survey and isolation plan before demolition; measure major plant separately if encountered.
A30: CORE QUALIFICATIONS
A31: 1 | B31: All new quantities are preliminary allowances derived from visible drawing dimensions, room functions and scaled plan interpretation. They are not a substitute for a measured survey.
A32: 2 | B32: The existing beam layout is used as a structural control: do not remove or cut structural beams/columns/slabs without the Structural Engineer's written approval.
A33: 3 | B33: Load-bearing masonry demolition is intentionally set to zero. If later required, measure masonry separately and price temporary works/propping/needling to the approved method.
A34: 4 | B34: The unchanged Modular OT package already includes modular walls/ceilings, conductive flooring, hermetic OT doors, OT fixed fittings, LAF/HVAC package, electrical/medical-gas interfaces and validation as scheduled. Added works avoid intentional duplication.
A35: 5 | B35: The unchanged Site Works BOQ remains exactly as supplied and is reproduced in the 'Site Works - Unchanged' sheet.
A36: 6 | B36: New building electrical, ELV, plumbing, medical-gas distribution and HVAC installations outside the unchanged Modular OT package remain excluded except for builders-work interfaces. Removal/strip-out of redundant existing service lines and associated safe isolation/capping are included under Section I of the Added Renovation BOQ.

Sheet Rates & Basis
A1: RATE REGISTER & PRICING BASIS - ADDED RENOVATION WORKS
A3: Rate Ref. | B3: Description / Application | C3: Unit | D3: Base / Source Rate | E3: Markup | F3: Applied Rate (LKR) | G3: Rate Type | H3: Source / Page | I3: Source URL / File | J3: Qualification
A4: DM41 | B4: Remove & stack aluminium door/window with frame and make good | C4: m² | D4: 405 | E4: 0 | F4: 405 | G4: Matara BSR 2026 | H4: DM 4/4 | I4: https://www.cs.sp.gov.lk/css/csw/rates/bsr_matara_2026.pdf | J4: Direct BSR; measure overall area.
A5: DM43 | B5: Carefully remove aluminium partitions at joints for reuse/stack | C5: m² | D5: 369 | E5: 0 | F5: 369 | G5: Matara BSR 2026 - qualified | H5: DM 4/4 | I5: https://www.cs.sp.gov.lk/css/csw/rates/bsr_matara_2026.pdf | J5: Used as closest rate for aluminium glazed partition/curtain wall removal.
A6: DM08 | B6: Demolish brickwork in cement and clear debris | C6: m³ | D6: 2000 | E6: 0 | F6: 2000 | G6: Matara BSR 2026 - qualified | H6: DM 1/4 | I6: https://www.cs.sp.gov.lk/css/csw/rates/bsr_matara_2026.pdf | J6: Does not include engineered shoring/needling.
A7: DM19 | B7: Demolish tiles with tile bed | C7: m² | D7: 770 | E7: 0 | F7: 770 | G7: Matara BSR 2026 | H7: DM 1/4-2/4 | I7: https://www.cs.sp.gov.lk/css/csw/rates/bsr_matara_2026.pdf | J7: Applied to floor finish strip-out.
A8: B40 | B8: Dispose debris by tractor trailer up to 3 km | C8: Load | D8: 4207 | E8: 0 | F8: 4207 | G8: Existing unchanged Site BOQ BSR | H8: B40 | I8: Matara_OT_Site_Works_Landscaping_BOQ(1).xlsx | J8: Reused only as disposal benchmark; source Site BOQ itself remains unchanged.
A9: CT54 | B9: Grade 25 concrete; reinforcement/formwork separate | C9: m³ | D9: 32300 | E9: 0 | F9: 32300 | G9: Matara BSR 2026 | H9: CT 8/11 | I9: https://www.cs.sp.gov.lk/css/csw/rates/bsr_matara_2026.pdf | J9: Generic Grade 25 rate for local concrete.
A10: RF02 | B10: Reinforcement cut/bend/fix | C10: kg | D10: 494 | E10: 0 | F10: 494 | G10: Matara BSR 2026 - qualified | H10: RF 1/1 | I10: https://www.cs.sp.gov.lk/css/csw/rates/bsr_matara_2026.pdf | J10: Split by level/grade when final details are issued.
A11: FW19 | B11: Plywood formwork to beam sides/soffits | C11: m² | D11: 4070 | E11: 0 | F11: 4070 | G11: Matara BSR 2026 - qualified | H11: FW 7/8 | I11: https://www.cs.sp.gov.lk/css/csw/rates/bsr_matara_2026.pdf | J11: Budget proxy for local formwork categories.
A12: DER-L100 | B12: Derived reinforced Grade 25 precast lintel 100x150 mm | C12: m | D12: 2650.8136 | E12: 0 | F12: 2650.8136 | G12: Derived Matara BSR 2026 | H12: CT44 + RF02 | I12: https://www.cs.sp.gov.lk/css/csw/rates/bsr_matara_2026.pdf | J12: Budgetary; final bar schedule/bearing length to structural details.
A13: DER-L150 | B13: Derived reinforced Grade 25 precast lintel 150x150 mm | C13: m | D13: 3520.3051 | E13: 0 | F13: 3520.3051 | G13: Derived Matara BSR 2026 | H13: CT44 + RF02 | I13: https://www.cs.sp.gov.lk/css/csw/rates/bsr_matara_2026.pdf | J13: Budgetary derived rate.
A14: CB01 | B14: 100 mm cement solid block wall in 1:5 mortar | C14: m² | D14: 3000 | E14: 0 | F14: 3000 | G14: Matara BSR 2026 | H14: CB 1/1 | I14: https://www.cs.sp.gov.lk/css/csw/rates/bsr_matara_2026.pdf | J14: Non-load-bearing.
A15: DER-CB6 | B15: 150 mm cement block wall derived from CB01 x1.50 | C15: m² | D15: 4500 | E15: 0 | F15: 4500 | G15: Derived Matara BSR 2026 | H15: CB01 x 1.50 | I15: https://www.cs.sp.gov.lk/css/csw/rates/bsr_matara_2026.pdf | J15: Obtain approval before final tender use.
... A26: MOD-R2 | B26: Clinical vinyl floor budget benchmark | C26: m² | D26: 13500 | E26: 0 | F26: 13500 | G26: Existing Modular OT market benchmark | H26: Rate Basis R2 / scrub application | I26: F-Matara_Modular_OT_BOQ_Market_Prices.xlsx | J26: Applied only outside specialist modular scope; obtain written supplier quote.
A27: PS | B27: Engineer provisional sums / market allowances | C27: Various | G27: Engineer PS / market allowance | H27: See BOQ item | I27: N/A | J27: Replace with approved quotation/rate analysis before tender where material to total.
A28: PS-I1 | B28: Existing equipment inventory/tagging and relocation schedule | C28: LS | D28: 250000 | E28: 0 | F28: 250000 | G28: Engineer PS | H28: Section I | I28: Site photographs / Employer direction | J28: Replace with agreed method/resource build-up if required.
A29: PS-I2 | B29: Relocation of loose/semi-fixed hospital furniture and non-specialist equipment | C29: LS | D29: 1000000 | E29: 0 | F29: 1000000 | G29: Engineer PS | H29: Section I | I29: Site photographs / Employer direction | J29: Provisional handling/protection allowance; final scope by inventory.
A30: PS-I3 | B30: Specialist biomedical/OEM attendance for sensitive/fixed medical equipment relocation | C30: PS | D30: 1500000 | E30: 0 | F30: 1500000 | G30: Engineer PS / provisional sum | H30: Section I | I30: Site photographs | J30: Expenditure only on written instruction and supported by quotations/invoices.
A31: PS-I4 | B31: Redundant electrical and ELV service-line strip-out | C31: LS | D31: 900000 | E31: 0 | F31: 900000 | G31: Engineer PS | H31: Section I | I31: Existing MEP / demolition coordination | J31: Safe isolation/testing by licensed personnel; new installation excluded.
A32: PS-I5 | B32: Redundant HVAC duct/air-distribution service-line strip-out | C32: LS | D32: 900000 | E32: 0 | F32: 900000 | G32: Engineer PS | H32: Section I | I32: Site photographs / ceiling zones | J32: Major plant excluded unless separately instructed.
A33: PS-I6 | B33: Redundant plumbing/water/drainage service-line strip-out | C33: LS | D33: 600000 | E33: 0 | F33: 600000 | G33: Engineer PS | H33: Section I | I33: Wet areas / existing services | J33: Includes drain down, capping and temporary seals only.
A34: PS-I7 | B34: Medical-gas line isolation/removal/capping/testing by approved specialist | C34: LS | D34: 600000 | E34: 0 | F34: 600000 | G34: Engineer PS / specialist allowance | H34: Section I | I34: Existing clinical services | J34: Permit-to-work, purge and certification mandatory.

Sheet Site Works - Unchanged
A1: PRELIMINARY BOQ & ENGINEER'S ESTIMATE - SITE WORKS / LANDSCAPING | O1: Source status | P1: UNCHANGED reproduction
A2: Improvement of MEP Services and Renovation of Theater Complex - Periphery Site Works | O2: Source file | P2: Matara_OT_Site_Works_Landscaping_BOQ(1).xlsx
A3: Preliminary quantity takeoff from the 1:200 development-boundary plan and site photographs. Final BOQ quantities shall be remeasured after topographic levels, demolition survey and approved landscape layout. | O3: Source total (LKR) | P3: 4798506.9
O4: Instruction | P4: Do not modify source site-work scope/rates/quantities in this consolidated estimate.
A5: Item | B5: Section | C5: Item | D5: Description | E5: BSR / Basis | F5: Unit | G5: Qty | H5: Rate (LKR) | I5: Amount (LKR) | J5: Status | K5: Drawing/Photo Basis | L5: Inclusion / Qualification | M5: Remarks
B6: A1.Preliminaries
A7: 1 | B7: A1.Preliminaries | C7: A1.1 | D7: Protection to live hospital, barricading, dust/noise control, temporary access and housekeeping | E7: Engineer PS | F7: Item | G7: 1 | H7: 150000 | I7: =IF(G7*H7<>0,G7*H7,"") -> 150000 | J7: PS | K7: Site condition | L7: Complete for external works adjoining occupied hospital
A8: 2 | B8: A1.Preliminaries | C8: A1.2 | D8: Setting out, levels and site survey for external works | E8: Engineer PS | F8: Item | G8: 1 | H8: 175000 | I8: =IF(G8*H8<>0,G8*H8,"") -> 175000 | J8: PS | K8: Site plan 1:200 | L8: Establish final grading and drain falls
A9: Subtotal - A. Preliminaries | I9: =SUM(I7:I8) -> 325000
I10: =IF(G10*H10<>0,G10*H10,"")
A11: 3 | B11: A2. Clearance & Demolition | C11: A2.1 | D11: Clear site vegetation, bushes, shrubs and rubbish | E11: B01 | F11: m² | G11: 650 | H11: 86 | I11: =IF(G11*H11<>0,G11*H11,"") -> 55900 | J11: BSR | K11: Scaled plan + photos | L11: Entire preliminary external site-work area
A12: 4 | B12: A2. Clearance & Demolition | C12: A2.2 | D12: Remove banana/small trees including roots | E12: Engineer PS | F12: LS | G12: 1 | H12: 25000 | I12: =IF(G12*H12<>0,G12*H12,"") -> 25000 | J12: PS | K12: Site photos | L12: Large mature trees excluded
A13: 5 | B13: A2. Clearance & Demolition | C13: A2.3 | D13: Demolish existing RCC canopy / covered walkway and supports | E13: Z01 proxy | F13: m³ | G13: 8 | H13: 12000 | I13: =IF(G13*H13<>0,G13*H13,"") -> 96000 | J13: BSR proxy | K13: Site photo | L13: Selective demolition only where conflicting with works
A14: 6 | B14: A2. Clearance & Demolition | C14: A2.4 | D14: Remove existing corrugated lean-to / roof and light frame | E14: Z28 proxy | F14: m² | G14: 45 | H14: 357 | I14: =IF(G14*H14<>0,G14*H14,"") -> 16065 | J14: BSR proxy | K14: Site photos | L14: Material survey required; ACM, if present, by approved specialist method
A15: 7 | B15: A2. Clearance & Demolition | C15: A2.5 | D15: Break out existing concrete hardstanding | E15: Z02 | F15: m³ | G15: 8 | H15: 10209 | I15: =IF(G15*H15<>0,G15*H15,"") -> 81672 | J15: BSR | K15: Photo provisional | L15: Quantity derived from 80m² x 0.10m average
A16: 8 | B16: A2. Clearance & Demolition | C16: A2.6 | D16: Demolish existing drain sections where replacement is required | E16: Z10 | F16: m | G16: 50 | H16: 262 | I16: =IF(G16*H16<>0,G16*H16,"") -> 13100 | J16: BSR | K16: Condition allowance | L16: Only defective/conflicting sections
A17: 9 | B17: A2. Clearance & Demolition | C17: A2.7 | D17: Dispose demolition/clearance debris by tractor trailer, up to 3km | E17: B40 | F17: Load | G17: 20 | H17: 4207 | I17: =IF(G17*H17<>0,G17*H17,"") -> 84140 | J17: BSR | K17: Provisional | L17: Approved disposal point to be confirmed
A18: Subtotal - B. Clearance & Demolition | I18: =SUM(I11:I17) -> 371877
A20: 10 | B20: A3. Earthworks & Grading | C20: A3.1 | D20: Supply approved earth for filling/regrading | E20: B26 | F20: m³ | G20: 30 | H20: 3177 | I20: =G20*H20 -> 95310 | J20: BSR | K20: Provisional levels | L20: Final from level survey
A21: 11 | B21: A3. Earthworks & Grading | C21: A3.2 | D21: Spread, level, water and compact approved earth | E21: B32 | F21: m³ | G21: 30 | H21: 444 | I21: =G21*H21 -> 13320 | J21: BSR | K21: Provisional levels | L21: To falls away from building and toward drains
A22: Subtotal - C. Earthworks & Grading | I22: =SUM(I20:I21) -> 108630
B23: Repair | D23: Repair existing drains
A24: 12 | B24: A4. Surface Drainage | C24: A4.1 | D24: Clean, desilt and flush existing perimeter drains | E24: Engineer PS | F24: m | G24: 100 | H24: 550 | I24: =G24*H24 -> 55000 | J24: PS | K24: Green drain alignment | L24: Protect connections and maintain drainage during works
A25: 13 | B25: A4. Surface Drainage | C25: A4.2 | D25: Repair / construct small concrete drains | E25: C23 proxy | F25: m | G25: 20 | H25: 3219 | I25: =G25*H25 -> 64380 | J25: BSR proxy | K25: Condition allowance | L25: Final section/cover details to be coordinated
B26: A4. Surface Drainage
B27: A4. Surface Drainage | C27: A4.3 | D27: Manual Excavation for column, surface drainage in hard dense soil (except rock requiring blasting) up to 5'-0" depth, part return fill in and ram and surplus deposited within site as directed. (Transport of material to be paid seperately) | F27: m³ | G27: =40*0.6*1 -> 24 | H27: 2371 | I27: =G27*H27 -> 56904
B28: A4. Surface Drainage | C28: A4.4 | D28: Cement concrete 1:3:6 (1") laid to a thickness of 2" under Drainage, including placing in position,compacting. | F28: m2 | G28: =40*0.75 -> 30 | H28: 1490 | I28: =G28*H28 -> 44700
C29: A4.5 | D29: Grade 25 concrete in foundation, wall in Drain construction | F29: m3 | G29: =40*1.8*0.15 -> 10.8 | H29: 34095 | I29: =G29*H29 -> 368226
C30: A4.6 | D30: Tor steel reinforcement to base, wall and cover of surface drainage work etc.. bent to shape, laid in position and tied with 16 B.W.G. Aneal binding wire in second floor. (Laps should be measured as per the drawings ). | F30: kg | G30: =G29*120 -> 1296 | H30: 459 | I30: =G30*H30 -> 594864
C31: A4.7 | D31: formwork | F31: m2 | G31: 120 | H31: 2790 | I31: =G31*H31 -> 334800
C32: A4.8 | D32: Supply, manufacture and place heavy-duty precast reinforced concrete cover slabs, minimum 125 mm thick, Grade 25 concrete, over surface drainage channels, of approved panel sizes, reinforced to withstand the specified vehicular/loading conditions, complete with high-yield reinforcement, moulds/formwork, lifting hooks/recesses where required, chamfered edges, curing, transportation, handling, bedding/seating in cement mortar, alignment and levelling, cutting and adjustment at ends and junctions, and all labour, materials, plant and incidental works necessary to provide a complete installation, all in accordance with approved drawings and Engineer's instructions. | F32: m2 | G32: 25 | H32: 35000 | I32: =G32*H32 -> 875000
C33: A4.9 | D33: Supply, fabricate and place precast reinforced concrete light-duty cover slabs over existing surface drainage, minimum 100 mm thick, Grade 25 concrete, in manageable panel sizes to suit the existing drain, reinforced with approved high-yield steel reinforcement, complete with formwork/moulds, lifting arrangements where required, chamfered edges, curing, transportation, handling, placing, levelling and proper seating over the existing drain walls; including minor preparation and making good of existing drain edges, cement mortar bedding where necessary, and all labour, materials, plant and incidental works required for a complete installation, all to the Engineer's approval. | F33: m2 | G33: =70*0.7 -> 49 | H33: 18000 | I33: =G33*H33 -> 882000
A34: Subtotal - D. Surface Drainage | I34: =SUM(I24:I33) -> 3275874
A36: 14 | B36: E. Hard Landscape | C36: A5.1 | D36: 60mm coloured interlocking paving blocks to pedestrian/service areas | E36: AA26 | F36: m² | G36: 700 | H36: 5136 | I36: =H36*G36 -> 3595200 | J36: BSR | K36: Design allocation | L36: Existing road and connecting corridors excluded
A37: 15 | B37: E. Hard Landscape | C37: A5.2 | D37: Precast concrete curb / edging | E37: AA31 | F37: m | G37: 90 | H37: 2713 | I37: =H37*G37 -> 244170 | J37: BSR | K37: Design allocation | L37: At turf/paving and landscape edges
A39: Subtotal - E. Hard Landscape | I39: =SUM(I36:I38) -> 3839370
A41: 16 | B41: F. Soft Landscape | C41: A6.1 | D41: Prepare turf area with 150mm top vegetable soil / coir mixture | E41: AA01 | F41: m² | G41: 150 | H41: 2390 | I41: =H41*G41 -> 358500 | J41: BSR | K41: Design allocation | L41: Includes root/gravel removal and final grading
A42: 17 | B42: F. Soft Landscape | C42: A6.2 | D42: Supply and lay buffalo grass turf | E42: AA02 | F42: m² | G42: 150 | H42: 624 | I42: =H42*G42 -> 93600 | J42: BSR | K42: Design allocation | L42: Includes establishment maintenance stated in BSR
A43: 18 | B43: F. Soft Landscape | C43: A6.3 | D43: Prepare ornamental planting beds incl. topsoil, compost, cultivation and mulch | E43: Engineer PS | F43: m² | G43: 40 | H43: 2400 | I43: =H43*G43 -> 96000 | J43: PS | K43: Design allocation | L43: Final landscape plan required
A44: 19 | B44: F. Soft Landscape | C44: A6.4 | D44: Supply and plant approved shrubs / groundcovers | E44: Engineer PS | F44: Nr | G44: 15 | H44: 1100 | I44: =H44*G44 -> 16500 | J44: PS | K44: Design allocation | L44: Low-maintenance species suited to hospital environment
A45: 20 | B45: F. Soft Landscape | C45: A6.5 | D45: Supply and plant approved ornamental palms / small trees | E45: AA12 proxy | F45: Nr | G45: 5 | H45: 10270 | I45: =H45*G45 -> 51350 | J45: BSR proxy | K45: Design allocation | L45: Foxtail Palm BSR rate used as proxy; final species to be approved
A46: 21 | B46: F. Soft Landscape | C46: A6.6 | D46: Landscape establishment / maintenance labour | E46: AA07 | F46: Month | G46: 3 | H46: 24570 | I46: =H46*G46 -> 73710 | J46: BSR | K46: Landscape allowance | L46: Subject to Engineer approval; avoid duplicate payment where included in turf item
A47: Subtotal - F. Soft Landscape | I47: =SUM(I41:I46) -> 689660
A49: 22 | B49: G. External Interfaces | C49: A7.1 | D49: Landscape watering points / hose bibs and minor distribution pipework | E49: Engineer PS | F49: Item | G49: 1 | H49: 120000 | I49: =G49*H49 -> 120000 | J49: PS | K49: Site requirement | L49: Coordinate with plumbing/water supply
A50: 23 | B50: G. External Interfaces | C50: A7.2 | D50: Making good interfaces to road, connecting corridors, walls and disturbed surfaces | E50: Engineer PS | F50: Item | G50: 1 | H50: 150000 | I50: =G50*H50 -> 150000 | J50: PS | K50: User boundary instruction | L50: No reconstruction of existing road/corridor except local making good
A51: Subtotal - G. External Interfaces | I51: =SUM(I49:I50) -> 270000
A53: DIRECT SITE WORKS SUBTOTAL | I53: =I51+I47+I39+I34+I22+I18+I9 -> 8880411

Sheet Modular OT - Unchanged
A1: Item No. | B1: Section | C1: Description | D1: Scope / technical basis | E1: Unit | F1: Quantity | G1: Market Rate (LKR) | H1: Amount (LKR) | I1: Rate basis | J1: Source URL / note
A2: A1 | B2: A - Modular envelope | C2: Modular OT wall panels with support frame and sealed joints | D2: Hygienic antibacterial coated 1.2mm metal/SS304 or approved equivalent; includes sub-frame, sealant and flush service coordination | E2: m² | F2: 345.9519 | G2: 48000 | H2: =F2*G2 -> 16605691 | I2: Direct market benchmark: modular OT wall panel INR 900/sq.ft converted and uplifted for import/local installation | J2: https://www.vkcleanrooms.co.in/modular-operation-theater.html
A3: A2 | B3: A - Modular envelope | C3: Airtight modular ceiling panels with support frame | D3: Hygienic removable/accessible sealed ceiling panels coordinated with LAF, lights and pendants | E3: m² | F3: 197 | G3: 48000 | H3: =F3*G3 -> 9456000 | I3: Applied same benchmark as modular OT panel with ceiling subframe/access uplift | J3: https://www.vkcleanrooms.co.in/modular-operation-theater.html
A4: A3 | B4: A - Modular envelope | C4: Scrub area wall panels and support frame | D4: Associated RN-03/RN-06/RN-08 scrub rooms; same hygienic panel system, subject to confirmation | E4: m² | F4: 131.1912 | G4: 42000 | H4: =F4*G4 -> 5510030.4 | I4: Budget rate derived from modular panel benchmark, lower complexity than OT rooms | J4: https://www.vkcleanrooms.co.in/modular-operation-theater.html
A5: A4 | B5: A - Modular envelope | C5: Scrub area ceiling panels | D5: Associated scrub-room hygienic ceilings | E5: m² | F5: 33.685313 | G5: 42000 | H5: =F5*G5 -> 1414783.1 | I5: Budget rate derived from modular panel benchmark | J5: https://www.vkcleanrooms.co.in/modular-operation-theater.html
A6: A5 | B6: A - Modular envelope | C6: 2mm conductive / anti-static vinyl flooring to OT rooms | D6: Self levelling screed, copper grid, conductive adhesive, heat welding and 100mm coved skirting interface | E6: m² | F6: 197.30326 | G6: 15000 | H6: =F6*G6 -> 2959549 | I6: Market benchmark INR 95/sq.ft anti-static vinyl plus adhesive, screed, copper grid and installation uplift | J6: https://www.tradeindia.com/products/hospital-vinyl-flooring-anti-static-homogeneous-conductive-vinyl-flooring-i-c8716784.html
A7: A6 | B7: A - Modular envelope | C7: Clinical vinyl flooring to scrub areas | D7: Same installed flooring standard, non-slip/cleanable with coving | E7: m² | F7: 33.685313 | G7: 13500 | H7: =F7*G7 -> 454751.72 | I7: Derived from anti-static vinyl benchmark with lower copper-grid allowance | J7: https://www.tradeindia.com/products/hospital-vinyl-flooring-anti-static-homogeneous-conductive-vinyl-flooring-i-c8716784.html
A8: A7 | B8: A - Modular envelope | C8: Coved skirting, internal coves, trims, sealants and penetration finishing | D8: Allowance for additional coving/trim around corners, columns, doors, and service penetrations | E8: LS | F8: 1 | G8: 1800000 | H8: =F8*G8 -> 1800000 | I8: Budget allowance based on measured perimeter and detailed trim complexity | J8: Measured allowance
A9: A8 | B9: A - Modular envelope | C9: Secondary steel/support framework for LAF, surgical lights, pendants and ceiling equipment | D9: Independent support frames, anchor bolts, coordination and load certification; excludes major structural strengthening | E9: No | F9: 4 | G9: 850000 | H9: =F9*G9 -> 3400000 | I9: Budget allowance; final rate to follow structural design and load calculations | J9: Provisional
A10: B1 | B10: B - Doors & dampers | C10: Automatic hermetically sealed theatre door 1500x2100x50mm | D10: Japan/equivalent machine set, touchless switches x2, sensors, manual release and trolley protection | E10: No | F10: 4 | G10: 1200000 | H10: =F10*G10 -> 4800000 | I10: Market benchmark: hermetic OT sliding door INR 185,000-268,000 plus import/local installation uplift | J10: https://www.hospitaldoors.in/operation-theater-doors.html
A11: B2 | B11: B - Doors & dampers | C11: Hermetic single swing/rear theatre door 1500x2100x50mm | D11: Hygienic door leaf/frame with vision panel, seals and hardware | E11: No | F11: 2 | G11: 480000 | H11: =F11*G11 -> 960000 | I11: Budget rate benchmarked from hermetic hospital door market listings | J11: https://www.hospitaldoors.in/hermetic-doors.html
B12: B - Doors & dampers | C12: Hermatic double swing door to scrub Area | F12: 3 | G12: 480000 | H12: =F12*G12 -> 1440000
A13: B3 | B13: B - Doors & dampers | C13: Pressure relief damper SS 350x140mm | D13: Stainless steel pressure relief damper, balancing and cleanable grille | E13: No | F13: 12 | G13: 95000 | H13: =F13*G13 -> 1140000 | I13: Market sources range from INR 12,000 to INR 84,900; selected mid budget installed rate | J13: https://www.jkenggindia.com/operation-theater-equipment.html
A14: B4 | B14: B - Doors & dampers | C14: Pass-through hatch box 600x600x600mm | D14: SS304 manual pass-through window with UV light and interlock where required | E14: No | F14: 4 | G14: 350000 | H14: =F14*G14 -> 1400000 | I14: Budgetary market allowance; exact rate depends on interlock/UV/control specification | J14: Provisional
A15: B5 | B15: B - Doors & dampers | C15: Air return inlet / fluff separator with filter | D15: Flush SS304 air return inlet, removable filter/fluff separator and volume damper | E15: No | F15: 16 | G15: 95000 | H15: =F15*G15 -> 1520000 | I15: Budgetary rate derived from pressure damper/fluff separator components | J15: Provisional
A16: C1 | B16: C - Fixed OT fittings | C16: Three-bay scrub sink with sensor/knee controls | D16: SS316 body/SS304 casing, infrared taps, soap dispensers, drainage connections | E16: No | F16: 3 | G16: 750000 | H16: =F16*G16 -> 2250000 | I16: Scrub sink market range INR 30,000-100,000; uplift for 3-bay SS316/sensor/local install | J16: https://www.tradeindia.com/products/stainless-steel-304-surgical-scrub-sink-6937771.html
A17: C2 | B17: C - Fixed OT fittings | C17: LED backlight X-ray viewer, 2 bay, approx. 1000x625x102mm | D17: Dimmable LED viewer with shutter, flush mounting and wiring | E17: No | F17: 4 | G17: 250000 | H17: =F17*G17 -> 1000000 | I17: Market LED X-ray viewer prices vary from low single/double units to INR 79,000 multi-screen; selected 2-bay installed allowance | J17: https://www.tradeindia.com/manufacturers/x-ray-viewer.html
A18: C3 | B18: C - Fixed OT fittings | C18: SS storage cabinets 900x350x1800mm | D18: Flush/hygienic SS304 storage cabinets; 3 per theatre | E18: No | F18: 12 | G18: 325000 | H18: =F18*G18 -> 3900000 | I18: Budgetary fabricated SS304 cabinet rate | J18: Provisional
A19: C4 | B19: C - Fixed OT fittings | C19: SS writing table / operating list board with light | D19: Approx. 900W x 450H x 280D, hygienic surface and concealed fixing | E19: No | F19: 4 | G19: 175000 | H19: =F19*G19 -> 700000 | I19: Budgetary fabricated SS rate | J19: Provisional
A20: C5 | B20: C - Fixed OT fittings | C20: Flush OT control panel | D20: Clock, timer, gas alarm interface, intercom/telephone, temperature/RH display, lighting controls and HEPA status | E20: No | F20: 4 | G20: 850000 | H20: =F20*G20 -> 3400000 | I20: Market control panel listings INR 90,000 to 500,000; selected mid/high healthcare integrated rate | J20: https://www.bio-xhealthcare.com/surgeon-control-panel.html
A21: C6 | B21: C - Fixed OT fittings | C21: Air-sealed cleanroom lighting box 1200x300x38mm | D21: Airtight cleanroom/OT LED luminaire, dimming interface and below-access maintenance | E21: No | F21: 40 | G21: 85000 | H21: =F21*G21 -> 3400000 | I21: Cleanroom light market references converted and uplifted for sealed OT luminaire | J21: https://denphongsach.com/en/post/latest-price-list-of-clean-room-lights-used-in-medical-clean-rooms-76.htm
A22: C7 | B22: C - Fixed OT fittings | C22: Ceiling-mounted double-dome LED surgical light | D22: Major surgery double dome LED light with ceiling suspension, controls and installation | E22: No | F22: 4 | G22: 1500000 | H22: =F22*G22 -> 6000000 | I22: Double-dome OT light market range INR 53,800-495,800; selected hospital-grade budget rate | J22: https://www.hospitalstore.com/ot-lights/double-dome/
A23: C8 | B23: C - Fixed OT fittings | C23: Single-arm anaesthetist pendant | D23: Medical gas/electrical/data pendant with outlets as uploaded quotation, arm and suspension | E23: No | F23: 4 | G23: 1600000 | H23: =F23*G23 -> 6400000 | I23: Pendant market references from INR 58,000 to 500,000; selected higher specification installed rate | J23: https://www.dnhshealthcaredevicesprivatelimited.com/single-arm-surgical-pendant-7535161.html
A24: C9 | B24: C - Fixed OT fittings | C24: Surgical pendant / monitor support arm allowance | D24: Ceiling-mounted surgical services/monitor arm, if required by final clinical equipment layout | E24: No | F24: 4 | G24: 1200000 | H24: =F24*G24 -> 4800000 | I24: Provisional allowance pending final clinical layout | J24: Provisional
... A38: F3 | B38: F - T&C / deliverables | C38: Mobilisation, freight, local handling, protection and demobilisation | D38: Import/local transport, unloading, storage, site protection, cleaning and demobilisation | E38: LS | F38: 1 | G38: 4200000 | H38: =F38*G38 -> 4200000 | I38: Budgetary logistics allowance for imported/modular packages | J38: Provisional
A40: Total before contingency and VAT | H40: =SUM(H2:H38) -> 1.4907081e+08

Sheet Source Notes
A1: SOURCE DOCUMENTS, SCOPE CONTROLS & EXCLUSIONS
A3: Source | B3: Reference / File | C3: How Used | D3: Important Control
A4: Site Works BOQ | B4: Matara_OT_Site_Works_Landscaping_BOQ(1).xlsx | C4: Copied unchanged; exact total retained in Summary. | D4: No changes to scope, quantities, rates or contingency.
A5: Modular OT BOQ | B5: F-Matara_Modular_OT_BOQ_Market_Prices.xlsx | C5: Copied unchanged; exact direct and VAT-inclusive totals retained. | D5: No changes to existing 35-line specialist modular package.
A6: Existing plan | B6: 004-Existing G.Floor plan.pdf / DGHM-P2-A-004 | C6: Existing layout and refurbishment boundary context. | D6: Remeasure final dimensions on site.
A7: Beam layout | B7: 005-Existing 1st floor beam layout.pdf / DGHM-P2-A-005 | C7: Structural frame control for demolition and openings. | D7: No structural demolition/cutting without Structural Engineer approval.
A8: Demolition plan | B8: 006-Existing G.floor Demolition.pdf / DGHM-P2-A-006 | C8: Primary selective demolition basis. | D8: Red-highlight demolition is interpreted as mainly partition/fit-out work; verify thickness/material.
A9: New construction | B9: 007-G.Floor New construction.pdf / DGHM-P2-A-007 | C9: New wall/partition and making-good basis. | D9: Partition areas are provisional until detailed room-by-room takeoff.
A10: Door layout | B10: 008-G.Floor Doors.pdf / DGHM-P2-A-008 | C10: Door allowance basis. | D10: 62 door tags identified; 8 modular hermetic OT doors are already in Modular OT BOQ, leaving 54 provisional non-modular doors.
A11: Ceiling layout | B11: 009-G.Floor Ceiling layout.pdf / DGHM-P2-A-009 | C11: Ceiling renewal allowance. | D11: Coordinate all ceiling work with MEP access and clean-zone requirements.
A12: Trolley / corner guard | B12: 010-Trolly & Conner Gurred.pdf / DGHM-P2-A-010 | C12: Trolley guard and corner guard allowance. | D12: Final lengths/counts to be measured from approved elevations.
A13: Room layout | B13: 011-G.Floor Room Layout.pdf / DGHM-P2-A-011 | C13: 33-room functional layout and zoning basis. | D13: Finishes split by clinical/support/wet-room functions.
A14: Modular OT Specification | B14: Modular_Operating_Theatre_Specification.docx | C14: Used to avoid duplication and define preparatory interface. | D14: Modular package includes specialist OT envelope, flooring, doors, supports, HVAC/LAF, electrical/gas interfaces and validation as scheduled.
... A23: Consolidated estimate | B23: Rev 7 | C23: Summary updated to reviewed package totals and 10% design-development contingencies on newly reviewed packages. | D23: VAT excluded from newly added/reviewed specialist packages unless expressly stated.

Sheet MVAC BOQ & Estimate
A1: DISTRICT GENERAL HOSPITAL MATARA – MVAC BOQ & ENGINEER'S ESTIMATE
A2: Prepared from uploaded MVAC drawings. OT-specific LAF/AHU/exhaust/ductwork/room-control scope already included in the Modular OT package is excluded to avoid duplication.
A4: Item | B4: Section | C4: BOQ Description | D4: Unit | E4: Qty | F4: Rate (LKR) | G4: Amount (LKR) | H4: Rate Basis | I4: Drawing / Source | J4: Duplication Check | K4: Status | L4: Remarks
A5: A1 | B5: A - Central chilled-water plant | C5: Supply, install, test and commission 50 RT standard water-cooled screw chiller, complete with compressor(s), evaporator, condenser, refrigerant charge, microprocessor controls, anti-vibration mounts, isolation valves, gauges, thermometers, flow proving and all accessories required for a complete operational unit. | D5: No | E5: 2 | F5: 13500000 | G5: =E5*F5 -> 27000000 | H5: Engineer 2026 provisional market allowance | I5: MVAC Equipment Schedule – CH-01 | J5: Not in Modular OT BOQ | K5: Provisional | L5: Obtain minimum 3 supplier quotations before tender.
A6: A2 | B6: A - Central chilled-water plant | C6: Supply, install, test and commission chilled-water circulation pump set, 130 GPM at 30 m head, complete with motor, base frame, flexible connectors, isolating valves, check valve, strainer, pressure gauges, vibration isolation and accessories. | D6: No | E6: 3 | F6: 1200000 | G6: =E6*F6 -> 3600000 | H6: Engineer 2026 provisional market allowance | I6: MVAC Equipment Schedule – CHWP-01 | J6: Not in Modular OT BOQ | K6: Provisional | L6: One duty/standby arrangement to be confirmed.
A7: A3 | B7: A - Central chilled-water plant | C7: Supply, install, test and commission condenser-water pump set, 160 GPM at 20 m head, complete with motor, base frame, flexible connectors, isolating valves, check valve, strainer, gauges, vibration isolation and accessories. | D7: No | E7: 3 | F7: 1100000 | G7: =E7*F7 -> 3300000 | H7: Engineer 2026 provisional market allowance | I7: MVAC Equipment Schedule – CWP-01 | J7: Not in Modular OT BOQ | K7: Provisional | L7: Final pump duty to approved selection.
A8: A4 | B8: A - Central chilled-water plant | C8: Supply, install, test and commission cross-flow square induced-draft cooling tower, 75 RT, design entering/leaving water temperatures 37/32°C, complete with fan, motor, drift eliminators, basin, make-up arrangement, vibration isolation, controls and accessories. | D8: No | E8: 2 | F8: 4500000 | G8: =E8*F8 -> 9000000 | H8: Engineer 2026 provisional market allowance | I8: MVAC Equipment Schedule – CT-01 | J8: Not in Modular OT BOQ | K8: Provisional | L8: Structural base/platform measured elsewhere unless specifically included.
A9: A5 | B9: A - Central chilled-water plant | C9: Provide cooling-tower make-up water tank, make-up/overflow connections, float control and associated valves and fittings as indicated, complete. | D9: LS | E9: 1 | F9: 800000 | G9: =E9*F9 -> 800000 | H9: Engineer provisional allowance | I9: MVAC drawing – cooling tower detail | J9: Not in Modular OT BOQ | K9: Provisional | L9: Final tank capacity/material to be confirmed.
A10: B1 | B10: B - Non-OT airside equipment | C10: Supply, install, test and commission hung-type AHU, nominal 5 RT / 1,500 CFM, G4 + F7 filtration, external static pressure approximately 150 Pa, with cooling coil, drain pan, fan/motor, access sections, controls, vibration isolation and flexible connections. | D10: No | E10: 2 | F10: 1800000 | G10: =E10*F10 -> 3600000 | H10: Engineer 2026 provisional market allowance | I10: MVAC Equipment Schedule – AHU-03 | J10: Outside Modular OT dedicated AHU scope | K10: Provisional | L10: Confirm served rooms before tender.
A11: B2 | B11: B - Non-OT airside equipment | C11: Supply, install, test and commission hung-type AHU, nominal 10 RT / 3,000 CFM, G4 + F7 filtration, approximately 400 CFM fresh air and 250 Pa external static pressure, complete with cooling coil, drain pan, fan/motor, controls and accessories. | D11: No | E11: 1 | F11: 2700000 | G11: =E11*F11 -> 2700000 | H11: Engineer 2026 provisional market allowance | I11: MVAC Equipment Schedule – AHU-04 | J11: Outside Modular OT dedicated AHU scope | K11: Provisional | L11: Confirm served rooms before tender.
A12: B3 | B12: B - Non-OT airside equipment | C12: Supply, install and commission 2-way cassette chilled-water fan-coil unit, nominal 1.0 RT, complete with control valve, thermostat, drain connection, condensate pump where required and all accessories. | D12: No | E12: 2 | F12: 450000 | G12: =E12*F12 -> 900000 | H12: Engineer provisional market allowance | I12: MVAC Equipment Schedule – FCU-01 | J12: Not in Modular OT BOQ | K12: Provisional
A13: B4 | B13: B - Non-OT airside equipment | C13: Supply, install and commission 2-way cassette chilled-water fan-coil unit, nominal 1.5 RT, complete. | D13: No | E13: 1 | F13: 550000 | G13: =E13*F13 -> 550000 | H13: Engineer provisional market allowance | I13: MVAC Equipment Schedule – FCU-02 | J13: Not in Modular OT BOQ | K13: Provisional
A14: B5 | B14: B - Non-OT airside equipment | C14: Supply, install and commission 2-way cassette chilled-water fan-coil unit, nominal 0.75 RT, complete. | D14: No | E14: 3 | F14: 400000 | G14: =E14*F14 -> 1200000 | H14: Engineer provisional market allowance | I14: MVAC Equipment Schedule – FCU-03 | J14: Not in Modular OT BOQ | K14: Provisional
A15: B6 | B15: B - Non-OT airside equipment | C15: Supply, install and commission 2-way cassette chilled-water fan-coil unit, nominal 2.0 RT, complete. | D15: No | E15: 1 | F15: 700000 | G15: =E15*F15 -> 700000 | H15: Engineer provisional market allowance | I15: MVAC Equipment Schedule – FCU-04 | J15: Not in Modular OT BOQ | K15: Provisional
A16: B7 | B16: B - Non-OT airside equipment | C16: Supply, install, test and commission duct-mounted silent exhaust fan, 750 CFM at approximately 200 Pa, complete with flexible connectors, vibration isolation, supports, backdraft damper and electrical isolator. | D16: No | E16: 1 | F16: 450000 | G16: =E16*F16 -> 450000 | H16: Engineer provisional market allowance | I16: MVAC Equipment Schedule – EF-02 | J16: Not identified as Modular OT exhaust fan | K16: Provisional | L16: Confirm served zone; exclude if found to serve an OT.
A17: B8 | B17: B - Non-OT airside equipment | C17: Supply, install and commission wall-mounted silent toilet exhaust fan, approximately 200 CFM, complete with louvre/backdraft shutter, wiring connection and accessories. | D17: No | E17: 6 | F17: 120000 | G17: =E17*F17 -> 720000 | H17: Engineer provisional market allowance | I17: MVAC Equipment Schedule – TEF-01 | J17: Not in Modular OT BOQ | K17: Provisional
A18: C1 | B18: C - Air distribution outside OT package | C18: Fabricate and install GI supply/return/fresh-air ductwork serving non-OT areas, including fittings, transitions, turning vanes, supports, hangers, access doors, flexible connections, sealants and external thermal insulation where required. OT ductwork from dedicated OT AHU to LAF/OT terminals is expressly excluded. | D18: m² | E18: 450 | F18: 22000 | G18: =E18*F18 -> 9900000 | H18: Preliminary composite rate; final by sheet-metal gauge/insulation class | I18: MVAC plan take-off allowance | J18: OT ductwork excluded – Modular OT D4 | K18: Provisional Qty | L18: Remeasure from final CAD/shop drawings.
A19: C2 | B19: C - Air distribution outside OT package | C19: Fabricate and install GI exhaust-air ductwork serving non-OT areas, complete with fittings, supports, sealants, access doors and flexible connections. OT exhaust/return ductwork included in the Modular OT package is excluded. | D19: m² | E19: 120 | F19: 14000 | G19: =E19*F19 -> 1680000 | H19: Preliminary composite rate | I19: MVAC plan take-off allowance | J19: OT exhaust ductwork excluded – Modular OT D3/D4 | K19: Provisional Qty | L19: Remeasure from final CAD/shop drawings.
A20: C3 | B20: C - Air distribution outside OT package | C20: Supply and install non-OT supply diffusers, return grilles, exhaust grilles and outdoor fresh/exhaust air louvers with demister filters/VCDs where scheduled, including neck adaptors, plenums, supports and finishes. | D20: LS | E20: 1 | F20: 2500000 | G20: =E20*F20 -> 2500000 | H20: Engineer provisional allowance | I20: MVAC Air Terminal Schedule | J20: Exclude LAF diffusers/OT terminal connections | K20: Provisional | L20: Final quantities by coordinated reflected ceiling plan.
A21: D1 | B21: D - Chilled/condenser water distribution | C21: Supply, install, pressure-test, flush, chemically clean and commission complete chilled-water supply and return pipework system from central plant to all non-OT AHUs/FCUs and up to agreed connection points for OT-package AHUs; including approved pipework, fittings, supports, sleeves, valves, strainers, balancing/control valves, thermometers, pressure gauges, air vents, drains, insulation, vapour barrier and identification. | D21: LS | E21: 1 | F21: 12000000 | G21: =E21*F21 -> 12000000 | H21: Engineer provisional allowance based on drawing network | I21: MVAC plan – CHWS/CHWR 25–100 mm | J21: OT AHUs excluded; distribution/interface retained | K21: Provisional | L21: Replace by measured diameter-by-diameter schedule before tender.
A22: D2 | B22: D - Chilled/condenser water distribution | C22: Supply, install, pressure-test and commission complete condenser-water supply/return pipework between chillers, pumps and cooling towers, including fittings, supports, isolation/check/balancing valves, strainers, gauges, drains, make-up/overflow interfaces and painting/identification. | D22: LS | E22: 1 | F22: 5500000 | G22: =E22*F22 -> 5500000 | H22: Engineer provisional allowance based on drawing network | I22: MVAC plan – CWS/CWR incl. 100/200 mm | J22: Not in Modular OT BOQ | K22: Provisional | L22: Final diameter/length take-off required.
A23: D3 | B23: D - Chilled/condenser water distribution | C23: Provide final chilled-water supply/return connection interface to each Modular OT-package AHU connection point, including isolation valves, balancing/control valve interface, flexible connectors, drain/air vent, gauges and insulation. AHU itself excluded. | D23: No | E23: 4 | F23: 500000 | G23: =E23*F23 -> 2000000 | H23: Engineer interface allowance | I23: MVAC / Modular OT interface | J23: Prevents gap without duplicating AHU | K23: Provisional | L23: Connection point to be defined on coordinated shop drawings.
A24: D4 | B24: D - Condensate drainage | C24: Supply and install uPVC Type 600 insulated condensate drain piping from all non-OT AHUs and FCUs to approved discharge points, including traps, fittings, supports, cleanouts and testing. | D24: LS | E24: 1 | F24: 1500000 | G24: =E24*F24 -> 1500000 | H24: Engineer provisional allowance | I24: MVAC drawing Note 2 & 3 | J24: OT condensate within OT package only if supplied there | K24: Provisional
A25: E1 | B25: E - Controls and BMS | C25: Provide complete plant and non-OT HVAC automatic controls/BMS interface, including chiller/pump/cooling-tower sequencing, AHU/FCU controls, temperature sensors, control valves/actuators, status/alarm points, interlocks and fire-alarm shutdown interface. OT room pressure/temperature/RH sensors and OT control-panel functions are excluded. | D25: LS | E25: 1 | F25: 4000000 | G25: =E25*F25 -> 4000000 | H25: Engineer provisional controls allowance | I25: MVAC drawing notes and equipment schedule | J25: OT controls excluded – Modular OT D5 | K25: Provisional
A26: E2 | B26: E - Electrical for MVAC | C26: Provide local MVAC equipment control/interconnection wiring, local isolator/interface allowance and control-panel terminations not included with packaged equipment. Main DB-AC, feeder cables and final power wiring to chillers/AHUs/cooling towers/FCUs are excluded and measured in the reviewed Electrical BOQ. | D26: LS | E26: 1 | F26: 1000000 | G26: =E26*F26 -> 1000000 | H26: Revised interface-only allowance after receipt of detailed Electrical BOQ | I26: MVAC equipment schedule | J26: Electrical BOQ now governs DB-AC and power feeders/cables | K26: Provisional | L26: Reduced from LKR 5.0m to LKR 1.0m to remove duplication with Electrical BOQ.
A27: E3 | B27: E - Testing, balancing and commissioning | C27: Testing, adjusting and balancing of complete central plant and non-OT air/water systems, flushing, pressure testing, water balancing, air balancing, controls functional testing and commissioning reports. Specialist OT cleanroom validation (HEPA leak, particle count, microbiology, smoke visualisation) is excluded. | D27: LS | E27: 1 | F27: 2500000 | G27: =E27*F27 -> 2500000 | H27: Engineer provisional allowance | I27: MVAC requirements | J27: OT validation excluded – Modular OT F1 | K27: Provisional
A28: E4 | B28: E - Documentation and training | C28: Coordinated shop drawings, equipment selections, calculations, builders-work drawings, as-built drawings, O&M manuals, warranties, spare-parts schedules and training for the MVAC system, excluding duplicate Modular OT package deliverables. | D28: LS | E28: 1 | F28: 1000000 | G28: =E28*F28 -> 1000000 | H28: Engineer provisional allowance | I28: Project deliverables | J28: OT duplicate documents excluded | K28: Provisional
F31: BOQ Subtotal | G31: =SUM(G5:G28) -> 98100000

Sheet MVAC Scope Reconciliation
A1: MVAC / MODULAR OPERATING THEATRE – SCOPE RECONCILIATION
A3: Scope Element | B3: Modular OT Existing BOQ | C3: MVAC Drawing | D3: Treatment in this MVAC BOQ | E3: Reason | F3: Connection / Boundary | G3: Risk | H3: Action
A4: OT Laminar-flow ceiling / H14 HEPA | B4: D1 – 4 No | C4: 1200x600 laminar-flow diffusers shown at OTs | D4: EXCLUDED | E4: Already priced in Modular OT package | F4: MVAC airside terminates at modular OT package interface | G4: High duplication risk | H4: Retain only in Modular OT BOQ
A5: Dedicated hygienic OT AHUs | B5: D2 – 4 No dedicated hygienic AHUs | C5: AHU-01/AHU-02 and other AHUs shown | D5: OT-serving AHUs EXCLUDED; AHU-03/AHU-04 retained only as non-OT | E5: Modular package explicitly prices dedicated OT AHUs | F5: Central CHW distribution to agreed OT AHU connection point remains in MVAC | G5: High | H5: Confirm final AHU-to-room mapping before tender
A6: OT exhaust/return fan sets | B6: D3 – 4 No | C6: EF-01/EF-02 shown | D6: Any fan serving OT EXCLUDED; EF-02 retained provisionally only if non-OT | E6: Avoid duplicate OT exhaust fan sets | F6: Non-OT ventilation remains MVAC | G6: Medium/High | H6: Confirm EF served areas
A7: OT ductwork/insulation/dampers | B7: D4 – 4 LS | C7: Extensive SA/EA/RA ductwork shown | D7: OT routes EXCLUDED; non-OT ductwork retained | E7: Modular package includes OT ductwork and clean terminal connections | F7: Define physical boundary at OT-package AHU/LAF/room interfaces | G7: High | H7: Mark excluded duct routes on coordinated drawing
A8: OT pressure/temp/RH controls | B8: D5 – 4 No | C8: Controls implied | D8: EXCLUDED | E8: Already priced per theatre | F8: Plant/non-OT BMS only under MVAC | G8: High | H8: Provide separate point schedule
A9: OT HEPA initial/spares | B9: D6 – LS | C9: Not separately scheduled | D9: EXCLUDED | E9: Already priced | F9: N/A | G9: High | H9: Retain only in Modular OT BOQ
A10: OT validation | B10: F1 – 4 No | C10: MVAC T&C required | D10: Specialist cleanroom/OT validation EXCLUDED; general TAB retained | E10: Already priced in Modular OT package | F10: MVAC contractor provides data/support to validator | G10: High | H10: Coordinate witness/acceptance tests
A11: Central chillers/pumps/cooling towers | B11: Not included | C11: CH-01, CHWP-01, CWP-01, CT-01 scheduled | D11: INCLUDED | E11: Central utility plant is outside modular room package | F11: Serves whole renovated HVAC system including OT connection points | G11: Low | H11: Obtain supplier quotations
A12: CHW/CW distribution | B12: Not specifically included except OT ductwork | C12: CHWS/CHWR/CWS/CWR shown | D12: INCLUDED | E12: Required central distribution; not duplicated by modular HVAC airside items | F12: Terminate at agreed modular AHU valve/flexible-connection point | G12: Medium | H12: Issue interface matrix
A13: Non-OT AHUs/FCUs/toilet ventilation | B13: Not included | C13: AHU-03/AHU-04, FCU-01..04, TEF-01 | D13: INCLUDED | E13: Outside modular theatre room package | F13: Full MVAC scope | G13: Low | H13: Confirm room mapping

Sheet MVAC Rates & Basis
A1: MVAC ENGINEER'S ESTIMATE – RATE BASIS / QUALIFICATIONS
A3: Ref | B3: Item / Application | C3: Unit | D3: Applied Rate (LKR) | E3: Rate Type | F3: Primary Basis | G3: Source | H3: Quotation Needed | I3: Confidence | J3: Qualification
A4: R01 | B4: 50 RT water-cooled screw chiller | C4: No | D4: 13500000 | E4: Engineer provisional market allowance | F4: Budget allowance for 2026 Sri Lanka supply/install; specialist quotation required | G4: MVAC Schedule CH-01 | H4: Yes – 3 quotes | I4: Low/Medium | J4: Not a published BSR item.
A5: R02 | B5: CHW pump 130 GPM @ 30m | C5: No | D5: 1200000 | E5: Engineer provisional market allowance | F5: Pump, motor, base, valves/flexible connections and installation | G5: MVAC Schedule CHWP-01 | H5: Yes | I5: Medium | J5: Final duty/efficiency and VSD requirement affect rate.
A6: R03 | B6: Condenser pump 160 GPM @ 20m | C6: No | D6: 1100000 | E6: Engineer provisional market allowance | F6: Pump, motor, base, valves/flexible connections and installation | G6: MVAC Schedule CWP-01 | H6: Yes | I6: Medium
A7: R04 | B7: 75 RT cooling tower | C7: No | D7: 4500000 | E7: Engineer provisional market allowance | F7: Cross-flow induced-draft package including local installation | G7: MVAC Schedule CT-01 | H7: Yes | I7: Low/Medium | J7: Structural platform excluded unless added.
A8: R05 | B8: 5 RT hung AHU | C8: No | D8: 1800000 | E8: Engineer provisional market allowance | F8: G4+F7 filters, coil, fan, drain pan, controls/basic accessories | G8: MVAC Schedule AHU-03 | H8: Yes | I8: Medium
A9: R06 | B9: 10 RT hung AHU | C9: No | D9: 2700000 | E9: Engineer provisional market allowance | F9: G4+F7 filters, coil, fan, controls/basic accessories | G9: MVAC Schedule AHU-04 | H9: Yes | I9: Medium
A10: R07 | B10: FCU 0.75–2.0 RT | C10: No | D10: 400,000–700,000 | E10: Engineer provisional market allowance | F10: 2-way cassette chilled-water FCU with controls and drain | G10: MVAC Schedule FCU-01..04 | H10: Yes | I10: Medium | J10: Rate varies by capacity.
A11: R08 | B11: Insulated GI SA/RA/FA ductwork | C11: m² | D11: 22000 | E11: Composite provisional | F11: Fabrication + fittings/supports + insulation; final rate to be built by gauge and insulation thickness | G11: MVAC drawing | H11: Recommended | I11: Low/Medium | J11: OT routes excluded.
A12: R09 | B12: GI exhaust ductwork | C12: m² | D12: 14000 | E12: Composite provisional | F12: Fabrication + fittings/supports; insulation excluded unless required | G12: MVAC drawing | H12: Recommended | I12: Low/Medium | J12: OT routes excluded.
A13: R10 | B13: CHW distribution | C13: LS | D13: 12000000 | E13: Engineer provisional allowance | F13: Network visible on drawing; final diameter-by-diameter take-off required | G13: MVAC drawing | H13: Yes / measured RA | I13: Low | J13: Replace LS with measured schedule before tender.
A14: R11 | B14: Condenser-water distribution | C14: LS | D14: 5500000 | E14: Engineer provisional allowance | F14: CWS/CWR network between chillers, pumps and towers | G14: MVAC drawing | H14: Yes / measured RA | I14: Low | J14: Replace LS with measured schedule before tender.
A15: R12 | B15: Plant/non-OT BMS controls | C15: LS | D15: 4000000 | E15: Engineer provisional allowance | F15: Excludes OT room controls already in Modular OT D5 | G15: MVAC + Modular OT reconciliation | H15: Yes | I15: Medium
A16: R13 | B16: General MVAC T&C/TAB | C16: LS | D16: 2500000 | E16: Engineer provisional allowance | F16: Excludes OT cleanroom validation in Modular OT F1 | G16: Scope reconciliation | H16: Recommended | I16: Medium
A19: SOURCE / GOVERNANCE NOTES
A20: 1 | B20: The uploaded MVAC equipment schedule is the governing basis for capacities and scheduled quantities in this estimate.
A21: 2 | B21: The existing 'Modular OT - Unchanged' BOQ already contains D1–D6 for LAF/HVAC and F1 validation; those items are not re-priced here.
A22: 3 | B22: Department of Buildings has a 2026 BSR system; Southern Provincial Council publishes a 2026 Matara BSR. Specialist central HVAC plant is not reliably priced by generic BSR and should be supported by current supplier quotations.
A23: 4 | B23: All duct and pipe quantities in this sheet are preliminary allowances because the uploaded drawings are PDF plan sheets rather than measurable CAD/BIM files.
A24: 5 | B24: VAT is excluded. A 10% design-development contingency is shown separately and is not a tender BOQ item.

Sheet Medical Gas BOQ & Estimate
A1: DISTRICT GENERAL HOSPITAL MATARA – MEDICAL GAS SYSTEM BOQ & ENGINEER'S ESTIMATE
A2: Preliminary estimate for the renovated OT complex. OT pendants and the 8 modular-theatre medical-gas terminal boxes are excluded from this BOQ to prevent duplication; this BOQ includes source/plant renovation, pipeline distribution, zone valves/alarms, non-OT patient outlets, interfaces, testing and commissioning.
A4: Item | B4: Section | C4: BOQ Description | D4: Unit | E4: Qty | F4: Rate (LKR) | G4: Amount (LKR) | H4: Rate Basis | I4: Source / Basis | J4: Duplication Check | K4: Status | L4: Remarks
A5: A1 | B5: A - Design, survey & enabling | C5: Detailed site survey and tracing of existing medical-gas services; verify live systems, source equipment, routes, pressures, pipe sizes and connection points; prepare design calculations, medical-gas schematic, zoning philosophy, shop drawings, penetration/support details and coordinated interface drawings in accordance with ISO 7396-1 / ISO 9170-1 and adopted hospital requirements. | D5: LS | E5: 1 | F5: 60000 | G5: =E5*F5 -> 60000 | H5: Engineer provisional specialist allowance | I5: Uploaded medical-gas DWG + Matara project documents | J5: No duplication | K5: Provisional | L5: Final design and quantities to be verified from CAD and site survey.
A6: A2 | B6: A - Design, survey & enabling | C6: Temporary isolation, shutdown planning, permit-to-work, purging, temporary caps/bypasses and safe continuity arrangements required to execute the medical-gas works within an operating hospital, complete. | D6: LS | E6: 1 | F6: 800000 | G6: =E6*F6 -> 800000 | H6: Engineer provisional specialist allowance | I6: Hospital refurbishment / live-services requirement | J6: General civil strip-out excludes specialist reconnection | K6: Provisional | L6: Coordinate shutdowns with hospital management.
A7: B1 | B7: B - Medical-gas plant / source systems | C7: Renovation and upgrade of the existing oxygen manifold/source system in the medical-gas plant room, including inspection and replacement as necessary of manifold headers, regulators, non-return valves, isolation valves, flexible cylinder tails, pressure switches, emergency reserve/changeover components, gauges, labels and associated source alarm interfaces; complete tested and recommissioned system. | D7: PS | E7: 1 | F7: 3000000 | G7: =E7*F7 -> 3000000 | H7: Engineer provisional sum – specialist market allowance | I7: Project scope confirms renovation of medical-gas plant room | J7: Not in Modular OT package | K7: Provisional Sum | L7: Final scope subject to condition survey and specialist quotation.
A8: B2 | B8: B - Medical-gas plant / source systems | C8: Overhaul/upgrade and recommission existing medical compressed-air source plant serving the OT complex, including compressors, receiver, dryers/filters, regulators, safety devices, drains, controls and alarms as required to restore compliant duty/standby operation. | D8: PS | E8: 1 | F8: 4000000 | G8: =E8*F8 -> 4000000 | H8: Engineer provisional sum – specialist market allowance | I8: Matara medical-gas requirements include Medical Air | J8: Not in Modular OT package | K8: Provisional Sum | L8: If complete replacement is required, reprice from approved supplier quotation.
A9: B3 | B9: B - Medical-gas plant / source systems | C9: Overhaul/upgrade and recommission existing medical vacuum source plant serving the OT complex, including pumps, receiver, bacterial filters, separators, controls, duty/standby sequencing, isolation and alarm interfaces, complete. | D9: PS | E9: 1 | F9: 4000000 | G9: =E9*F9 -> 4000000 | H9: Engineer provisional sum – specialist market allowance | I9: Matara medical-gas requirements include Vacuum | J9: Not in Modular OT package | K9: Provisional Sum | L9: If complete replacement is required, reprice from approved supplier quotation.
A10: B4 | B10: B - Medical-gas plant / source systems | C10: Provide or upgrade anaesthetic gas scavenging system (AGSS) plant/pump arrangement, including receiver/separator where applicable, controls, duty arrangements, exhaust discharge, vibration isolation and all accessories required to serve the operating theatres. | D10: PS | E10: 1 | F10: 2500000 | G10: =E10*F10 -> 2500000 | H10: Engineer provisional specialist allowance | I10: Matara equipment schedule identifies AGSS outlets | J10: OT outlet hardware excluded; central AGSS source retained here | K10: Provisional Sum | L10: Confirm whether existing AGSS plant can be retained.
A11: B5 | B11: B - Medical-gas plant / source systems | C11: Medical-gas plant master alarm / source-status panel and alarm interface, including pressure/vacuum switches, low/high alarms, source changeover/fault indication, audible/visual alarms, volt-free/BMS contacts and cabling from source equipment. | D11: No | E11: 1 | F11: 900000 | G11: =E11*F11 -> 900000 | H11: Engineer provisional specialist allowance | I11: ISO 7396-1 source alarm requirement | J11: OT local control-panel repeater functions excluded | K11: Provisional
A12: C1 | B12: C - Medical-gas pipeline distribution | C12: Supply and install degreased seamless copper tube suitable for medical-gas service, 15 mm nominal outside diameter, including medical-gas fittings, silver brazing under nitrogen purge, supports, sleeves, identification, access coordination and all accessories. | D12: m | E12: 260 | F12: 9000 | G12: =E12*F12 -> 2340000 | H12: Preliminary installed composite rate | I12: Uploaded medical-gas DWG – provisional takeoff allowance | J12: Distribution only; outlet hardware separate | K12: Provisional Qty | L12: Re-measure from final CAD/shop drawings.
A13: C2 | B13: C - Medical-gas pipeline distribution | C13: As above, 22 mm nominal outside diameter medical-gas copper tube. | D13: m | E13: 220 | F13: 13000 | G13: =E13*F13 -> 2860000 | H13: Preliminary installed composite rate | I13: Uploaded medical-gas DWG – provisional takeoff allowance | J13: No duplication | K13: Provisional Qty | L13: Re-measure from final CAD/shop drawings.
A14: C3 | B14: C - Medical-gas pipeline distribution | C14: As above, 28 mm nominal outside diameter medical-gas copper tube. | D14: m | E14: 140 | F14: 17000 | G14: =E14*F14 -> 2380000 | H14: Preliminary installed composite rate | I14: Uploaded medical-gas DWG – provisional takeoff allowance | J14: No duplication | K14: Provisional Qty | L14: Re-measure from final CAD/shop drawings.
A15: C4 | B15: C - Medical-gas pipeline distribution | C15: As above, 35 mm nominal outside diameter medical-gas copper tube. | D15: m | E15: 80 | F15: 23000 | G15: =E15*F15 -> 1840000 | H15: Preliminary installed composite rate | I15: Uploaded medical-gas DWG – provisional takeoff allowance | J15: No duplication | K15: Provisional Qty | L15: Re-measure from final CAD/shop drawings.
A16: C5 | B16: C - Medical-gas pipeline distribution | C16: As above, 42 mm nominal outside diameter medical-gas copper tube. | D16: m | E16: 40 | F16: 31000 | G16: =E16*F16 -> 1240000 | H16: Preliminary installed composite rate | I16: Uploaded medical-gas DWG – provisional takeoff allowance | J16: No duplication | K16: Provisional Qty | L16: Re-measure from final CAD/shop drawings.
A17: C6 | B17: C - Medical-gas pipeline distribution | C17: Specialist tie-in to existing medical-gas plant/header/risers including shutdown, cutting, brazed connections, isolation valves, pressure testing and recommissioning, per gas service. | D17: No | E17: 4 | F17: 250000 | G17: =E17*F17 -> 1000000 | H17: Engineer specialist interface allowance | I17: Four services: Oxygen, Air, Vacuum, AGSS | J17: No duplication | K17: Provisional | L17: Nitrous oxide is not included unless subsequently confirmed.
A18: C7 | B18: C - Medical-gas pipeline distribution | C18: Pipe identification, flow arrows, valve/service labels, ceiling markers and durable identification throughout the complete medical-gas installation, including updated schematic and valve register. | D18: LS | E18: 1 | F18: 500000 | G18: =E18*F18 -> 500000 | H18: Engineer allowance | I18: ISO 7396-1 / hospital identification requirement | J18: No duplication | K18: Provisional
A19: D1 | B19: D - Zone valves & alarms | C19: Four-service area valve service unit (AVSU) for each operating theatre zone, suitable for Oxygen, Medical Air, Vacuum and AGSS as applicable, complete with lockable box, isolation valves, gauges/test points, labels and flush/recessed mounting. | D19: No | E19: 4 | F19: 450000 | G19: =E19*F19 -> 1800000 | H19: Engineer provisional specialist market allowance | I19: Four operating theatres / medical-gas zoning | J19: Terminal boxes/pendants remain in Modular OT package | K19: Provisional | L19: Final gas services per OT to approved medical-gas schematic.
A20: D2 | B20: D - Zone valves & alarms | C20: Three-service area valve service unit (AVSU) for Recovery / ICU / Isolation clinical zones, suitable for Oxygen, Medical Air and Vacuum, complete with valves, gauges/test points, labels and enclosure. | D20: No | E20: 4 | F20: 380000 | G20: =E20*F20 -> 1520000 | H20: Engineer provisional specialist market allowance | I20: Recovery + ICU support areas | J20: No duplication | K20: Provisional | L20: Final zoning to be confirmed.
A21: D3 | B21: D - Zone valves & alarms | C21: Area medical-gas alarm panel for clinical zone, monitoring Oxygen pressure, Medical Air pressure, Vacuum and AGSS status where applicable, complete with audible/visual indication, mute/test, PSU and interface wiring. | D21: No | E21: 2 | F21: 650000 | G21: =E21*F21 -> 1300000 | H21: Engineer provisional specialist market allowance | I21: OT suite and Recovery/ICU alarm zones | J21: OT control panels may repeat alarms; primary alarm panel retained here | K21: Provisional
A22: D4 | B22: D - Zone valves & alarms | C22: Line isolation valves / branch valves suitable for medical-gas service, including lockable valve box, identification and access panel where required. | D22: No | E22: 12 | F22: 90000 | G22: =E22*F22 -> 1080000 | H22: Engineer provisional specialist allowance | I22: Pipeline zoning allowance | J22: No duplication | K22: Provisional Qty | L22: Confirm count from final schematic.
A23: E1 | B23: E - Terminal units & OT interfaces | C23: Medical-gas terminal outlet to non-OT patient spaces, BS/ISO compatible type as approved, for Oxygen, Medical Air or Vacuum, complete with first-fix box, second-fix terminal, colour/service identification and connection to pipeline. Quantity allows a minimum one Oxygen + one Air + one Vacuum outlet at each of 17 Recovery/ICU patient spaces. | D23: No | E23: 51 | F23: 55000 | G23: =E23*F23 -> 2805000 | H23: Engineer provisional specialist market allowance | I23: Matara RDS: 8 Recovery + 1 Isolation Recovery + 6 ICU + 2 Isolation ICU = 17 patient spaces | J23: Excludes 8 OT terminal boxes already in Modular OT E3 | K23: Provisional Qty | L23: Final outlet multiplicity per bed to clinical user/RDS approval.
A24: E2 | B24: E - Terminal units & OT interfaces | C24: Connection of medical-gas distribution piping to each Modular OT medical-gas terminal box / pendant interface, including four-service pipe tails, local isolation as required, final brazed joints, pressure test and labelling. Terminal box / pendant itself excluded. | D24: Set | E24: 8 | F24: 125000 | G24: =E24*F24 -> 1000000 | H24: Engineer interface allowance | I24: Modular OT E3 includes 8 terminal boxes; pipeline excluded there | J24: Avoids terminal-box duplication | K24: Provisional | L24: Coordinate exact connection boundary with modular OT supplier.
A25: F1 | B25: F - Testing, commissioning & handover | C25: Pressure testing, tightness testing, cross-connection testing, particulate/cleanliness verification, gas identity testing, flow/pressure performance tests, alarm/valve tests and complete commissioning of the medical-gas pipeline system by competent specialist personnel. | D25: LS | E25: 1 | F25: 1800000 | G25: =E25*F25 -> 1800000 | H25: Engineer specialist T&C allowance | I25: ISO 7396-1 / Modular OT medical-gas validation requirement | J25: OT package validation does not include central pipeline installation tests | K25: Provisional | L25: Provide calibrated test records and certificates.
A26: F2 | B26: F - Testing, commissioning & handover | C26: Independent medical-gas quality / purity verification and final acceptance testing where required by the Employer, including test certificates for Oxygen, Medical Air, Vacuum and AGSS performance. | D26: LS | E26: 1 | F26: 1000000 | G26: =E26*F26 -> 1000000 | H26: Engineer specialist allowance | I26: Hospital commissioning requirement | J26: No duplication | K26: Provisional
A27: F3 | B27: F - Testing, commissioning & handover | C27: As-built drawings, medical-gas schematic, valve register, source/area alarm schedules, O&M manuals, preventive-maintenance schedules, recommended spare parts, warranties and training of hospital engineering/clinical staff. | D27: LS | E27: 1 | F27: 800000 | G27: =E27*F27 -> 800000 | H27: Engineer allowance | I27: Project deliverables | J27: Exclude duplicate modular OT manuals for pendants/terminal boxes | K27: Provisional
F30: BOQ Subtotal | G30: =SUM(G5:G27) -> 40525000

Sheet Medical Gas Reconciliation
A1: MEDICAL GAS / MODULAR OT / GENERAL RENOVATION – SCOPE RECONCILIATION
A3: Scope Element | B3: Existing Package / Source | C3: Treatment in Medical-Gas BOQ | D3: Reason | E3: Boundary / Interface | F3: Duplication Risk | G3: Current Allowance | H3: Action Before Tender
A4: Medical gas pendants – anaesthetist | B4: Modular OT C8 – 4 No | C4: EXCLUDED | D4: Already priced in Modular OT package | E4: Medical-gas contractor connects pipeline to pendant/terminal interface | F4: High | G4: Nil in this BOQ | H4: Freeze pendant model and outlet configuration.
A5: Surgical pendant / monitor support arm | B5: Modular OT C9 – 4 No | C5: EXCLUDED | D5: Already priced in Modular OT package | E5: Only gas pipe connection retained where the pendant carries gas outlets | F5: High | G5: Nil in this BOQ | H5: Confirm which pendant contains gas outlets.
A6: OT medical-gas terminal boxes | B6: Modular OT E3 – 8 No, 5 terminals each; explicitly excludes pipeline | C6: EXCLUDED terminal boxes; INCLUDED pipeline connection | D6: Avoid double-counting terminal hardware while closing pipeline interface | E6: Boundary at inlet/tail connection to supplied terminal box/pendant | F6: High | G6: 8 connection sets | H6: Issue interface matrix with modular supplier.
A7: OT control-panel gas alarm repeater/interface | B7: Modular OT C5 control panel | C7: EXCLUDED local repeater hardware | D7: Control panel already priced; central/area alarm remains medical-gas scope | E7: Medical-gas alarm provides volt-free/repeater interface | F7: High | G7: Primary area alarms only | H7: Confirm signal protocol and wiring responsibility.
A8: Medical-gas pipeline distribution | B8: Not included in Modular OT E3 | C8: INCLUDED | D8: Modular BOQ expressly excludes pipeline system | E8: From source plant through valves to OT connection points and non-OT outlets | F8: Low | G8: 740 m provisional copper tube | H8: Final CAD takeoff required.
A9: Recovery/ICU patient outlets | B9: Matara RDS identifies 17 patient spaces | C9: INCLUDED | D9: Outside Modular OT package | E9: Minimum one O2 + Air + Vacuum per patient space assumed | F9: Low/Medium | G9: 51 outlets | H9: Confirm outlet multiplicity with clinical user.
A10: Medical-gas plant room renovation | B10: Project feasibility/scope documents | C10: INCLUDED as provisional sums | D10: Explicit project scope; not in Modular OT package | E10: Existing plant/source equipment to be surveyed and retained/overhauled where viable | F10: Low | G10: O2, Air, Vacuum, AGSS source allowances | H10: Obtain condition report and three specialist quotations.
A11: General wall/ceiling repairs to plant room | B11: Added Renovation BOQ / general civil works | C11: EXCLUDED except specialist mounting/sealing | D11: Avoid civil duplication | E11: Medical-gas BOQ includes only gas-specific supports, penetrations and making good incidental to installation | F11: Medium | G11: Nil general architectural allowance | H11: Coordinate with renovation BOQ.
A12: Existing redundant medical-gas strip-out | B12: Added Renovation BOQ Section I includes specialist isolation/removal/capping allowance | C12: EXCLUDED from this new-installation BOQ | D12: Already allowed under preparatory/strip-out works | E12: New medical-gas contractor starts after approved isolation/demolition handover | F12: Medium | G12: Nil | H12: Confirm whether contractor scope combines demolition and new installation.
A13: Nitrous oxide (N2O) | B13: Not identified in Matara equipment schedule provided | C13: NOT INCLUDED | D13: Source schedule identifies Oxygen, Air, Vacuum and AGSS | E13: Add only if final clinical brief/drawing requires it | F13: Medium | G13: Nil | H13: Obtain written clinical confirmation before tender.

Sheet Medical Gas Rates & Basis
A1: MEDICAL GAS ENGINEER'S ESTIMATE – RATE BASIS / ASSUMPTIONS
A3: Ref | B3: Item / Application | C3: Unit | D3: Applied Rate (LKR) | E3: Rate Type | F3: Basis | G3: Source / Reference | H3: Quotation Needed | I3: Confidence | J3: Qualification
A4: MG-R01 | B4: Existing oxygen manifold/source renovation | C4: PS | D4: 3000000 | E4: Engineer provisional sum | F4: Overhaul/upgrade rather than assumed complete new source plant | G4: Matara project scope – medical-gas plant room renovation | H4: Yes – minimum 3 specialist quotes | I4: Low | J4: Condition survey may substantially change cost.
A5: MG-R02 | B5: Medical air source overhaul/upgrade | C5: PS | D5: 4000000 | E5: Engineer provisional sum | F5: Allowance for duty/standby compressors, dryer/filter/control repairs or replacement components | G5: Matara equipment schedule: Medical Air | H5: Yes | I5: Low | J5: Complete replacement to be separately quoted if required.
A6: MG-R03 | B6: Medical vacuum source overhaul/upgrade | C6: PS | D6: 4000000 | E6: Engineer provisional sum | F6: Allowance for pumps, receiver, bacterial filters, controls and commissioning | G6: Matara equipment schedule: Vacuum | H6: Yes | I6: Low | J6: Complete replacement to be separately quoted if required.
A7: MG-R04 | B7: AGSS plant / source upgrade | C7: PS | D7: 2500000 | E7: Engineer provisional specialist allowance | F7: AGSS source and exhaust arrangement for four OTs | G7: Matara equipment schedule: AGSS outlets | H7: Yes | I7: Low/Medium | J7: Verify existing AGSS installation.
A8: MG-R05 | B8: 15 mm medical-gas copper pipeline installed | C8: m | D8: 9000 | E8: Composite provisional | F8: Degreased tube, fittings, nitrogen-purge brazing, supports, identification and testing allowance | G8: Specialist market allowance | H8: Recommended | I8: Medium | J8: Final rate depends on tube brand/specification and route/access.
A9: MG-R06 | B9: 22 mm medical-gas copper pipeline installed | C9: m | D9: 13000 | E9: Composite provisional | F9: As above | G9: Specialist market allowance | H9: Recommended | I9: Medium
A10: MG-R07 | B10: 28 mm medical-gas copper pipeline installed | C10: m | D10: 17000 | E10: Composite provisional | F10: As above | G10: Specialist market allowance | H10: Recommended | I10: Medium
A11: MG-R08 | B11: 35 mm medical-gas copper pipeline installed | C11: m | D11: 23000 | E11: Composite provisional | F11: As above | G11: Specialist market allowance | H11: Recommended | I11: Medium
A12: MG-R09 | B12: 42 mm medical-gas copper pipeline installed | C12: m | D12: 31000 | E12: Composite provisional | F12: As above | G12: Specialist market allowance | H12: Recommended | I12: Medium
A13: MG-R10 | B13: Four-service OT AVSU | C13: No | D13: 450000 | E13: Specialist market allowance | F13: Lockable valve box, service valves, gauges/test points and labels | G13: ISO 7396-1 zoning requirement | H13: Yes | I13: Medium | J13: Final service count may change.
A14: MG-R11 | B14: Three-service Recovery/ICU AVSU | C14: No | D14: 380000 | E14: Specialist market allowance | F14: O2 / Medical Air / Vacuum zone-valve assembly | G14: Matara RDS clinical zones | H14: Yes | I14: Medium
A15: MG-R12 | B15: Area medical-gas alarm panel | C15: No | D15: 650000 | E15: Specialist market allowance | F15: Multi-service pressure/vacuum monitoring panel with audible/visual alarms | G15: ISO 7396-1 | H15: Yes | I15: Medium
A16: MG-R13 | B16: Individual non-OT medical-gas terminal outlet | C16: No | D16: 55000 | E16: Specialist market allowance | F16: First/second fix terminal, service identity and final connection | G16: Matara RDS + modular package benchmark | H16: Yes | I16: Medium | J16: Modular OT E3 rate is not reused for its terminal boxes.
A17: MG-R14 | B17: OT terminal-box / pendant pipeline interface | C17: Set | D17: 125000 | E17: Engineer interface allowance | F17: Four-service pipe tails, final brazing, test and labels; excludes terminal hardware | G17: Modular OT E3 boundary | H17: Recommended | I17: Medium | J17: Coordinate exact physical handover point.
A20: KEY QUANTITY / SCOPE ASSUMPTIONS
A21: 1 | B21: Matara RDS schedule identifies 8 Recovery Bays, 1 Isolation Recovery, 6 ICU bed spaces and 2 Isolation ICU bed spaces = 17 patient spaces.
A22: 2 | B22: The estimate assumes a minimum one Oxygen, one Medical Air and one Vacuum outlet at each of the 17 non-OT patient spaces = 51 outlets. Clinical confirmation is required.
A23: 3 | B23: The Modular OT package already contains 8 medical-gas terminal boxes (two per theatre) and four anaesthetist pendants plus four surgical pendant/monitor allowances; these hardware items are excluded here.
A24: 4 | B24: Medical-gas copper pipeline quantities are preliminary allowances pending an exact CAD takeoff from the final coordinated medical-gas drawing and verified existing-service survey.
A25: 5 | B25: The Matara equipment schedule lists Oxygen, Medical Air, Vacuum and AGSS outlets. Nitrous oxide is not included in this estimate unless later confirmed by the clinical brief/drawing.
A26: 6 | B26: All specialist rates are budgetary installed allowances exclusive of VAT and should be replaced/validated by current quotations from competent medical-gas contractors before tender approval.
A27: 7 | B27: Testing, commissioning and certification are to comply with ISO 7396-1 / ISO 9170-1 and adopted Ministry of Health requirements.

Sheet Water Supply BOQ & Estimate
A1: DISTRICT GENERAL HOSPITAL MATARA – WATER SUPPLY SYSTEM BOQ & ENGINEER'S ESTIMATE
A2: Preliminary estimate for the renovated operating-theatre complex based on the uploaded WS drawing, room layout and existing consolidated BOQ. Sanitary fixtures, scrub sinks, redundant-water-line demolition, MVAC water systems and drainage are excluded where already measured or belonging to other packages.
A4: Item | B4: Section | C4: BOQ Description | D4: Unit | E4: Qty | F4: Rate (LKR) | G4: Amount (LKR) | H4: Rate Basis | I4: Drawing / Source | J4: Duplication Check | K4: Status | L4: Remarks
A5: A1 | B5: A - Survey, design & interfaces | C5: Detailed survey and tracing of the existing domestic-water system serving the theatre complex; verify live mains, pressures, routes, available source capacity and connection points; prepare hydraulic calculations, coordinated water-supply schematic/shop drawings, pipe sizing, valve schedule, penetration/support details and builders-work information. | D5: LS | E5: 1 | F5: 500000 | G5: =E5*F5 -> 500000 | H5: Engineer provisional allowance | I5: Uploaded Matara Hospital - MEP - WS.dwg / room layout | J5: No duplication | K5: Provisional | L5: Exact pipe lengths and pump duty to be confirmed from final CAD/shop drawings and site survey.
A6: A2 | B6: A - Survey, design & interfaces | C6: Connection to existing hospital domestic cold-water main including planned shutdown, isolation, drain-down, cut-in, new branch connection, temporary capping/bypass where required, reinstatement and making good, complete. | D6: LS | E6: 1 | F6: 400000 | G6: =E6*F6 -> 400000 | H6: Engineer provisional refurbishment allowance | I6: Existing hospital interface | J6: Existing redundant-line removal already measured under Added Renovation BOQ | K6: Provisional | L6: Coordinate shutdown with hospital engineering staff.
A7: B1 | B7: B - Cold-water pumping / pressure | C7: Supply, install, test and commission packaged domestic cold-water transfer/booster pump set comprising two pumps arranged duty/standby, vertical multistage or approved equivalent, complete with common skid, isolation/check valves, flexible connectors, pressure gauges, dry-run protection, pressure controls, local control panel/VFDs as required, automatic duty changeover, alarms and all accessories. Final flow/head to approved hydraulic calculation. | D7: Set | E7: 1 | F7: 1800000 | G7: =E7*F7 -> 1800000 | H7: Engineer provisional specialist market allowance | I7: Uploaded WS drawing – pump indicated; final duty not available from extracted drawing | J7: Not included in Modular OT / MVAC BOQs | K7: Provisional Sum | L7: Electrical feeder to pump control panel to be measured under the Electrical BOQ.
A8: B2 | B8: B - Cold-water pumping / pressure | C8: Supply and install potable-water pressure vessel / hydropneumatic accumulator, nominal 200–300 litre capacity or as selected, rated for system working pressure, complete with isolating valve, drain, pressure gauge and flexible connection. | D8: No | E8: 1 | F8: 250000 | G8: =E8*F8 -> 250000 | H8: Engineer provisional market allowance | I8: Associated booster-set allowance | J8: Not duplicated | K8: Provisional | L8: Final size to pump manufacturer's selection.
A9: C1 | B9: C - Cold-water distribution | C9: Supply and install pressure-rated uPVC / approved cold-water pipe, nominal 15 mm (1/2 in), including sockets/fittings, supports/clips, sleeves, cutting and making good, identification and all incidental accessories. | D9: m | E9: 180 | F9: 850 | G9: =E9*F9 -> 153000 | H9: Matara BSR 2026 PB46 base rate with hospital-refurbishment uplift | I9: Matara BSR 2026 / uploaded WS drawing | J9: Fixtures excluded | K9: Provisional Qty | L9: BSR PB46 base: LKR 620/m.
A10: C2 | B10: C - Cold-water distribution | C10: As above, nominal 20 mm (3/4 in) pressure-rated cold-water pipe. | D10: m | E10: 120 | F10: 1200 | G10: =E10*F10 -> 144000 | H10: Matara BSR 2026 PB47 base rate with hospital-refurbishment uplift | I10: Matara BSR 2026 / uploaded WS drawing | J10: Fixtures excluded | K10: Provisional Qty | L10: BSR PB47 base: LKR 875/m.
A11: C3 | B11: C - Cold-water distribution | C11: As above, nominal 25 mm (1 in) pressure-rated cold-water pipe. | D11: m | E11: 80 | F11: 1300 | G11: =E11*F11 -> 104000 | H11: Engineer qualified rate using Matara BSR pipe series | I11: Matara BSR 2026 / uploaded WS drawing | J11: Fixtures excluded | K11: Provisional Qty | L11: PB48 published rate appears anomalously low; qualified estimating rate adopted pending supplier quotation.
A12: C4 | B12: C - Cold-water distribution | C12: As above, nominal 32 mm (1-1/4 in) pressure-rated cold-water pipe. | D12: m | E12: 50 | F12: 1500 | G12: =E12*F12 -> 75000 | H12: Matara BSR 2026 PB49 base plus hospital installation allowance | I12: Matara BSR 2026 / uploaded WS drawing | J12: Fixtures excluded | K12: Provisional Qty | L12: BSR PB49 base: LKR 510/m; allowance includes suspended routing/support and fittings.
A13: C5 | B13: C - Cold-water distribution | C13: As above, nominal 40 mm (1-1/2 in) pressure-rated cold-water pipe. | D13: m | E13: 30 | F13: 1800 | G13: =E13*F13 -> 54000 | H13: Matara BSR 2026 PB50 base plus hospital installation allowance | I13: Matara BSR 2026 / uploaded WS drawing | J13: Fixtures excluded | K13: Provisional Qty | L13: BSR PB50 base: LKR 875/m.
A14: C6 | B14: C - Cold-water distribution | C14: As above, nominal 50 mm (2 in) pressure-rated cold-water pipe. | D14: m | E14: 20 | F14: 2300 | G14: =E14*F14 -> 46000 | H14: Matara BSR 2026 PB51 base plus hospital installation allowance | I14: Matara BSR 2026 / uploaded WS drawing | J14: Fixtures excluded | K14: Provisional Qty | L14: BSR PB51 base: LKR 1,210/m.
A15: C7 | B15: C - Cold-water distribution | C15: Approved service isolation / stop valves up to 20 mm complete with unions/adaptors, identification and accessible installation. | D15: No | E15: 20 | F15: 8000 | G15: =E15*F15 -> 160000 | H15: Matara BSR PB75/PB76 benchmark upgraded to hospital-grade valve | I15: Matara BSR 2026 | J15: Sanitary-fixture taps/angle valves excluded where included with fixture | K15: Provisional Qty | L15: Use DZR brass / approved quality where accessible for maintenance.
A16: C8 | B16: C - Cold-water distribution | C16: Approved full-bore isolation ball valves, 25–50 mm, suitable for potable-water service, including unions/flanges/adaptors and identification. | D16: No | E16: 12 | F16: 25000 | G16: =E16*F16 -> 300000 | H16: Engineer provisional market allowance | I16: Water-supply distribution | J16: No duplication | K16: Provisional Qty | L16: Final quantity by valve schedule.
... A29: F2 | B29: F - Testing, commissioning & handover | C29: As-built water-supply drawings, hydraulic calculation record, valve schedule, pump/heater data, O&M manuals, warranties, spare-parts recommendations and training of hospital engineering staff. | D29: LS | E29: 1 | F29: 250000 | G29: =E29*F29 -> 250000 | H29: Engineer deliverables allowance | I29: Project handover requirements | J29: No duplication | K29: Provisional | L29: Include final asset labels and maintenance schedules.
F32: BOQ Subtotal | G32: =SUM(G5:G29) -> 7038560

Sheet Water Supply Reconciliation
A1: WATER SUPPLY / MODULAR OT / RENOVATION / MVAC – SCOPE RECONCILIATION
A3: Scope Element | B3: Existing Package / Source | C3: Treatment in Water-Supply BOQ | D3: Reason | E3: Boundary / Interface | F3: Duplication Risk | G3: Current Allowance | H3: Action Before Tender
A4: Three-bay scrub sinks | B4: Modular OT C1 – 3 No | C4: EXCLUDED sink hardware; INCLUDED hot/cold service connection only | D4: Scrub sinks and sensor taps are already priced in Modular OT package | E4: Water-supply contractor terminates at approved sink connection points | F4: High | G4: 3 connection sets | H4: Freeze sink connection sizes/positions with modular supplier.
A5: Accessible toilet fixtures | B5: Added Renovation G1 | C5: EXCLUDED fixture hardware; INCLUDED branch water supply only | D5: WC, basin, accessories already priced under architectural renovation | E5: Terminate at local angle/stop-valve connection point | F5: High | G5: Branch/service allowance only | H5: Final fixture schedule to identify number and connection size.
A6: Staff/changing/utility sanitary fixtures | B6: Added Renovation G2 | C6: EXCLUDED fixture hardware; INCLUDED branch/final water service | D6: Existing renovation BOQ contains fixture allowance but excludes distribution pipework | E6: Water BOQ covers main/branch pipework to fixture connection point | F6: High | G6: LS branch allowance | H6: Replace LS with fixture-by-fixture points before tender.
A7: Tea/dining & equipment-washing sinks | B7: Added Renovation G3 – 2 No | C7: EXCLUDED sink/worktop hardware; INCLUDED hot/cold final connection | D7: Sink/worktop already measured separately | E7: Water contractor provides local isolation and connection tails | F7: High | G7: 2 connections | H7: Coordinate tap type and hot-water demand.
A8: Redundant water/plumbing lines | B8: Added Renovation Section I / service strip-out | C8: EXCLUDED | D8: Demolition/capping already allowed under enabling works | E8: New water-supply scope begins at approved retained system connection | F8: Medium | G8: Nil | H8: Confirm split if same specialist contractor carries both scopes.
A9: Cooling-tower makeup / chilled & condenser water | B9: MVAC BOQ | C9: EXCLUDED | D9: These are HVAC process-water systems, not domestic water supply | E9: Any domestic source branch to MVAC shall be assigned to one package only | F9: High | G9: Nil | H9: Confirm interface at coordination stage.
A10: Domestic drainage / soil & waste | B10: Not included in this Water Supply BOQ | C10: EXCLUDED | D10: Separate drainage package required | E10: Water BOQ stops at fixture water connection; drains/traps/mains separate | F10: Low | G10: Nil | H10: Prepare drainage BOQ separately.
A11: Fire-water system | B11: Not part of uploaded domestic WS scope | C11: EXCLUDED | D11: Fire protection is a separate life-safety system | E11: No interface except shared incoming utility where approved | F11: Low | G11: Nil | H11: Price separately if fire-water alterations are required.
A12: Water-storage tank | B12: No confirmed capacity identified from accessible source information | C12: NOT PRICED as a new tank | D12: Avoid assuming replacement where existing hospital storage may be retained | E12: Booster set assumed connected to existing suitable source/storage | F12: Medium | G12: Nil | H12: Confirm existing tank capacity/condition and WS drawing requirement.
A13: Electrical supply to pump/heaters | B13: Future / separate Electrical BOQ | C13: EXCLUDED except local packaged controls | D13: Avoid double-counting electrical feeders/isolators | E13: Water package includes pump local controls; incoming feeder by electrical trade | F13: Medium | G13: Nil | H13: Coordinate loads and isolator positions.

Sheet Water Supply Rates & Basis
A1: WATER SUPPLY ENGINEER'S ESTIMATE – RATE BASIS / ASSUMPTIONS
A3: Ref | B3: Item / Application | C3: Unit | D3: Applied Rate (LKR) | E3: Rate Type | F3: Basis | G3: Source / URL | H3: Quotation Needed | I3: Confidence | J3: Qualification
A4: WS-R01 | B4: 15 mm (1/2 in) cold-water pipe | C4: m | D4: 850 | E4: BSR-based qualified rate | F4: Matara BSR PB46 = LKR 620/m; uplift for hospital suspended/concealed installation, supports and coordination | G4: https://www.cs.sp.gov.lk/css/csw/rates/bsr_matara_2026.pdf | H4: No | I4: Medium | J4: Final material/specification to approved WS design.
A5: WS-R02 | B5: 20 mm (3/4 in) cold-water pipe | C5: m | D5: 1200 | E5: BSR-based qualified rate | F5: Matara BSR PB47 = LKR 875/m; hospital-refurbishment uplift applied | G5: https://www.cs.sp.gov.lk/css/csw/rates/bsr_matara_2026.pdf | H5: No | I5: Medium
A6: WS-R03 | B6: 25 mm (1 in) cold-water pipe | C6: m | D6: 1300 | E6: Engineer qualified rate | F6: Matara BSR PB48 published value is anomalously low relative to adjacent sizes; conservative engineer rate used | G6: https://www.cs.sp.gov.lk/css/csw/rates/bsr_matara_2026.pdf | H6: Recommended | I6: Low/Medium | J6: Replace by approved material quotation/rate analysis before tender.
A7: WS-R04 | B7: 32 mm (1-1/4 in) cold-water pipe | C7: m | D7: 1500 | E7: BSR-based qualified rate | F7: Matara BSR PB49 base = LKR 510/m plus fittings/support/refurbishment allowance | G7: https://www.cs.sp.gov.lk/css/csw/rates/bsr_matara_2026.pdf | H7: Recommended | I7: Medium
A8: WS-R05 | B8: 40 mm (1-1/2 in) cold-water pipe | C8: m | D8: 1800 | E8: BSR-based qualified rate | F8: Matara BSR PB50 base = LKR 875/m plus hospital installation allowance | G8: https://www.cs.sp.gov.lk/css/csw/rates/bsr_matara_2026.pdf | H8: Recommended | I8: Medium
A9: WS-R06 | B9: 50 mm (2 in) cold-water pipe | C9: m | D9: 2300 | E9: BSR-based qualified rate | F9: Matara BSR PB51 base = LKR 1,210/m plus hospital installation allowance | G9: https://www.cs.sp.gov.lk/css/csw/rates/bsr_matara_2026.pdf | H9: Recommended | I9: Medium
A10: WS-R07 | B10: 1/2 in chromium-plated bib tap / hose point | C10: No | D10: 5390 | E10: Direct BSR benchmark | F10: Matara BSR PB27 | G10: https://www.cs.sp.gov.lk/css/csw/rates/bsr_matara_2026.pdf | H10: No | I10: High | J10: Local valve/connection allowance may be adjusted after final details.
A11: WS-R08 | B11: 50 L electric storage water heater | C11: No | D11: 160000 | E11: Updated government benchmark / budget allowance | F11: Department of Buildings BSR 2024 Q476 = LKR 143,968 installed; rounded/up-rated for 2026 budgeting | G11: https://www.buildings.gov.lk/images/news/im/BSR_2024_2272024.pdf | H11: Recommended | I11: Medium | J11: Electrical feeder/isolator excluded.
A12: WS-R09 | B12: 20 mm insulated hot-water PPR | C12: m | D12: 2800 | E12: Engineer market allowance | F12: Installed PPR PN20 + fittings/supports/insulation | G12: Specialist supplier quotation required | H12: Yes | I12: Low/Medium | J12: No direct Matara BSR match identified.
A13: WS-R10 | B13: 25 mm insulated hot-water PPR | C13: m | D13: 3600 | E13: Engineer market allowance | F13: Installed PPR PN20 + fittings/supports/insulation | G13: Specialist supplier quotation required | H13: Yes | I13: Low/Medium | J13: No direct Matara BSR match identified.
A14: WS-R11 | B14: Duty/standby domestic booster pump set | C14: Set | D14: 1800000 | E14: Engineer provisional specialist allowance | F14: Twin multistage pump package with controls/VFD, valves and commissioning; final flow/head not yet confirmed | G14: Uploaded WS drawing / supplier quotation required | H14: Yes – minimum 3 quotes | I14: Low | J14: Rate can change materially with duty and brand.
A15: WS-R12 | B15: Thermostatic mixing valve | C15: No | D15: 75000 | E15: Engineer provisional specialist allowance | F15: Hospital scrub service mixing valve with isolators/check/strainer arrangement | G15: Supplier quotation required | H15: Yes | I15: Low/Medium | J15: Final selected product to infection-control/clinical approval.
A18: KEY QUANTITY / SCOPE ASSUMPTIONS
A19: 1 | B19: The uploaded source is a binary DWG; the estimate therefore uses preliminary pipe-length allowances and must be remeasured from the final coordinated CAD/PDF or contractor shop drawings.
A20: 2 | B20: Cold-water material is budgeted as pressure-rated uPVC / approved equivalent using Matara BSR plumbing rates as the primary local benchmark.
A21: 3 | B21: The Modular OT specification requires hot and cold water coordination to scrub sinks; three scrub-sink zones are already priced in the Modular OT package, so only water services and heaters are included here.
A22: 4 | B22: No new domestic water-storage tank is included because the accessible source information does not establish a required new tank capacity. Existing storage/source suitability must be verified.
A23: 5 | B23: Sanitary fixtures and non-OT sinks are already allowed in Added Renovation BOQ Section G; this Water Supply BOQ excludes those fixture bodies and prices distribution/connection only.
A24: 6 | B24: Domestic drainage, sewer/soil/waste and stormwater works are excluded and should be measured in a separate drainage BOQ.
A25: 7 | B25: MVAC chilled-water, condenser-water and cooling-tower makeup equipment remain within the MVAC package and are not duplicated here.
A26: 8 | B26: All new water-supply rates and totals are exclusive of VAT; specialist pump/hot-water rates should be validated by current quotations before tender approval.

Sheet Sheet1

Sheet Wastewater & Sewer BOQ
A1: DISTRICT GENERAL HOSPITAL MATARA – WASTEWATER & SEWERAGE SYSTEM BOQ & ENGINEER'S ESTIMATE
A2: Preliminary estimate for sanitary wastewater/soil and sewerage works serving the renovated operating-theatre complex. Fixture bodies, modular scrub-sink hardware, redundant drainage demolition and MVAC condensate drains are excluded where already included in other packages.
A4: Item | B4: Section | C4: BOQ Description | D4: Unit | E4: Qty | F4: Rate (LKR) | G4: Amount (LKR) | H4: Rate Basis | I4: Drawing / Source | J4: Duplication Check | K4: Status | L4: Remarks
A5: A1 | B5: A - Survey, design & enabling | C5: Detailed survey and tracing of existing sanitary wastewater, soil, vent and sewer connections serving the theatre complex; verify pipe routes, invert levels, existing manholes/inspection chambers and final connection point; prepare coordinated drainage schematic, pipe sizing/gradient calculations, setting-out information and shop drawings. | D5: LS | E5: 1 | F5: 400000 | G5: =E5*F5 -> 400000 | H5: Engineer provisional allowance | I5: Uploaded Matara Hospital - MEP - SW & WW.dwg / room layout | J5: No duplication | K5: Provisional | L5: Exact lengths/inverts to be verified from final CAD/shop drawings and site survey.
A6: A2 | B6: A - Survey, design & enabling | C6: Temporary isolation, plugging/bypass, odour control and safe continuity arrangements required during alteration of the existing live drainage/sewer system, including temporary caps and reinstatement. | D6: LS | E6: 1 | F6: 250000 | G6: =E6*F6 -> 250000 | H6: Engineer provisional refurbishment allowance | I6: Live hospital refurbishment condition | J6: Redundant pipe removal already measured in Added Renovation BOQ | K6: Provisional | L6: Coordinate shutdown/works with hospital engineering and infection-control teams.
A7: B1 | B7: B - Internal waste / soil / vent pipework | C7: Supply and install 50 mm diameter uPVC sanitary waste pipe, approved heavy-duty/non-pressure grade, including normal bends/tees/reducers, solvent joints, supports/clamps, sleeves, access coordination, identification and local making good. | D7: m | E7: 180 | F7: 1800 | G7: =E7*F7 -> 324000 | H7: BSR-qualified composite installed rate | I7: Matara BSR 2026 PB51 used as local small-bore PVC benchmark / uploaded SW & WW drawing | J7: Fixture traps/hardware excluded | K7: Provisional Qty | L7: Re-measure from final coordinated drawing.
A8: B2 | B8: B - Internal waste / soil / vent pipework | C8: Supply and install 75 mm diameter uPVC sanitary waste pipe, including fittings, joints, supports/clamps, sleeves and access coordination, complete. | D8: m | E8: 120 | F8: 2400 | G8: =E8*F8 -> 288000 | H8: Engineer qualified installed rate | I8: Uploaded SW & WW drawing / Matara BSR pipe series benchmark | J8: No duplication | K8: Provisional Qty | L8: No direct 75 mm BSR item identified; obtain supplier rate before tender.
A9: B3 | B9: B - Internal waste / soil / vent pipework | C9: Supply and install 110 mm diameter uPVC soil/waste pipe, wall/ceiling mounted, including normal fittings, access fittings, wall clamps/supports and all accessories. | D9: m | E9: 80 | F9: 3000 | G9: =E9*F9 -> 240000 | H9: Matara BSR PB54 base with hospital-refurbishment allowance | I9: Matara BSR 2026 / uploaded SW & WW drawing | J9: No duplication | K9: Provisional Qty | L9: PB54 base benchmark: LKR 2,290/m.
A10: B4 | B10: B - Internal waste / soil / vent pipework | C10: Supply and install 50 mm diameter uPVC vent pipework including fittings, supports, roof/wall termination connection and identification, complete. | D10: m | E10: 100 | F10: 1700 | G10: =E10*F10 -> 170000 | H10: Engineer qualified installed rate | I10: Uploaded SW & WW drawing / local PVC benchmark | J10: No duplication | K10: Provisional Qty | L10: Vent termination caps/cowls measured separately where required.
A11: B5 | B11: B - Internal waste / soil / vent pipework | C11: Access/cleanout fittings to sanitary pipework, including approved door bends/tees, rodding eyes or cleanout caps and accessible cover where concealed. | D11: No | E11: 12 | F11: 15000 | G11: =E11*F11 -> 180000 | H11: Engineer composite allowance using PB55-PB60 fitting benchmarks | I11: Matara BSR 2026 | J11: No duplication | K11: Provisional Qty | L11: Final count by drainage schematic.
A12: B6 | B12: B - Internal waste / soil / vent pipework | C12: Vent terminal / cowl complete with weatherproof termination and insect protection as applicable. | D12: No | E12: 4 | F12: 12000 | G12: =E12*F12 -> 48000 | H12: Engineer provisional allowance | I12: Drainage vent termination | J12: No duplication | K12: Provisional Qty | L12: Final number/termination location to coordinated design.
A13: C1 | B13: C - Floor drainage & fixture interfaces | C13: Supply and install stainless-steel hygienic floor drain / floor trap, minimum SS304, removable grating and trapped outlet suitable for hospital wet/clinical areas, complete with waterproofing interface and connection to waste pipe. | D13: No | E13: 10 | F13: 45000 | G13: =E13*F13 -> 450000 | H13: Engineer specialist market allowance | I13: Scrub rooms, equipment-washing, accessible toilet and changing/wet areas | J13: General floor finishes/waterproofing excluded | K13: Provisional Qty | L13: Final locations to approved sanitary drainage plan.
A14: C2 | B14: C - Floor drainage & fixture interfaces | C14: Trap/waste connection set to non-OT sink or basin where not integral with the sanitary fixture package, including bottle/P trap, waste coupling interface and branch connection. | D14: No | E14: 5 | F14: 18000 | G14: =E14*F14 -> 90000 | H14: Engineer provisional allowance | I14: Support sinks/basins | J14: Fixture bodies already measured in Added Renovation BOQ | K14: Provisional Qty | L14: Delete where trap/waste fitting is confirmed included with sanitary fixture.
A15: C3 | B15: C - Floor drainage & fixture interfaces | C15: Branch drainage connection from each Modular OT scrub sink outlet to the sanitary waste system, including branch pipe, access fitting and final joint at agreed interface. Scrub sink, waste fitting/trap and sink hardware excluded. | D15: No | E15: 3 | F15: 40000 | G15: =E15*F15 -> 120000 | H15: Engineer interface allowance | I15: Modular OT C1 – three scrub sinks | J15: Avoids duplication of modular sink hardware | K15: Provisional | L15: Coordinate connection diameter/location with modular OT supplier.
A16: C4 | B16: C - Floor drainage & fixture interfaces | C16: Branch drainage connection from non-OT sink/worktop units to sanitary waste system, including branch pipe and final joint. Sink/worktop hardware excluded. | D16: No | E16: 2 | F16: 30000 | G16: =E16*F16 -> 60000 | H16: Engineer interface allowance | I16: Added Renovation BOQ G3 – RN-20 / RN-23 | J16: Sink/worktop already measured elsewhere | K16: Provisional | L16: Tea/dining and equipment-washing areas.
... A27: F3 | B27: F - Testing, commissioning & handover | C27: As-built sanitary drainage/sewer drawings, invert schedule, chamber register, O&M instructions and maintenance/rodding access schedule, including training/briefing to hospital engineering staff. | D27: LS | E27: 1 | F27: 250000 | G27: =E27*F27 -> 250000 | H27: Engineer deliverables allowance | I27: Project handover requirements | J27: No duplication | K27: Provisional | L27: Include final asset/valve/chamber identification.
F30: BOQ Subtotal | G30: =SUM(G5:G27) -> 5632000
F31: Design-development contingency | G31: 0.1
F32: Contingency Amount | G32: =G30*G31 -> 563200
F33: Engineer’s Estimate excl. VAT | G33: =G30+G32 -> 6195200
F34: VAT | G34: Excluded

Sheet Wastewater Reconciliation
A1: WASTEWATER / SEWERAGE – SCOPE RECONCILIATION WITH OTHER MATARA PACKAGES
A3: Scope Element | B3: Existing Package / Source | C3: Treatment in Wastewater BOQ | D3: Reason | E3: Boundary / Interface | F3: Duplication Risk | G3: Current Allowance | H3: Action Before Tender
A4: Three modular scrub sinks | B4: Modular OT C1 – 3 No; sink description includes drainage connection hardware | C4: EXCLUDED sink/trap hardware; INCLUDED branch drainage from agreed outlet interface | D4: Avoid duplicate sink hardware while providing connection to building drainage | E4: Wastewater contractor starts at agreed outlet after modular sink trap/waste assembly | F4: High | G4: 3 branch connections | H4: Freeze outlet size/location with modular supplier.
A5: Accessible toilet sanitary fixtures | B5: Added Renovation G1 | C5: EXCLUDED fixture bodies; INCLUDED soil/waste branch after fixture trap/pan connector | D5: WC/basin/accessories already priced in renovation BOQ | E5: Drainage contractor provides downstream sanitary pipework | F5: High | G5: Included in branch LS | H5: Issue final sanitary fixture schedule.
A6: Staff/changing/utility sanitary fixtures | B6: Added Renovation G2 | C6: EXCLUDED fixture bodies; INCLUDED downstream branch waste/soil system | D6: Renovation BOQ already includes fixture allowance | E6: Boundary after fixture trap/pan connector | F6: High | G6: Included in branch LS | H6: Replace LS with fixture-by-fixture takeoff.
A7: Tea/dining and equipment-washing sinks | B7: Added Renovation G3 – 2 No | C7: EXCLUDED sink/worktop hardware; INCLUDED waste branch connection | D7: Sink units already measured separately | E7: Wastewater contractor connects to sink outlet/trap interface | F7: High | G7: 2 connections | H7: Confirm grease-trap requirement for RN-20.
A8: Redundant plumbing/drainage strip-out | B8: Added Renovation Section I | C8: EXCLUDED | D8: Existing-service removal/capping already allowed | E8: New wastewater scope starts after approved demolition handover | F8: Medium | G8: Nil | H8: Confirm trade boundary in tender preliminaries.
A9: MVAC condensate drains | B9: MVAC BOQ D4 | C9: EXCLUDED | D9: FCU/AHU condensate drains are HVAC scope | E9: Any final discharge into sanitary system must be coordinated once and not remeasured | F9: High | G9: Nil | H9: Define connection points on coordinated MEP drawing.
A10: Water supply pipework | B10: Water Supply BOQ | C10: EXCLUDED | D10: Separate domestic-water package | E10: Only drainage from plumbing fixtures included here | F10: Low | G10: Nil | H10: Coordinate penetrations/routes.
A11: Stormwater / roof drainage | B11: Not requested under wastewater & sewerage package | C11: EXCLUDED unless specifically shown as sanitary discharge interface | D11: Roof/surface water should remain separate from foul sewer | E11: Separate stormwater BOQ if alterations are required | F11: Medium | G11: Nil | H11: Confirm drawing title/legend and whether SW means stormwater on final issue.
A12: New septic tank / soakage pit | B12: No confirmed requirement for theatre renovation | C12: NOT INCLUDED | D12: Assumed connection to existing hospital sewerage system | E12: Final connection at existing sewer/manhole | F12: Medium | G12: Nil | H12: Add only if site survey confirms no suitable sewer connection.
A13: Sewage ejector/lifting station | B13: No evidence in accessible design basis | C13: NOT INCLUDED | D13: Ground-floor system assumed to drain by gravity | E13: N/A | F13: Medium | G13: Nil | H13: Add if invert survey shows gravity drainage is not achievable.

Sheet Wastewater Rates & Basis
A1: WASTEWATER & SEWERAGE ENGINEER'S ESTIMATE – RATE BASIS / ASSUMPTIONS
A3: Ref | B3: Item / Application | C3: Unit | D3: Applied Rate (LKR) | E3: Rate Type | F3: Basis | G3: Source / URL | H3: Quotation Needed | I3: Confidence | J3: Qualification
A4: WW-R01 | B4: 50 mm internal sanitary waste pipe | C4: m | D4: 1800 | E4: BSR-qualified composite rate | F4: PB51 (2 in PVC pressure pipe) LKR 1,210/m used only as a local PVC/material-installation benchmark; uplift for sanitary fittings/supports | G4: https://www.cs.sp.gov.lk/css/csw/rates/bsr_matara_2026.pdf | H4: Recommended | I4: Medium | J4: Final approved sanitary uPVC series to be confirmed.
A5: WW-R02 | B5: 75 mm internal sanitary waste pipe | C5: m | D5: 2400 | E5: Engineer qualified rate | F5: No direct 75 mm sanitary BSR item identified; interpolated from local PVC pipe/fitting rates with hospital supports/fittings | G5: https://www.cs.sp.gov.lk/css/csw/rates/bsr_matara_2026.pdf | H5: Yes | I5: Low/Medium | J5: Obtain supplier/contractor quotation before tender.
A6: WW-R03 | B6: 110 mm wall-mounted soil/waste pipe | C6: m | D6: 3000 | E6: BSR-based qualified rate | F6: Matara BSR PB54 = LKR 2,290/m; uplift for hospital renovation, normal fittings and coordination | G6: https://www.cs.sp.gov.lk/css/csw/rates/bsr_matara_2026.pdf | H6: Recommended | I6: Medium | J6: Separate unusual fittings/access panels may be measured if material.
A7: WW-R04 | B7: 110 mm buried Type 600 sewer pipe | C7: m | D7: 3100 | E7: BSR-based qualified rate | F7: Matara BSR PB52 = LKR 2,390/m; allowance added for refurbishment coordination | G7: https://www.cs.sp.gov.lk/css/csw/rates/bsr_matara_2026.pdf | H7: No | I7: Medium/High | J7: PB52 includes excavation to 600 mm depth; final surface finishes excluded.
A8: WW-R05 | B8: 150 x 150 plastic gully trap | C8: No | D8: 6500 | E8: BSR-based qualified rate | F8: Matara BSR PB92 = LKR 4,700/No. plus local surround/connection allowance | G8: https://www.cs.sp.gov.lk/css/csw/rates/bsr_matara_2026.pdf | H8: No | I8: High
A9: WW-R06 | B9: 600 x 600 inspection chamber/manhole | C9: No | D9: 55000 | E9: BSR-based qualified rate | F9: Matara BSR BK13 = LKR 45,200/No. for approx. 2 ft x 2 ft x 2 ft chamber including base/channel/cover slab; uplift for tie-ins/refurbishment | G9: https://www.cs.sp.gov.lk/css/csw/rates/bsr_matara_2026.pdf | H9: No | I9: High | J9: Final chamber depth/cover class to drawing.
A10: WW-R07 | B10: SS304 hygienic floor drain | C10: No | D10: 45000 | E10: Engineer specialist market allowance | F10: Hospital-grade stainless floor drain with trapped outlet and cleanable removable grate | G10: Specialist supplier quotation required | H10: Yes | I10: Low/Medium | J10: Not directly covered by Matara BSR.
A11: WW-R08 | B11: Grease interceptor to pantry/tea sink | C11: No | D11: 180000 | E11: Engineer provisional market allowance | F11: Compact accessible grease trap including connections | G11: Supplier quotation required | H11: Yes | I11: Low | J11: Delete if final design confirms no grease separation is required.
A12: WW-R09 | B12: Drainage cleanout/access fitting | C12: No | D12: 15000 | E12: Composite BSR-based allowance | F12: PB55-PB60 110 mm PVC bends/tees/Y fittings range about LKR 1,630–3,010 each; allowance includes access cover, installation and hospital coordination | G12: https://www.cs.sp.gov.lk/css/csw/rates/bsr_matara_2026.pdf | H12: Recommended | I12: Medium | J12: Final size/type to drain route.
A15: KEY QUANTITY / SCOPE ASSUMPTIONS
A16: 1 | B16: The uploaded SW & WW source is a binary AutoCAD DWG. Exact entity-based pipe lengths/invert data were not recoverable in the spreadsheet workflow, so pipe quantities are preliminary allowances and must be remeasured from the final coordinated CAD/PDF/shop drawings.
A17: 2 | B17: The architectural room layout identifies scrub areas, RN-20 Tea and Dining Area, RN-23 Equipment Washing Room, RN-27 Accessible Toilet and staff changing/support rooms; these form the principal sanitary drainage demand points.
A18: 3 | B18: Ten hospital-grade floor drains are allowed provisionally for scrub/wet/equipment-washing/changing areas. Final count and outlet sizes require the sanitary layout.
A19: 4 | B19: A gravity connection to the existing hospital sewer is assumed. No new septic tank, soakage pit or sewage lifting station has been included.
A20: 5 | B20: Stormwater/roof drainage is excluded from this foul wastewater/sewerage estimate. If 'SW' on the final drawing denotes stormwater rather than soil/sewer waste, prepare a separate stormwater BOQ.
A21: 6 | B21: Sanitary fixture bodies, sinks and modular scrub-sink hardware are excluded because they are already priced in Added Renovation / Modular OT packages; downstream drainage connections are included.
A22: 7 | B22: MVAC condensate drains are excluded because they are already included in the MVAC package.
A23: 8 | B23: Final architectural floor finishes after pipe trenching remain in the renovation BOQ; this package includes only structural/local trench reinstatement necessary for the drainage work.
A24: 9 | B24: All rates and totals are exclusive of VAT. Provisional/specialist items should be validated by current supplier/contractor quotations before tender approval.

Sheet Rainwater Disposal BOQ
A1: DISTRICT GENERAL HOSPITAL MATARA – RAINWATER DISPOSAL SYSTEM BOQ & ENGINEER'S ESTIMATE
A2: Special design emphasis: courtyard rainwater is to be collected positively and diverted in a fully closed, maintainable pipe system across/over the first-floor slab through the building to an external discharge point. Provide independent emergency overflow so blockage of the primary system cannot flood the courtyard or theatre complex.
A4: Item | B4: Section | C4: BOQ Description | D4: Unit | E4: Qty | F4: Rate (LKR) | G4: Amount (LKR) | H4: Rate Basis | I4: Drawing / Source | J4: Duplication Check | K4: Status | L4: Remarks
A5: A1 | B5: A - Survey, hydraulic design & coordination | C5: Detailed survey of roof/courtyard catchments, existing rainwater outlets, slab levels, parapets and available external surface-drain connection points; prepare hydraulic sizing based on approved design rainfall, coordinated plan/profile showing invert levels and falls, first-floor slab crossing route, outlet/overflow details, supports, sleeves, access points and discharge connections. | D5: LS | E5: 1 | F5: 450000 | G5: =E5*F5 -> 450000 | H5: Engineer design allowance | I5: User design instruction + Matara MEP/architectural coordination | J5: No duplication | K5: Provisional | L5: Final pipe diameter/number must be confirmed by hydraulic calculation before tender/construction.
A6: B1 | B6: B - Courtyard collection & waterproofing | C6: Form/adjust cement-sand screed to courtyard slab to positive falls toward rainwater collection points, including preparation, bonding agent, local fillets and making good, without reducing required door thresholds or compromising waterproofing. | D6: m² | E6: 40 | F6: 3500 | G6: =E6*F6 -> 140000 | H6: Engineer provisional refurbishment rate | I6: Courtyard – provisional area allowance | J6: General internal floor finishes excluded | K6: Provisional Qty | L6: Final courtyard area and levels to measured survey.
A7: B2 | B7: B - Courtyard collection & waterproofing | C7: Provide approved flexible waterproofing membrane system to courtyard slab including surface preparation, primer, reinforced corners, minimum 300 mm upstands at walls/kerbs, detailing around rainwater outlets/penetrations and protective layer where required; complete with 48-hour pond test before covering. | D7: m² | E7: 40 | F7: 4500 | G7: =E7*F7 -> 180000 | H7: Engineer provisional waterproofing allowance | I7: Courtyard – high-risk rainwater interface | J7: Separate from toilet/wet-area waterproofing in renovation BOQ | K7: Provisional Qty | L7: Critical item due to occupied/clinical spaces below or adjacent.
A8: B3 | B8: B - Courtyard collection & waterproofing | C8: Supply and install heavy-duty courtyard linear channel drain with removable stainless-steel / hot-dip galvanized grating, trapped/silt-controlled outlet where required, complete with concrete bedding/haunch, falls, end caps and connection to rainwater pipe. | D8: m | E8: 20 | F8: 28000 | G8: =E8*F8 -> 560000 | H8: Engineer specialist market allowance | I8: Courtyard collection – provisional | J8: Not included in Site Works surface drainage | K8: Provisional Qty | L8: Final channel length/section to courtyard grading plan.
A9: B4 | B9: B - Courtyard collection & waterproofing | C9: Supply and install heavy-duty rainwater outlet / roof drain, minimum 150 mm outlet connection, with stainless-steel dome/leaf guard and removable silt basket, clamping flange compatible with waterproofing membrane and access for maintenance. | D9: No | E9: 2 | F9: 85000 | G9: =E9*F9 -> 170000 | H9: Engineer specialist market allowance | I9: Courtyard primary outlets | J9: No duplication | K9: Provisional | L9: Provide minimum two independent primary collection points.
A10: B5 | B10: B - Courtyard collection & waterproofing | C10: Provide independent emergency overflow/scupper from courtyard, sized to safely discharge externally if the primary drainage system is blocked, including stainless/HDPE outlet sleeve, weathering, external discharge piece and splash protection. | D10: No | E10: 2 | F10: 60000 | G10: =E10*F10 -> 120000 | H10: Engineer flood-resilience allowance | I10: Courtyard emergency overflow | J10: No duplication | K10: Provisional | L10: Overflow invert to be above normal ponding level but below vulnerable thresholds.
A11: C1 | B11: C - Courtyard first-floor slab crossing | C11: Supply and install fusion-welded HDPE PE100 rainwater carrier pipe, provisional 160 mm OD, laid across/over the first-floor slab through the building at continuous positive fall to the external wall, including fittings, long-radius bends, electrofusion/butt-fusion joints, anchor/fixed points, expansion allowance and identification. Final diameter to hydraulic calculation. | D11: m | E11: 35 | F11: 15000 | G11: =E11*F11 -> 525000 | H11: Engineer specialist installed allowance | I11: Special courtyard crossing requested by Employer | J11: Not part of wastewater/sewer BOQ | K11: Provisional Qty | L11: Fusion-welded HDPE selected provisionally to minimise leakage risk inside the building.
A12: C2 | B12: C - Courtyard first-floor slab crossing | C12: Provide rigid supports and protective service kerb/tray/chase to rainwater carrier pipe across the first-floor slab, including galvanized/stainless brackets, vibration/isolation pads where required, removable access covers or concrete protection where exposed to traffic, maintaining drainage fall and full maintainability. | D12: m | E12: 35 | F12: 10000 | G12: =E12*F12 -> 350000 | H12: Engineer interface/protection allowance | I12: First-floor slab crossing | J12: General structural slab excluded | K12: Provisional Qty | L12: Do not bury inaccessible joints beneath permanent finishes without approved access strategy.
A13: C3 | B13: C - Courtyard first-floor slab crossing | C13: Supply and install external/downward continuation of courtyard rainwater line in heavy-duty HDPE/uPVC, provisional 160 mm diameter, from first-floor crossing discharge point to ground-level surface drain, complete with brackets at approved centres, offsets/bends, expansion allowance and weather-resistant fixing. | D13: m | E13: 12 | F13: 12000 | G13: =E13*F13 -> 144000 | H13: Engineer specialist installed allowance | I13: Courtyard discharge riser/downpipe | J13: External surface drain itself remains in Site Works BOQ | K13: Provisional Qty | L13: Final routing to minimize façade impact and allow maintenance.
A14: C4 | B14: C - Courtyard first-floor slab crossing | C14: Inspection/cleanout access points to enclosed courtyard rainwater system, including removable bolted/rodding access fitting and access panel where concealed, complete. | D14: No | E14: 4 | F14: 35000 | G14: =E14*F14 -> 140000 | H14: Engineer maintenance allowance | I14: At changes of direction and before/after building crossing | J14: No duplication | K14: Provisional Qty | L14: Locations to be accessible without entering sterile operating rooms where practicable.
A15: C5 | B15: C - Courtyard first-floor slab crossing | C15: Core openings/sleeves through walls/parapets for rainwater carrier pipes, including puddle flange/waterproof collar where exposed to weather, approved fire/acoustic seal where crossing rated construction, non-shrink making good and hygiene sealing. | D15: No | E15: 4 | F15: 50000 | G15: =E15*F15 -> 200000 | H15: Engineer interface allowance | I15: Building-crossing penetrations | J15: General wall finishes excluded | K15: Provisional Qty | L15: No structural beam/slab cutting without Structural Engineer approval.
A16: D1 | B16: D - General roof rainwater items | C16: Supply and fix 100 mm square PVC eaves gutter or approved equivalent, complete with brackets, joints, end caps and fittings. | D16: m | E16: 0 | F16: 3000 | G16: =E16*F16 -> 0 | H16: Matara BSR 2026 PB82 series benchmark | I16: Matara BSR 2026 | J16: Ancillary roof schedule R.08-R.12 now governs gutters/downpipes/tie-ins | K16: REMOVED - covered by Ancillary Roof BOQ | L16: Zeroed in consolidated estimate to avoid duplication.
... A21: E2 | B21: E - Testing & handover | C21: As-built rainwater disposal drawings with pipe sizes, invert/fall data, outlet/overflow locations, cleanout/access schedule and maintenance instructions; include photographs of concealed slab-crossing work before covering. | D21: LS | E21: 1 | F21: 200000 | G21: =E21*F21 -> 200000 | H21: Engineer deliverables allowance | I21: Project handover requirement | J21: No duplication | K21: Provisional | L21: Include emergency-overflow maintenance notes.
F24: BOQ Subtotal | G24: =SUM(G5:G21) -> 3479000

Sheet Rainwater Reconciliation
A1: RAINWATER DISPOSAL – SCOPE RECONCILIATION WITH MATARA BOQ PACKAGES
A3: Scope Element | B3: Existing Package / Source | C3: Treatment in Rainwater BOQ | D3: Reason | E3: Boundary / Interface | F3: Duplication Risk | G3: Current Allowance | H3: Action Before Tender
A4: Existing/new external surface drains | B4: Site Works - Unchanged, Section D | C4: EXCLUDED except final pipe/catchpit tie-in | D4: External drain cleaning/construction and covers are already priced | E4: Rainwater BOQ terminates at connection into existing/new surface drain | F4: High | G4: 3 tie-ins | H4: Confirm discharge points and capacities.
A5: Sanitary wastewater/sewer pipes | B5: Wastewater & Sewerage BOQ | C5: EXCLUDED | D5: Foul drainage must remain separate from stormwater/rainwater | E5: No cross-connection permitted | F5: High | G5: Nil | H5: Confirm final SW/WW drawing legend and route separation.
A6: MVAC condensate drains | B6: MVAC BOQ D4 | C6: EXCLUDED | D6: HVAC condensate is already measured | E6: Any discharge into storm system to be coordinated once | F6: Medium | G6: Nil | H6: Identify final condensate discharge interface.
A7: Courtyard floor/screed finishes | B7: Added Renovation BOQ | C7: ONLY rainwater-specific regrading screed included | D7: Positive falls are critical to courtyard drainage performance | E7: Final decorative/architectural finishes remain in renovation scope | F7: Medium | G7: 100 m² provisional | H7: Coordinate final finish build-up and threshold levels.
A8: Courtyard waterproofing | B8: Not otherwise specifically measured for courtyard | C8: INCLUDED as dedicated high-risk rainwater item | D8: Courtyard and slab-crossing arrangement creates significant leakage risk | E8: Includes outlet/upstand detailing and pond test | F8: Low/Medium | G8: 100 m² provisional | H8: Confirm membrane system and substrate condition.
A9: First-floor slab crossing | B9: User/Employer instruction | C9: INCLUDED as dedicated fusion-welded enclosed carrier route | D9: This is the critical project-specific rainwater diversion requirement | E9: From courtyard outlet to external building face | F9: Low | G9: 35 m provisional | H9: Prepare profile drawing with exact falls and access points.
A10: Structural modifications | B10: Structural design / renovation works | C10: EXCLUDED except non-structural sleeves/core holes | D10: No beam/slab cutting should be assumed in plumbing rate | E10: Any structural opening/support requires Engineer approval | F10: High | G10: Nil | H10: Route below/over slab avoiding beams wherever possible.
A11: Emergency overflow | B11: Not present in other packages | C11: INCLUDED | D11: Courtyard blockage must not flood clinical/OT areas | E11: Independent discharge externally | F11: Low | G11: 2 No | H11: Set overflow level below vulnerable door thresholds.
A12: Roof gutters/downpipes | B12: No dedicated rainwater package previously | C12: EXCLUDED from Rainwater package; measured in reviewed Ancillary Roof schedule | D12: Ancillary R.08-R.12 now provide gutter, downpipe and stormwater connection scope | E12: Discharge to existing external surface drainage | F12: Low/Medium | G12: Nil in Rainwater BOQ | H12: Retain only courtyard-specific drainage in Rainwater package; verify ancillary roof quantities.
A13: Rainwater harvesting/storage | B13: No requirement provided | C13: NOT INCLUDED | D13: User requested disposal/diversion rather than storage/reuse | E13: N/A | F13: Low | G13: Nil | H13: Add only if Employer later requires harvesting.

Sheet Rainwater Rates & Basis
A1: RAINWATER DISPOSAL ENGINEER'S ESTIMATE – RATE BASIS / DESIGN ASSUMPTIONS
A3: Ref | B3: Item / Application | C3: Unit | D3: Applied Rate (LKR) | E3: Rate Type | F3: Basis | G3: Source / URL | H3: Quotation Needed | I3: Confidence | J3: Qualification
A4: RW-R01 | B4: 100 mm square PVC eaves gutter | C4: m | D4: 3000 | E4: BSR-based qualified rate | F4: Matara BSR 2026 PB82 series; floor-level/floor-specific rates approx. LKR 2,600/m around the published schedule | G4: https://www.cs.sp.gov.lk/css/csw/rates/bsr_matara_2026.pdf | H4: No | I4: Medium/High | J4: Rounded up for renovation coordination and minor fittings.
A5: RW-R02 | B5: 90 mm PVC rainwater downpipe | C5: m | D5: 2700 | E5: BSR-based qualified rate | F5: Matara BSR 2026 PB83 = LKR 2,390/m and PB83a first-floor = LKR 2,460/m; rounded for project allowance | G5: https://www.cs.sp.gov.lk/css/csw/rates/bsr_matara_2026.pdf | H5: No | I5: High | J5: Use exact floor-specific rate after final routing.
A6: RW-R03 | B6: Gutter heads/end caps/mitres | C6: No | D6: 6000 | E6: BSR/Engineer composite allowance | F6: Matara BSR 2026 PB85-PB87 provide separate accessory rates; composite budget allowance used | G6: https://www.cs.sp.gov.lk/css/csw/rates/bsr_matara_2026.pdf | H6: No | I6: Medium | J6: Final fitting type/count to roof layout.
A7: RW-R04 | B7: 160 mm fusion-welded HDPE rainwater carrier across building | C7: m | D7: 15000 | E7: Engineer specialist market allowance | F7: PE100 fusion-welded internal stormwater carrier, fittings, fusion joints, anchors/expansion provision and installation | G7: Specialist contractor quotation required | H7: Yes – minimum 3 quotes | I7: Low/Medium | J7: Final diameter may increase after hydraulic calculation.
A8: RW-R05 | B8: Protective support/service kerb or tray to first-floor crossing | C8: m | D8: 10000 | E8: Engineer interface allowance | F8: Heavy-duty supports plus accessible protection to pipe routed across/over occupied building slab | G8: Detailed structural/architectural coordination required | H8: Recommended | I8: Low/Medium | J8: Final build-up depends on route and whether exposed to foot/trolley traffic.
A9: RW-R06 | B9: Heavy-duty courtyard rainwater outlet 150 mm | C9: No | D9: 85000 | E9: Engineer specialist allowance | F9: SS outlet with clamping flange, leaf guard/silt basket, waterproofing-compatible detail | G9: Specialist supplier quotation required | H9: Yes | I9: Low/Medium | J9: Critical waterproofing interface.
A10: RW-R07 | B10: Courtyard linear channel drain | C10: m | D10: 28000 | E10: Engineer specialist allowance | F10: Heavy-duty channel, removable grating, bedding/haunch and outlet connection | G10: Specialist supplier / civil rate build-up | H10: Yes | I10: Low/Medium | J10: Final section/cover class to courtyard use.
A11: RW-R08 | B11: Courtyard waterproofing membrane | C11: m² | D11: 4500 | E11: Engineer refurbishment allowance | F11: Flexible membrane with reinforced corners/upstands and outlet detailing; includes pond test allowance | G11: Approved waterproofing contractor quotation recommended | H11: Recommended | I11: Medium | J11: Final rate varies by membrane system.
A12: RW-R09 | B12: Emergency overflow/scupper | C12: No | D12: 60000 | E12: Engineer flood-resilience allowance | F12: Independent external overflow with sleeve, weathering and discharge piece | G12: Specialist/fabricated item | H12: Recommended | I12: Medium | J12: Final size by overflow calculation.
A15: KEY DESIGN / QUANTITY ASSUMPTIONS
A16: 1 | B16: The courtyard is treated as a critical catchment because its rainwater must cross the building over/across the first-floor slab before reaching an external discharge point.
A17: 2 | B17: A fully closed fusion-welded HDPE carrier is budgeted for the internal building crossing to reduce joint leakage risk. Final material may be altered by the Engineer after detailed design.
A18: 3 | B18: A continuous positive fall is mandatory through the first-floor crossing. Final route shall be shown in profile with invert levels and shall avoid structural beams and inaccessible clinical/OT areas wherever practicable.
A19: 4 | B19: At least two independent primary courtyard collection points plus independent emergency overflow are allowed. Hydraulic capacity must be confirmed using the final courtyard/roof catchment area and approved design rainfall intensity.
A20: 5 | B20: The estimate includes provisional 100 m² courtyard regrading/waterproofing, 20 m linear channel, 35 m internal carrier pipe and 12 m external continuation; all quantities require final measured takeoff.
A21: 6 | B21: Existing/new external surface drains remain in the Site Works package. Only rainwater pipe tie-ins are included here, avoiding double-counting.
A22: 7 | B22: Sanitary wastewater and sewerage systems remain completely separate and are excluded from this storm/rainwater package.
A23: 8 | B23: No rainwater harvesting tank or reuse system is included.
A24: 9 | B24: All rates and totals are exclusive of VAT. Specialist courtyard drainage/HDPE/waterproofing rates should be confirmed by current quotations before tender issue.

Sheet Electrical BOQ - Reviewed
A1: DISTRICT GENERAL HOSPITAL MATARA – ELECTRICAL BOQ REVIEWED FOR CONSOLIDATION
A2: Source: uploaded legacy Excel electrical BOQ (subtotal LKR 21,039,600). Quantities have been reviewed against the Modular OT and MVAC packages. Only clearly identifiable overlaps are deducted; upstream UPS distribution and general electrical infrastructure are retained.
A4: Source Row | B4: Item | C4: Description | D4: Unit | E4: Source Qty | F4: Rate (LKR) | G4: Source Amount | H4: Duplicate Qty | I4: Duplicate Amount | J4: Reviewed Qty | K4: Reviewed Amount | L4: Overlap / Reason | M4: Action | N4: Confidence | O4: Remarks
A5: 28 | B5: 1 | C5: Main Distribution Board (MDB) | D5: No | E5: 1 | F5: 970000 | G5: 970000 | H5: 0 | I5: 0 | J5: 1 | K5: 970000 | M5: RETAIN | N5: High
A6: 51 | C6: DB - GF - 1 | D6: No | E6: 1 | F6: 220000 | G6: 220000 | H6: 0 | I6: 0 | J6: 1 | K6: 220000 | M6: RETAIN | N6: High
A7: 67 | B7: 2.1 | C7: DB - GF - 2 | D7: No | E7: 1 | F7: 235000 | G7: 235000 | H7: 0 | I7: 0 | J7: 1 | K7: 235000 | M7: RETAIN | N7: High
A8: 82 | B8: 2.2 | C8: DB - GF - 3 | D8: No | E8: 1 | F8: 235000 | G8: 235000 | H8: 0 | I8: 0 | J8: 1 | K8: 235000 | M8: RETAIN | N8: High
A9: 95 | B9: 2.3 | C9: DB - OT1 - U | D9: No | E9: 1 | F9: 140000 | G9: 140000 | H9: 0 | I9: 0 | J9: 1 | K9: 140000 | L9: OT UPS distribution boards retained: treated as upstream UPS distribution, distinct from Modular OT medical IT/IPS isolated power boards. | M9: RETAIN | N9: Medium | O9: Confirm final SLD/interface before tender.
A10: 108 | B10: 2.4 | C10: DB - OT2 - U | D10: No | E10: 1 | F10: 140000 | G10: 140000 | H10: 0 | I10: 0 | J10: 1 | K10: 140000 | L10: OT UPS distribution boards retained: treated as upstream UPS distribution, distinct from Modular OT medical IT/IPS isolated power boards. | M10: RETAIN | N10: Medium | O10: Confirm final SLD/interface before tender.
A11: 121 | B11: 2.5 | C11: DB - ORT1 - U | D11: No | E11: 1 | F11: 140000 | G11: 140000 | H11: 0 | I11: 0 | J11: 1 | K11: 140000 | L11: OT UPS distribution boards retained: treated as upstream UPS distribution, distinct from Modular OT medical IT/IPS isolated power boards. | M11: RETAIN | N11: Medium | O11: Confirm final SLD/interface before tender.
A12: 134 | B12: 2.6 | C12: DB - ORT2 - U | D12: No | E12: 1 | F12: 145000 | G12: 145000 | H12: 0 | I12: 0 | J12: 1 | K12: 145000 | L12: OT UPS distribution boards retained: treated as upstream UPS distribution, distinct from Modular OT medical IT/IPS isolated power boards. | M12: RETAIN | N12: Medium | O12: Confirm final SLD/interface before tender.
A13: 147 | B13: 2.7 | C13: DB - MG | D13: No | E13: 1 | F13: 140000 | G13: 140000 | H13: 0 | I13: 0 | J13: 1 | K13: 140000 | M13: RETAIN | N13: High
A14: 158 | B14: 2.8 | C14: DB - AC | D14: No | E14: 1 | F14: 735000 | G14: 735000 | H14: 0 | I14: 0 | J14: 1 | K14: 735000 | L14: AC/MVAC power distribution retained in Electrical BOQ. MVAC E2 has been reduced to local equipment/control interfaces only. | M14: RETAIN | N14: High
A15: 192 | B15: 3.1 | C15: 95 mm² 4C,AL / PVC (ABC) from Hospital Incommer DB to MDB | D15: m | E15: 120 | F15: 15000 | G15: 1800000 | H15: 0 | I15: 0 | J15: 120 | K15: 1800000 | M15: RETAIN | N15: High
A16: 194 | B16: 3.2 | C16: 35 mm2 Cu/PVC Green & Yellow Earth cable from MDB to Earth electrode. | D16: m | E16: 15 | F16: 5500 | G16: 82500 | H16: 0 | I16: 0 | J16: 15 | K16: 82500 | M16: RETAIN | N16: High
A17: 196 | B17: 3.4 | C17: 10mm2, 1C x 4 , Cu/PVC/PVC + 10mm2 Cu/PVC Earth cable from MDB to DB-GF-1 | D17: m | E17: 55 | F17: 6500 | G17: 357500 | H17: 0 | I17: 0 | J17: 55 | K17: 357500 | M17: RETAIN | N17: High
A18: 198 | B18: 3.4 | C18: 10mm2, 1C x 4 , Cu/PVC/PVC + 10mm2 Cu/PVC Earth cable from MDB to DB-GF-2 | D18: m | E18: 40 | F18: 6500 | G18: 260000 | H18: 0 | I18: 0 | J18: 40 | K18: 260000 | M18: RETAIN | N18: High
A19: 200 | B19: 3.5 | C19: 10mm2, 1C x 4 , Cu/PVC/PVC + 10mm2 Cu/PVC Earth cable from MDB to DB-GF-3 | D19: m | E19: 20 | F19: 6500 | G19: 130000 | H19: 0 | I19: 0 | J19: 20 | K19: 130000 | M19: RETAIN | N19: High
A20: 202 | B20: 3.6 | C20: 10mm2, 1C x 2 , Cu/PVC/PVC + 10mm2 Cu/PVC Earth cable from MDB to DB-OT1-U | D20: m | E20: 50 | F20: 4500 | G20: 225000 | H20: 0 | I20: 0 | J20: 50 | K20: 225000 | M20: RETAIN | N20: High
A21: 204 | B21: 3.7 | C21: 10mm2, 1C x 2 , Cu/PVC/PVC + 10mm2 Cu/PVC Earth cable from MDB to DB-OT2-U | D21: m | E21: 30 | F21: 4500 | G21: 135000 | H21: 0 | I21: 0 | J21: 30 | K21: 135000 | M21: RETAIN | N21: High
A22: 206 | B22: 3.8 | C22: 10mm2, 1C x 2 , Cu/PVC/PVC + 10mm2 Cu/PVC Earth cable from MDB to DB-ORT1-U | D22: m | E22: 12 | F22: 4500 | G22: 54000 | H22: 0 | I22: 0 | J22: 12 | K22: 54000 | M22: RETAIN | N22: High
A23: 208 | B23: 3.9 | C23: 10mm2, 1C x 2 , Cu/PVC/PVC + 10mm2 Cu/PVC Earth cable from MDB to DB-ORT2-U | D23: m | E23: 14 | F23: 4500 | G23: 63000 | H23: 0 | I23: 0 | J23: 14 | K23: 63000 | M23: RETAIN | N23: High
A24: 210 | B24: 3.1-1 | C24: 10mm2, 1C x 4 , Cu/PVC/PVC + 10mm2 Cu/PVC Earth cable from MDB to DB-MG | D24: m | E24: 25 | F24: 6500 | G24: 162500 | H24: 0 | I24: 0 | J24: 25 | K24: 162500 | M24: RETAIN | N24: High
A25: 212 | B25: 3.1-2 | C25: 70mm2, 1C x 4 , Cu/XLPE/PVC + 35mm2 Cu/PVC Earth cable from MDB to DB-AC | D25: m | E25: 5 | F25: 35000 | G25: 175000 | H25: 0 | I25: 0 | J25: 5 | K25: 175000 | L25: AC/MVAC power distribution retained in Electrical BOQ. MVAC E2 has been reduced to local equipment/control interfaces only. | M25: RETAIN | N25: High
A26: 214 | B26: 3.1-3 | C26: 10mm2, 1C x 4 , Cu/PVC/PVC + 10mm2 Cu/PVC Earth cable from MDB to DB-FIRE | D26: m | E26: 20 | F26: 6500 | G26: 130000 | H26: 0 | I26: 0 | J26: 20 | K26: 130000 | M26: RETAIN | N26: High
A27: 218 | B27: 4.1 | C27: 50mm2, 1C x 4 , Cu/XLPE/PVC + 25mm2 Cu/PVC Earth cable from DB-AC to CHILLER ROOM Isolator | D27: m | E27: 20 | F27: 25000 | G27: 500000 | H27: 0 | I27: 0 | J27: 20 | K27: 500000 | L27: AC/MVAC power distribution retained in Electrical BOQ. MVAC E2 has been reduced to local equipment/control interfaces only. | M27: RETAIN | N27: High
A28: 220 | B28: 4.2 | C28: 16mm2, 1C x 4 , Cu/PVC/PVC + 16mm2 Cu/PVC Earth cable from DB-AC to AHU ROOM1 Isolator | D28: m | E28: 5 | F28: 8500 | G28: 42500 | H28: 0 | I28: 0 | J28: 5 | K28: 42500 | L28: AC/MVAC power distribution retained in Electrical BOQ. MVAC E2 has been reduced to local equipment/control interfaces only. | M28: RETAIN | N28: High
A29: 222 | B29: 4.3 | C29: 16mm2, 1C x 4 , Cu/PVC/PVC + 16mm2 Cu/PVC Earth cable from DB-AC to AHU ROOM2 Isolator | D29: m | E29: 30 | F29: 8500 | G29: 255000 | H29: 0 | I29: 0 | J29: 30 | K29: 255000 | L29: AC/MVAC power distribution retained in Electrical BOQ. MVAC E2 has been reduced to local equipment/control interfaces only. | M29: RETAIN | N29: High
A30: 224 | B30: 4.4 | C30: 2.5mm2, 1C x 4 , Cu/PVC/PVC + 2.5mm2 Cu/PVC Earth cable from DB-AC to COOLING TOWER Isolator | D30: m | E30: 10 | F30: 2000 | G30: 20000 | H30: 0 | I30: 0 | J30: 10 | K30: 20000 | L30: AC/MVAC power distribution retained in Electrical BOQ. MVAC E2 has been reduced to local equipment/control interfaces only. | M30: RETAIN | N30: High
A31: 226 | B31: 4.5 | C31: 2.5mm2, 1C x 4 , Cu/PVC/PVC + 2.5mm2 Cu/PVC Earth cable from DB-AC to SEMI STERILE CORRIDOR | D31: m | E31: 10 | F31: 2000 | G31: 20000 | H31: 0 | I31: 0 | J31: 10 | K31: 20000 | L31: AC/MVAC power distribution retained in Electrical BOQ. MVAC E2 has been reduced to local equipment/control interfaces only. | M31: RETAIN | N31: High
A32: 228 | B32: 4.6 | C32: 2.5mm2, 1C x 4 , Cu/PVC/PVC + 2.5mm2 Cu/PVC Earth cable from DB-AC to RECOVERY AREA 1 | D32: m | E32: 10 | F32: 2000 | G32: 20000 | H32: 0 | I32: 0 | J32: 10 | K32: 20000 | L32: AC/MVAC power distribution retained in Electrical BOQ. MVAC E2 has been reduced to local equipment/control interfaces only. | M32: RETAIN | N32: High
A33: 230 | B33: 4.7 | C33: 2.5mm2, 1C x 4 , Cu/PVC/PVC + 2.5mm2 Cu/PVC Earth cable from DB-AC to RECOVERY AREA 2 | D33: m | E33: 10 | F33: 2000 | G33: 20000 | H33: 0 | I33: 0 | J33: 10 | K33: 20000 | L33: AC/MVAC power distribution retained in Electrical BOQ. MVAC E2 has been reduced to local equipment/control interfaces only. | M33: RETAIN | N33: High
A34: 232 | B34: 4.8 | C34: 2.5mm2, 1C x 4 , Cu/PVC/PVC + 2.5mm2 Cu/PVC Earth cable from DB-AC to FAN COIL UNIT | D34: m | E34: 10 | F34: 2000 | G34: 20000 | H34: 0 | I34: 0 | J34: 10 | K34: 20000 | L34: AC/MVAC power distribution retained in Electrical BOQ. MVAC E2 has been reduced to local equipment/control interfaces only. | M34: RETAIN | N34: High
A35: 234 | B35: 9 | C35: Cable Tray | D35: Pro. Sum | G35: 800000 | H35: 0 | I35: 0 | K35: 800000 | M35: RETAIN | N35: High
A36: 246 | C36: Wiring of a light point from the respective Distribution Board using 1mm2 Cu/PVC/PVC cables drawn through concealed PVC conduits/PVC casing or as applicable, controlled by a 10A flush switch. | D36: No | E36: 177 | F36: 10500 | G36: 1858500 | H36: 40 | I36: 420000 | J36: 137 | K36: 1438500 | L36: 40 OT general/cleanroom lighting points already included with Modular OT C6 and modular final lighting connections. | M36: REDUCE | N36: Medium/High | O36: Reviewed qty = 177 - 40 = 137.
A37: 260 | B37: 10.3 | C37: Type 1 | D37: No | E37: 75 | F37: 16500 | G37: 1237500 | H37: 40 | I37: 660000 | J37: 35 | K37: 577500 | L37: 40 OT cleanroom luminaires already included in Modular OT C6. | M37: REDUCE | N37: Medium/High | O37: Generic Type 1 fittings reduced by Modular OT quantity.
A38: 263 | B38: 10.4 | C38: Type 2 | D38: No | E38: 7 | F38: 10500 | G38: 73500 | H38: 0 | I38: 0 | J38: 7 | K38: 73500 | M38: RETAIN | N38: High
A39: 266 | B39: 10.5 | C39: Down light-Type 1 | D39: No | E39: 47 | F39: 7500 | G39: 352500 | H39: 0 | I39: 0 | J39: 47 | K39: 352500 | M39: RETAIN | N39: High
A40: 269 | B40: 10.6 | C40: Down light-Type 2 | D40: No | E40: 28 | F40: 11300 | G40: 316400 | H40: 0 | I40: 0 | J40: 28 | K40: 316400 | M40: RETAIN | N40: High
A41: 272 | B41: 10.7 | C41: Wall Lamp-Type 1 | D41: No | E41: 14 | F41: 8500 | G41: 119000 | H41: 0 | I41: 0 | J41: 14 | K41: 119000 | M41: RETAIN | N41: High
A42: 275 | B42: 10.8 | C42: Wall Lamp-Type 2 | D42: No | E42: 6 | F42: 9500 | G42: 57000 | H42: 0 | I42: 0 | J42: 6 | K42: 57000 | M42: RETAIN | N42: High
A43: 280 | C43: Wiring of a ceiling fan from the respective Distribution Board using 1mm2 Cu/PVC/PVC cable and 2.5 mm2 Cu/PVC earth wire drawn through concealed PVC conduits, controlled by a regulator and 10A switch. | D43: No | E43: 6 | F43: 11500 | G43: 69000 | H43: 0 | I43: 0 | J43: 6 | K43: 69000 | M43: RETAIN | N43: High
A44: 283 | C44: Supply and installation of 1400 mm sweep diameter ceiling fan complete with regulator, fan hook, extension rod and all other accessories required. Guarantee cards shall be provided from accredited agent and approved by the Engineer before placing the order. (Recommended brands are KDK, Panasonic) | D44: No | E44: 6 | F44: 35000 | G44: 210000 | H44: 0 | I44: 0 | J44: 6 | K44: 210000 | M44: RETAIN | N44: High
A45: 287 | C45: Wiring (including supply of all material required ) of 13A socket outlets using approved type 2.5 mm2 Cu/PVC/PVC, 2C cable & 2.5 mm2 earth cable drawn through securely fixed concealed PVC conduit / PVC trunking. (Radial circuit). | D45: No | E45: 212 | F45: 13500 | G45: 2862000 | H45: 80 | I45: 1080000 | J45: 132 | K45: 1782000 | L45: 16 Modular OT power socket boxes x 5 sockets = 80 sockets; modular specification also includes final OT subcircuits. | M45: REDUCE | N45: High | O45: Reviewed qty = 212 - 80 = 132.
A46: 289 | B46: 11.1 | C46: 13A Socket outlets | D46: No | E46: 212 | F46: 1850 | G46: 392200 | H46: 80 | I46: 148000 | J46: 132 | K46: 244200 | L46: 80 individual 13A outlets are already embodied in the 16 Modular OT power socket boxes. | M46: REDUCE | N46: High | O46: Reviewed qty = 132.
A47: 293 | B47: 12 | C47: Un-interrupted Power supply Systems (UPS) | D47: No | E47: 4 | F47: 1250000 | G47: 5000000 | H47: 0 | I47: 0 | J47: 4 | K47: 5000000 | L47: 4 x 8 kVA UPS retained: Modular OT requires UPS/emergency interface but does not separately price central UPS units. | M47: RETAIN | N47: Medium/High
A48: 302 | C48: Supply and Installation of an earth electrode of minimum 10mm dia. solid copper rod of length 1.2m or more with a clamp connection to earth conductor. Earth resistance shall be less than 10 Ohms tested on a dry day. An earth pit of size 300mm x 300mm x 200mm is to be prepared and covered by removable concrete plate to protect the earth electrode. | D48: Item | G48: 40000 | H48: 0 | I48: 0 | K48: 40000 | M48: RETAIN | N48: High
A49: 306 | C49: Testing the installation and rectify any defects and submit a certificate by a Chartered Electrical Engineer. | D49: Item | G49: 80000 | H49: 0 | I49: 0 | K49: 80000 | L49: General electrical inspection/testing retained; specialist OT validation remains under Modular OT. | M49: RETAIN | N49: High
F52: Source BOQ subtotal | K52: =SUM(G5:G49) -> 21039600
F53: Identified duplicate deductions | K53: =SUM(I5:I49) -> 2308000
F54: Reviewed direct electrical subtotal | K54: =SUM(K5:K49) -> 18731600
F55: Design-development contingency | K55: 0.1
F56: Contingency Amount | K56: =K54*K55 -> 1873160
F57: Engineer’s Estimate excl. VAT | K57: =K54+K56 -> 20604760
F58: VAT | K58: Excluded

Sheet Electrical Reconciliation
A1: ELECTRICAL / MODULAR OT / MVAC – SCOPE RECONCILIATION
A3: Scope Element | B3: Source Electrical BOQ | C3: Other Package | D3: Consolidated Treatment | E3: Deduction / Adjustment | F3: Reason | G3: Risk | H3: Tender Action
